Workbook
Name a: #REF!
Name a: #REF!
Name a: #REF!
Name Columns: #REF!
Name Columns: #REF!
Name Columns: #REF!
Name EBIT: #REF!
Name EBIT: #REF!
Name IQ_CH: 110000
Name IQ_CQ: 5000
Name IQ_CY: 10000
Name IQ_DAILY: 500000
Name IQ_FH: 100000
Name IQ_FQ: 500
Name IQ_FY: 1000
Name IQ_LTM: 2000
Name IQ_MONTH: 15000
Name IQ_NTM: 6000
Name IQ_WEEK: 50000
Name IQ_YTD: 3000
Name languageinput: #REF!
Name languageinput: #REF!
Name languageinput: #REF!
Name Tradings: #REF!
Name Tradings: #REF!
Name Tradings: #REF!

Sheet __FDSCACHE__
B1: This sheet contains Factset binary data for use with this workbook's =FDS codes. Modifying the worksheet's contents may damage the workbook's =FDS functionality.

Sheet Project Omega
D8: Project Omega
D10: Trading Multiples Analysis

Sheet __APW_ACTIVE_FIELD_RESTORE__

Sheet LinkingMetadata

Sheet CIQ_LinkingNames
A1: CIQANR_d9b112d924bd4db49d6c8ba0418839e5 | B1: 45447.393

Sheet Financials_hard coded
B2: Financials (EURm)
E7: Local | F7: Exchange | H7: Market cap | I7: Bridge | J7: EV | L7: Sales (EURm) | Q7: EBITDA (EURm) | V7: EBIT (EURm) | AA7: Net income (EURm)
B8: Ticker | C8: Companies | E8: currency | F8: rate | H8: (EURm) | I8: (EURm) | J8: (EURm) | L8: 45291 | M8: 45657 | N8: 46022 | O8: 46387 | Q8: 45291 | R8: 45657 | S8: 46022 | T8: 46387 | V8: 45291 | W8: 45657 | X8: 46022 | Y8: 46387 | AA8: 45291 | AB8: 45657 | AC8: 46022 | AD8: 46387 | AF8: EBITDA Margin | AG8: EBIT Margin
L9: FY2023 | M9: FY2024 | N9: FY2025 | O9: FY2026 | Q9: FY2023 | R9: FY2024 | S9: FY2025 | T9: FY2026 | V9: FY2023 | W9: FY2024 | X9: FY2025 | Y9: FY2026
B10: OM:ALFA | C10: Alfa Laval AB | E10: SEK | F10: 0.08753 | H10: 17554.591 | I10: ='Equity Bridge (simple)'!M10 -> 0 | J10: =+I10+H10 -> 17554.591 | L10: 5721.2828 | M10: 6121.1208 | N10: 6451.8569 | O10: 6724.2899 | Q10: 996.48809 | R10: 1176.45 | S10: 1260.234 | T10: 1333.8341 | V10: 823.58477 | W10: 1001.1347 | X10: 1083.5158 | Y10: 1148.4025 | AA10: 569.44747 | AB10: 712.71129 | AC10: 780.55911 | AD10: 837.64371 | AF10: =Q10/L10*100 -> 17.417214 | AG10: =V10/L10*100 -> 14.395107
B11: OTCCH:001268465 | C11: Bobst Group SA | E11: CHF | F11: 1.02055 | H11: 965.96212 | I11: ='Equity Bridge (simple)'!M11 -> 130.22218 | J11: =+I11+H11 -> 1096.1843 | L11: 2106.1247 | M11: na | N11: na | O11: na | Q11: 188.87759 | R11: na | S11: na | T11: na | V11: 160.83603 | W11: na | X11: na | Y11: na | AA11: 127.52997 | AB11: na | AC11: na | AD11: na | AF11: =Q11/L11*100 -> 8.9680153 | AG11: =V11/L11*100 -> 7.6365861
B12: TSE:6407 | C12: CKD Corp. | E12: JPY | F12: 0.00587 | H12: 1198.2796 | I12: ='Equity Bridge (simple)'!M12 -> -64.29998 | J12: =+I12+H12 -> 1133.9796 | L12: 1104.0383 | M12: 823.7563 | N12: 888.99308 | O12: 1003.5588 | Q12: 192.45912 | R12: 117.85602 | S12: 154.3711 | T12: 199.78372 | V12: 146.58244 | W12: 75.61277 | X12: 107.69959 | Y12: 145.05312 | AA12: 102.38822 | AB12: 0 | AC12: 0 | AD12: 0 | AF12: =Q12/L12*100 -> 17.432286 | AG12: =V12/L12*100 -> 13.276934
B13: XTRA:DEZ | C13: Deutz AG | E13: EUR | F13: 1 | H13: 658.48836 | I13: ='Equity Bridge (simple)'!M13 -> 0 | J13: =+I13+H13 -> 658.48836 | L13: 2063.2 | M13: 2008.3 | N13: 2304.9 | O13: 2443.8 | Q13: 188.7 | R13: 209.7 | S13: 246.3731 | T13: 277.16052 | V13: 132.6 | W13: 116.68 | X13: 150.9 | Y13: 180.8 | AA13: 81.9 | AB13: 89.32 | AC13: 112.66 | AD13: 135.475 | AF13: =Q13/L13*100 -> 9.1459868 | AG13: =V13/L13*100 -> 6.4269097
B14: TSE:6141 | C14: DMG Mori co. | E14: JPY | F14: 0.00587 | H14: 3706.0245 | I14: ='Equity Bridge (simple)'!M14 -> 0 | J14: =+I14+H14 -> 3706.0245 | L14: 3462.2128 | M14: 3249.4363 | N14: 3464.2849 | O14: 3633.4336 | Q14: 495.52419 | R14: 515.75528 | S14: 581.58679 | T14: 633.22166 | V14: 325.33055 | W14: 343.63902 | X14: 400.39287 | Y14: 445.05408 | AA14: 217.85402 | AB14: na | AC14: na | AD14: na | AF14: =Q14/L14*100 -> 14.312355 | AG14: =V14/L14*100 -> 9.3966077
B15: XTRA:DUE | C15: Dürr AG | E15: EUR | F15: 1 | H15: 1622.0968 | I15: ='Equity Bridge (simple)'!M15 -> 0 | J15: =+I15+H15 -> 1622.0968 | L15: 4627.334 | M15: 4830.7766 | N15: 4997.0693 | O15: 5198.3644 | Q15: 285.604 | R15: 389.79815 | S15: 456.07663 | T15: 485.37016 | V15: 205.624 | W15: 265.01667 | X15: 322.65 | Y15: 373.75 | AA15: 111.981 | AB15: 153.90883 | AC15: 198.2509 | AD15: 228.11065 | AF15: =Q15/L15*100 -> 6.1721069 | AG15: =V15/L15*100 -> 4.4436818
B16: XTRA:G1A | C16: Gea Group AG | E16: EUR | F16: 1 | H16: 6441.47 | I16: ='Equity Bridge (simple)'!M16 -> 643.612 | J16: =+I16+H16 -> 7085.082 | L16: 5373.491 | M16: 5468.9982 | N16: 5630.3151 | O16: 5844.2816 | Q16: 597.081 | R16: 801.93084 | S16: 834.56619 | T16: 877.03472 | V16: 512.521 | W16: 618.12173 | X16: 647.99194 | Y16: 666.66304 | AA16: 392.765 | AB16: 439.89013 | AC16: 462.76394 | AD16: 496.33208 | AF16: =Q16/L16*100 -> 11.111603 | AG16: =V16/L16*100 -> 9.5379521
B17: XTRA:KRN | C17: Krones AG | E17: EUR | F17: 1 | H17: 3980.7271 | I17: ='Equity Bridge (simple)'!M17 -> -68.334 | J17: =+I17+H17 -> 3912.3931 | L17: 4765.479 | M17: 5290.9195 | N17: 5676.1437 | O17: 5953.1904 | Q17: 463.434 | R17: 537.39476 | S17: 616.51451 | T17: 672.20381 | V17: 315.669 | W17: 375.14707 | X17: 454.74651 | Y17: 506.79624 | AA17: 224.511 | AB17: 276.40599 | AC17: 335.53172 | AD17: 373.22502 | AF17: =Q17/L17*100 -> 9.7248147 | AG17: =V17/L17*100 -> 6.624077
B21: Stock prices and consensus estimates as of current
B22: Date | C22: current
B23: Currency | C23: EUR
B28: Peer Selection Criteria
B30: 1. Industry & Segment | D30: Companies operating in the packaging machinery, engineering, or industrial machinery sectors.
B31: 2. Product Overlap | D31: Companies manufacturing similar types of machinery and equipment, particularly: Packaging machinery (filling, sealing, wrapping, etc.), focused on food, beverage, and dairy industries. Providers of integrated systems or after-sales services.
B32: 3. Geography | D32: Companies with a strong presence in Europe (Omega's core market), but also consider global players with significant operations or sales in regions where Omega is expanding (e.g., North America, Asia-Pacific).
B33: 4. Size | D33: Companies with comparable financial metrics, factor 2x: Revenue within 0.5x to 2.0x of Omega’s EUR 325.5m revenue (approximately EUR 160m–650m range). Market Capitalization: Within a reasonable range around Omega.
B34: 5. Profitability Metrics | D34: Companies with EBIT/EBITDA margins in a range comparable to Omega's current and forecast margins (~5%-8% EBITDA; ~3,3%-6% EBIT margins).
B35: 6. Market Trends | D35: Companies exposed to similar market trends, such as: Growing demand for packaging machinery; for automation; for eco-friendly and efficient packaging solutions.
B37: Peer Selection Outcome
C38: Company | D38: Alignment Score
B39: OM:ALFA | C39: Alfa Laval AB | D39: =SUM(I51:I56)&" / 6" -> 1 / 6 | E39: 1
B40: OTCCH:001268465 | C40: Bobst Group SA | D40: =SUM(I59:I64)&" / 6" -> 5 / 6 | E40: 1 | F40: -> Included
B41: TSE:6407 | C41: CKD Corp. | D41: =SUM(I67:I72)&" / 6" -> 4 / 6 | E41: 1 | F41: -> Included
B42: XTRA:DEZ | C42: Deutz AG | D42: =SUM(I75:I80)&" / 6" -> 2 / 6 | E42: 1
B43: TSE:6141 | C43: DMG Mori co. | D43: =SUM(I75:I80)&" / 6" -> 2 / 6 | E43: 1
B44: XTRA:DUE | C44: Dürr AG | D44: =SUM(I91:I96)&" / 6" -> 3 / 6 | E44: 1
B45: XTRA:G1A | C45: Gea Group AG | D45: =SUM(I99:I104)&" / 6" -> 4 / 6 | E45: 1 | F45: -> Included
B46: XTRA:KRN | C46: Krones AG | D46: =SUM(I107:I112)&" / 6" -> 4 / 6 | E46: 1 | F46: -> Included
B48: Peer Justification:
B50: Alfa Laval AB | D50: Outcome for Alfa Laval | I50: Met Criteria?
B51: Industry & Segment | D51: No overlap with packaging machinery | I51: 0
B52: Product Overlap | D52: No alignment with packaging machinery (heat exchange) | I52: 0
B53: Geography | D53: Strong presence in Europe and globally | I53: 1
B54: Size | D54: Revenue far exceeds range (EUR 160M–650M) | I54: 0
B55: Profitability Metrics | D55: EBITDA margin (18.5%) in 2023; exceed range | I55: 0
B56: Market Trends | D56: Unrelated (exposed to energy efficiency, water treatment) | I56: 0
B58: Bobst Group SA | D58: Outcome for Bobst Group SA | I58: Met Criteria?
B59: Industry & Segment | D59: Strong overlap with packaging machinery, focused on printing and converting | I59: 1
B60: Product Overlap | D60: Partial overlap with complementary but not identical products | I60: 1
B61: Geography | D61: Strong presence in Europe and globally | I61: 1
B62: Size | D62: Revenue exceeds range | I62: 0
B63: Profitability Metrics | D63: EBITDA margin ~9% comparable with Omega's range | I63: 1
B64: Market Trends | D64: Exposed to eco-friendly solutions, and flexible packaging trends | I64: 1
B66: CKD Corp. | D66: Outcome for CKD Corp. | I66: Met Criteria?
B67: Industry & Segment | D67: Align with the packaging machinery. | I67: 1
B68: Product Overlap | D68: Partly, focusing more on packaging of pharmaceutical products | I68: 1
B69: Geography | D69: CKD Corporation has a significant presence in Japan and operates extensively in overseas markets, including North America, Europe, China, and Southeast Asia. | I69: 1
B70: Size | D70: For FY2024, CKD reported net sales of ¥134,425 million (approx. EUR 880 million) | I70: 0
B71: Profitability Metrics | D71: Much higher than Omega's range | I71: 0
B72: Market Trends | D72: Growing demand for automation in manufacturing and efficiency improvements | I72: 1
B74: Deutz AG | D74: Outcome for Deutz AG | I74: Met Criteria?
B75: Industry & Segment | D75: Manufacturing engines for construction, agriculture, and material handling applications. | I75: 0
B76: Product Overlap | D76: No alignment with packaging machinery (engines) | I76: 0
B77: Geography | D77: Strong presence in Europe, Americas, and Asia-Pacific | I77: 1
B78: Size | D78: Revenue of EUR 1.72B, 4x Omega's revenue | I78: 0
B79: Profitability Metrics | D79: EBITDA margin of 13%, higher than Omega's | I79: 0
B80: Market Trends | D80: Exposure to eco-friendly and sustainable solutions | I80: 1
B82: DMG Mori co. | D82: Outcome for DMG Mori co. | I82: Met Criteria?
B83: Industry & Segment | D83: No overlap: focuses on turning, milling, and additive manufacturing. | I83: 0
B84: Product Overlap | D84: No overlap | I84: 0
B85: Geography | D85: Strong international presence, including in Europe | I85: 1
B86: Size | D86: Sales revenue of EUR 2,498.6 million (in 2023) is well above | I86: 0
B87: Profitability Metrics | D87: EBIT margin higher than Omega|s range | I87: 0
B88: Market Trends | D88: Trends are more specific to the industrial machinery and tools | I88: 0
B90: Dürr AG | D90: Outcome for Dürr AG | I90: Met Criteria?
B91: Industry & Segment | D91: Solutions for painting, assembly, and clean technologies to sectors like automotive | I91: 0
B92: Product Overlap | D92: Limited overlap with packaging machinery applications for automation | I92: 0
B93: Geography | D93: Strong presence in Europe and expanding in global markets like Asia-Pacific. | I93: 1
B94: Size | D94: Significantly larger than Omega in terms of revenue (€4.63 billion) | I94: 0
B95: Profitability Metrics | D95: EBIT margin 4.0% is comparable to Omega’s | I95: 1
B96: Market Trends | D96: Aligns with growth market trends in automation, eco-friendly solutions. | I96: 1
B98: Gea Group AG | D98: Outcome for Gea Group AG | I98: Met Criteria?
B99: Industry & Segment | D99: Operates in relevant machinery sectors, aligned with Omega's focus. | I99: 1
B100: Product Overlap | D100: Focuses on food processing equipment but not specifically packaging. | I100: 1
B101: Geography | D101: Strong presence in Europe and global operations | I101: 1
B102: Size | D102: GEA's EUR 5.4 billion revenue far exceeds Omega's range | I102: 0
B103: Profitability Metrics | D103: GEA's 11% EBITDA margin is much higher | I103: 0
B104: Market Trends | D104: Aligns with trends for eco-friendly and efficient solutions. | I104: 1
B106: Krones AG | D106: Outcome for Krones AG | I106: Met Criteria?
B107: Industry & Segment | D107: Operates in the packaging machinery sector, aligning with Omega’s focus on packaging machinery for the food, beverage, and dairy industries. | I107: 1
B108: Product Overlap | D108: Manufactures filling, sealing, and packaging systems for the beverage and food | I108: 1
B109: Geography | D109: Krones has a strong European presence, with extensive operations across the globe, particularly in North America and Asia-Pacific | I109: 1
B110: Size | D110: Krones' revenue in 2023 is EUR 4.7 billion | I110: 0
B111: Profitability Metrics | D111: EBITDA margin 9,7% is higher | I111: 0
B112: Market Trends | D112: Operates in the same trends as Omega, such as demand for eco-friendly packaging solutions, automation, and increasing demand for packaging machinery. | I112: 1

Sheet Equity Bridge (simple)
B2: Equity Bridge
E7: Local | F7: Exchange | I7: Net debt/(net cash) | J7: Pensions | K7: Minorities | M7: Sum
C8: Companies | E8: currency | F8: rate | I8: (EURm) | J8: (EURm) | K8: (EURm) | M8: (EURm)
C10: Alfa Laval AB | E10: =+'Financials_hard coded'!E10 -> SEK | F10: =+'Financials_hard coded'!F10 -> 0.08753
C11: Bobst Group SA | E11: =+'Financials_hard coded'!E11 -> CHF | F11: =+'Financials_hard coded'!F11 -> 1.02055 | I11: =('BS Bobst'!J31+'BS Bobst'!J37-'BS Bobst'!J22)*F11 -> 136.54959 | J11: =('BS Bobst'!J33+'BS Bobst'!J39-'BS Bobst'!J11)*F11 -> -8.062345 | K11: ='BS Bobst'!J29*F11 -> 1.734935 | M11: =+SUM(I11:K11) -> 130.22218
C12: CKD Corp. | E12: =+'Financials_hard coded'!E12 -> JPY | F12: =+'Financials_hard coded'!F12 -> 0.00587 | I12: =('BS CKD'!K49+'BS CKD'!K50+'BS CKD'!K51+'BS CKD'!K61+'BS CKD'!K62-'BS CKD'!K9)*F12 -> -58.36541 | J12: =('BS CKD'!K65+'BS CKD'!K66-'BS CKD'!K35)*F12 -> -5.93457 | K12: 0 | M12: =+SUM(I12:K12) -> -64.29998
C13: Deutz AG | E13: =+'Financials_hard coded'!E13 -> EUR | F13: =+'Financials_hard coded'!F13 -> 1
C14: DMG Mori co. | E14: =+'Financials_hard coded'!E14 -> JPY | F14: =+'Financials_hard coded'!F14 -> 0.00587
C15: Dürr AG | E15: =+'Financials_hard coded'!E15 -> EUR | F15: =+'Financials_hard coded'!F15 -> 1
C16: Gea Group AG | E16: =+'Financials_hard coded'!E16 -> EUR | F16: =+'Financials_hard coded'!F16 -> 1 | I16: =('BS GEA'!L44+'BS GEA'!L53-'BS GEA'!L24)*F16 -> -282.872 | J16: =('BS GEA'!L43+'BS GEA'!L52)*F16 -> 926.072 | K16: ='BS GEA'!L39*'Equity Bridge (simple)'!F16 -> 0.412 | M16: =+SUM(I16:K16) -> 643.612
C17: Krones AG | E17: =+'Financials_hard coded'!E17 -> EUR | F17: =+'Financials_hard coded'!F17 -> 1 | I17: =('BS Krones'!N50+'BS Krones'!N57+'BS Krones'!N52+'BS Krones'!N61-'BS Krones'!N25)*F17 -> -247.24 | J17: ='BS Krones'!N46*'Equity Bridge (simple)'!F17 -> 178.444 | K17: ='BS Krones'!N43*F17 -> 0.462 | M17: =+SUM(I17:K17) -> -68.334

Sheet Equity Bridge
B2: Equity Bridge
E7: Local | F7: Exchange | I7: Net (debt)/net cash | J7: Pensions | K7: Minorities | M7: Sum
C8: Companies | E8: currency | F8: rate | I8: (EURm) | J8: (EURm) | K8: (EURm) | M8: (EURm)
C10: Alfa Laval AB | E10: =+'Financials_hard coded'!E10 -> SEK | F10: =+'Financials_hard coded'!F10 -> 0.08753 | I10: =+(#REF!+#REF!+#REF!+#REF!-#REF!-#REF!-#REF!-#REF!-#REF!-#REF!)*F10 -> #REF! | J10: =+(-#REF!+#REF!)*F10 -> #REF! | K10: =345*F10 -> 30.19785 | M10: =+SUM(I10:K10) -> #REF!
C11: Bobst Group SA | E11: =+'Financials_hard coded'!E11 -> CHF | F11: =+'Financials_hard coded'!F11 -> 1.02055 | I11: =+(#REF!+#REF!+#REF!+#REF!+#REF!+#REF!+#REF!+#REF!-#REF!-#REF!-#REF!)*F11 -> #REF! | J11: =+(-#REF!-#REF!+#REF!)*F11 -> #REF! | K11: =1.7*F11 -> 1.734935 | M11: =+SUM(I11:K11) -> #REF!
C12: CKD Corp. | E12: =+'Financials_hard coded'!E12 -> JPY | F12: =+'Financials_hard coded'!F12 -> 0.00587 | I12: =+(#REF!+#REF!-#REF!-#REF!-#REF!)*F12 -> #REF! | J12: =+(-#REF!-#REF!+#REF!)*F12 -> #REF! | K12: 0 | M12: =+SUM(I12:K12) -> #REF!
C13: Deutz AG | E13: =+'Financials_hard coded'!E13 -> EUR | F13: =+'Financials_hard coded'!F13 -> 1 | I13: =+(#REF!+#REF!+#REF!-#REF!-#REF!-#REF!+#REF!-#REF!) -> #REF! | J13: =+(-#REF!-#REF!) -> #REF! | K13: 0 | M13: =+SUM(I13:K13) -> #REF!
C14: DMG Mori co. | E14: =+'Financials_hard coded'!E14 -> JPY | F14: =+'Financials_hard coded'!F14 -> 0.00587 | I14: =+(#REF!+#REF!+#REF!+#REF!+#REF!+#REF!+#REF!-#REF!-#REF!-#REF!-#REF!-#REF!) -> #REF! | J14: =+(-#REF!) -> #REF! | K14: 20.223 | M14: =+SUM(I14:K14) -> #REF!
C15: Dürr AG | E15: =+'Financials_hard coded'!E15 -> EUR | F15: =+'Financials_hard coded'!F15 -> 1 | I15: =+(#REF!+#REF!+#REF!+#REF!+#REF!+#REF!+#REF!-#REF!-#REF!-#REF!-#REF!-#REF!-#REF!-#REF!) -> #REF! | J15: =+(-#REF!) -> #REF! | K15: 7.071 | M15: =+SUM(I15:K15) -> #REF!
C16: Gea Group AG | E16: =+'Financials_hard coded'!E16 -> EUR | F16: =+'Financials_hard coded'!F16 -> 1 | I16: =+(#REF!+#REF!+#REF!+#REF!+#REF!-#REF!-#REF!-#REF!) -> #REF! | J16: =+(-#REF!-#REF!) -> #REF! | K16: 0.412 | M16: =+SUM(I16:K16) -> #REF!
C17: Krones AG | E17: =+'Financials_hard coded'!E17 -> EUR | F17: =+'Financials_hard coded'!F17 -> 1 | I17: =+(#REF!+#REF!+#REF!+#REF!-#REF!-#REF!-#REF!-#REF!) -> #REF! | J17: =+(-#REF!) -> #REF! | K17: 0.462 | M17: =+SUM(I17:K17) -> #REF!

Sheet _CIQHiddenCacheSheet
A1: 94 | B1: AwABTANFVVIBSP////8BUG8BAAAaQ0lRLlRTRTo2MTQxLklRX05JLi4uLi5FVVIBAAAA0FwNAAIAAAAKMTE2LDM0NzM4NQEIAAAABQAAAAExAQAAAAstMTk5Mzk2NzMwMgMAAAACNTACAAAAAjE1BAAAAAEwBwAAAAg2LzUvMjAyNAgAAAAJMy8zMS8yMDI0CQAAAAEwYEHcdnqF3AjQHVR0NobcCC1DSVEuRU5YVFBBOk1DLklRX0VCSVREQV9FU1RfQ0lRLkZZMjAyNC4uLi5FVVIBAAAAoPsCAAIAAAALMjk0MzIsNjQ0NDQBDgAAAAUAAAABMwEAAAABMAIAAAAKMTAwMTc2MzA4MwMAAAAGMTAwMTg3BAAAAAEzBgAAAAEwBwAAAAI1MAgAAAABMAkAAAABMQoAAAABMAsAAAALMTM4MDcwNzYwMjAMAAAAATENAAAACDYvNi8yMDI0EAAAAAg2LzUvMjAyNPFWudJ5hdwIoub30nmF3AgrQ0lRLk9UQ0NIOjAwMTI2ODQ2NS5JUV9FQklUREEuRlkyMDIzLi4uLkVVUgEAAAB+WQ0AAgAAAAoxODgsODc3NTg2AQgAAAAFAAAAATEBAAAACy0yMDA4MzIyMzE5AwAAAAI1MAIAAAAENDA1MQQAAAABMAcAAAAINi82LzIwMjQIAAAACjEyLzMxLzIwMjMJAAAAATD6xQR0NobcCLH/WHQ2htwILkNJUS5FTlhUUEE6RlIuSVFfUkVWRU5VRV9FU1RfQ0lRLkZZMjAyMy4uLi5FVVIBAAAAhoAKAAIAAAALMjIxNDYsNDM0NzkBDgAAAAUAAAABMwEAAAABMAIAAAAKMTAwMjA5OTcwOAMAAAAGMTAwMTgwBAAAAAEzBgAAAAEwBwAAAAI1MAgA | C1: AAABMAkAAAABMQoAAAABMAsAAAALMTM2Njk0MDM2OTkMAAAAATENAAAACDYvNi8yMDI0EAAAAAoxMi8zMS8yMDIz8Va50nmF3Agrg/jSeYXcCCtDSVEuTllTRTpBUFRWLklRX0VCSVRfRVNUX0NJUS5GWTIwMjQuLi4uRVVSAQAAAFTviwMCAAAAEDIyODIsNjEyMDg5MzU5MzUBDgAAAAUAAAABMwEAAAABMAIAAAAKMTAwMzM2ODA0NgMAAAAGMTAwMjE1BAAAAAEyBgAAAAEwBwAAAAI1MAgAAAABMAkAAAABMQoAAAABMAsAAAALMTM3OTgwNjcwNzIMAAAAATENAAAACDYvNi8yMDI0EAAAAAg2LzUvMjAyNPQvudJ5hdwIHFz40nmF3AgtQ0lRLkVOWFRQQTpGUi5JUV9FQklUREFfRVNUX0NJUS5GWTIwMjQuLi4uRVVSAQAAAIaACgACAAAACjI4MzMsMjQ1OTkBDgAAAAUAAAABMwEAAAABMAIAAAAKMTAwMjM1ODE5NQMAAAAGMTAwMTg3BAAAAAEzBgAAAAEwBwAAAAI1MAgAAAABMAkAAAABMQoAAAABMAsAAAALMTM4MDc4NDE4NjAMAAAAATENAAAACDYvNi8yMDI0EAAAAAg2LzUvMjAyNPFWudJ5hdwIw3H30nmF3AgkQ0lRLlhUUkE6RFVFLklRX0VCSVRfRVNUX0NJUS4uLi4uRVVSAQAAALRzDQACAAAABzI3OSw0MjUBDgAAAAUAAAACMTEBAAAAATACAAAACDU3NDc2NTQzAwAAAAYxMDAyMTUEAAAAATMGAAAAATAHAAAAAjUwCAAAAAEwCQAAAAExCgAAAAEwCwAAAAsxMzgwODI0MTM4NQwAAAACMTINAAAACDYvNi8y | D1: MDI0EAAAAAg2LzUvMjAyNDXWj7p5hdwIm/ZTdDaG3AgtQ0lRLlhUUkE6Qk1XLklRX1JFVkVOVUVfRVNUX0NJUS5GWTIwMjQuLi4uRVVSAQAAAHrACgACAAAADDE1ODEzNSw2NjI4NwEOAAAABQAAAAEzAQAAAAEwAgAAAAoxMDAxNTg3MTMyAwAAAAYxMDAxODAEAAAAATMGAAAAATAHAAAAAjUwCAAAAAEwCQAAAAExCgAAAAEwCwAAAAsxMzgwNzk2NjUzMwwAAAABMQ0AAAAINi82LzIwMjQQAAAACDYvNS8yMDI09C+50nmF3AiX0fjSeYXcCChDSVEuWFRSQTpCTVcuSVFfTUFSS0VUQ0FQLjMxLjA1LjIwMjMuRVVSAQAAAHrACgACAAAACzY0OTk0LDQ3NzA4AQYAAAAFAAAAATEBAAAACy0yMDQ3MjM1NjYxAwAAAAI1MAIAAAAGMTAwMDU0BAAAAAEwBwAAAAk1LzMxLzIwMjMsCbnSeYXcCNW/99J5hdwILENJUS5UU0U6Njc3MC5JUV9FQklUREFfRVNUX0NJUS5GWTIwMjUuLi4uRVVSAQAAAE9YDQACAAAAEDM0MCw0ODc5NjYzNzYyMjkBDgAAAAUAAAABMwEAAAABMAIAAAAKMTAwMTk3MTYzNAMAAAAGMTAwMTg3BAAAAAI1NgYAAAABMAcAAAACNTAIAAAAATAJAAAAATEKAAAAATALAAAACzEzODA4NzIyODg3DAAAAAExDQAAAAg2LzYvMjAyNBAAAAAINi81LzIwMjT0L7nSeYXcCNW/99J5hdwIKUNJUS5YVFJBOkRVRS5JUV9OSV9FU1RfTk9URS5GWTIwMjYuLi4uRVVSAQAAALRzDQADAAAAT0luY2x1ZGVzIEFtb3J0 | E1: aXphdGlvbiBvZiBJbnRhbmdpYmxlIEFzc2V0cyBhbmQgU3RvY2sgQmFzZWQgQ29tcGVuc2F0aW9uIEV4cGVuc2UA/j0tK3qF3AgciTgreoXcCCJDSVEuWFRSQTpLUk4uSVFfRUJJVC5GWTIwMjMuLi4uRVVSAQAAAMFhDQACAAAABzMxNSw2NjkBCAAAAAUAAAABMQEAAAALLTIwMDUwODcwMDQDAAAAAjUwAgAAAAM0MDAEAAAAATAHAAAACDYvNi8yMDI0CAAAAAoxMi8zMS8yMDIzCQAAAAEw+sUEdDaG3Aj1TVl0NobcCCFDSVEuT006QUxGQS5JUV9FQklULkZZMjAyMy4uLi5FVVIBAAAAOGgGAAIAAAAJODIzLDU4NDc3AQgAAAAFAAAAATEBAAAACy0yMDA0MTc1MDY4AwAAAAI1MAIAAAADNDAwBAAAAAEwBwAAAAg2LzYvMjAyNAgAAAAKMTIvMzEvMjAyMwkAAAABMPrFBHQ2htwI9U1ZdDaG3AgnQ0lRLlhUUkE6RFVFLklRX1JFVkVOVUVfRVNUX0NJUS4uLi4uRVVSAQAAALRzDQACAAAACTQ4NzIsMzQ5OAEOAAAABQAAAAIxMQEAAAABMAIAAAAINTc0NzY1NDMDAAAABjEwMDE4MAQAAAABMwYAAAABMAcAAAACNTAIAAAAATAJAAAAATEKAAAAATALAAAACzEzODA4MjQxMzc3DAAAAAIxMg0AAAAINi83LzIwMjQQAAAACDYvNi8yMDI0Vtk4dTaG3AhW2Th1NobcCCpDSVEuVFNFOjYxNDEuSVFfRUJJVF9FU1RfQ0lRLkZZMjAyNC4uLi5FVVIBAAAA0FwNAAIAAAAQMzQxLDE3MDUwNDkwNTg5MgEOAAAABQAAAAEzAQAA | F1: AAEwAgAAAAoxMDAzNzU5NTczAwAAAAYxMDAyMTUEAAAAATMGAAAAATAHAAAAAjUwCAAAAAEwCQAAAAExCgAAAAEwCwAAAAsxMzc1ODI1MTIyNQwAAAABMQ0AAAAINi83LzIwMjQQAAAACDYvNi8yMDI0cewEdDaG3AiVJll0NobcCCBDSVEuT006QUxGQS5JUV9SRVYuRlkyMDIzLi4uLkVVUgEAAAA4aAYAAgAAAAs1NzIxLDI4MjgyMQEIAAAABQAAAAExAQAAAAstMjAwNDE3NTA2OAMAAAACNTACAAAAAzExMgQAAAABMAcAAAAINi82LzIwMjQIAAAACjEyLzMxLzIwMjMJAAAAATD6xQR0NobcCEvjRnU2htwIJ0NJUS4kRVVSRVVSLklRX0xBU1RTQUxFUFJJQ0UuMzEuMDUuMjAyMwEAAAC461oAAgAAAAExAPQvudJ5hdwIK4P40nmF3AgkQ0lRLlRTRTo2MTQxLklRX0VCSVRfRVNUX0NJUS4uLi4uRVVSAQAAANBcDQACAAAAEDM1Nyw4Mjc0ODM1MjgyMDcBDgAAAAUAAAACMTEBAAAAATACAAAABzM4MDY2MDUDAAAABjEwMDIxNQQAAAABMwYAAAABMAcAAAACNTAIAAAAATAJAAAAATEKAAAAATALAAAACzEzNzU4MjUxNDIzDAAAAAIxMg0AAAAINi82LzIwMjQQAAAACDYvNS8yMDI0NdaPunmF3AjSRFR0NobcCC1DSVEuTllTRTpBUFRWLklRX0VCSVREQV9FU1RfQ0lRLkZZMjAyMy4uLi5FVVIBAAAAVO+LAwIAAAAQMjUxNiw0Mjc5MTgwNTU1MgEOAAAABQAAAAEzAQAAAAEwAgAAAAoxMDAzMzY4MDQ1AwAAAAYxMDAx | G1: ODcEAAAAATIGAAAAATAHAAAAAjUwCAAAAAEwCQAAAAExCgAAAAEwCwAAAAsxMzYzMTEzNzQwNQwAAAABMQ0AAAAINi82LzIwMjQQAAAACjEyLzMxLzIwMjP0L7nSeYXcCBxc+NJ5hdwIMENJUS5PVENDSDowMDEyNjg0NjUuSVFfTklfRVNUX05PVEUuRlkyMDI2Li4uLkVVUgEAAAB+WQ0AAwAAAAAAd4xNKHqF3AhUAlcoeoXcCC5DSVEuTllTRTpBUFRWLklRX1JFVkVOVUVfRVNUX0NJUS5GWTIwMjUuLi4uRVVSAQAAAFTviwMCAAAAEDIwOTEyLDQ3ODY3NDc2NTgBDgAAAAUAAAABMwEAAAABMAIAAAAKMTAwMzM2ODA0NwMAAAAGMTAwMTgwBAAAAAEyBgAAAAEwBwAAAAI1MAgAAAABMAkAAAABMQoAAAABMAsAAAALMTM3OTgwNjY5ODgMAAAAATENAAAACDYvNi8yMDI0EAAAAAg2LzUvMjAyNPQvudJ5hdwI6Kr40nmF3AgtQ0lRLlhUUkE6REVaLklRX1JFVkVOVUVfRVNUX0NJUS5GWTIwMjYuLi4uRVVSAQAAAFZwCQACAAAABjI0NDMsOAEOAAAABQAAAAEzAQAAAAEwAgAAAAoxMDAzNjY0MzczAwAAAAYxMDAxODAEAAAAATMGAAAAATAHAAAAAjUwCAAAAAEwCQAAAAExCgAAAAEwCwAAAAsxMzc1NjE3MzAzMQwAAAABMQ0AAAAINi83LzIwMjQQAAAACDYvNi8yMDI0cewEdDaG3AjCMUd1NobcCCxDSVEuVFNFOjYxNDEuSVFfRUJJVERBX0VTVF9DSVEuRlkyMDI0Li4uLkVVUgEAAADQXA0AAgAAABA1MTIsMDUwMzc3 | H1: ODI5Mzk1AQ4AAAAFAAAAATMBAAAAATACAAAACjEwMDM3NTk1NzMDAAAABjEwMDE4NwQAAAABMwYAAAABMAcAAAACNTAIAAAAATAJAAAAATEKAAAAATALAAAACzEzNzU3MDkxNTAyDAAAAAExDQAAAAg2LzcvMjAyNBAAAAAINi82LzIwMjRx7AR0NobcCEhYR3U2htwIJENJUS5YVFJBOkcxQS5JUV9OSV9FU1QuRlkyMDI2Li4uLkVVUgEAAAAyVw0AAgAAAAk0OTYsMzMyMDgBDgAAAAUAAAABMwEAAAABMAIAAAAKMTAwMTU0ODA4OQMAAAAGMTAwMjUwBAAAAAEzBgAAAAEwBwAAAAI1MAgAAAABMAkAAAABMQoAAAABMAsAAAALMTM3OTQyMzg3MDQMAAAAATENAAAACDYvNy8yMDI0EAAAAAg2LzYvMjAyNDgTBXQ2htwI3RVYdDaG3AgpQ0lRLlRTRTo2MTQxLklRX05JX0VTVF9OT1RFLkZZMjAyNS4uLi5FVVIBAAAA0FwNAAMAAAAAAP49LSt6hdwIHIk4K3qF3AgcQ0lRLlhUUkE6RFVFLklRX0VCSVQuLi4uLkVVUgEAAAC0cw0AAgAAAAcyMDcsNzM2AQgAAAAFAAAAATEBAAAACy0xOTk0NDcxNjQyAwAAAAI1MAIAAAADNDAwBAAAAAEwBwAAAAg2LzUvMjAyNAgAAAAJMy8zMS8yMDI0CQAAAAEwYEHcdnqF3AiMz1N0NobcCBtDSVEuWFRSQTpERVouSVFfUkVWLi4uLi5FVVIBAAAAVnAJAAIAAAAGMjAxMCw5AQgAAAAFAAAAATEBAAAACy0xOTk3NTAwNDU2AwAAAAI1MAIAAAADMTEyBAAAAAEwBwAAAAg2LzYvMjAyNAgA | I1: AAAJMy8zMS8yMDI0CQAAAAEwZ7I4dTaG3Ahnsjh1NobcCCVDSVEuRU5YVFBBOk1DLklRX0VCSVRfRVNUX0NJUS4uLi4uRVVSAQAAAKD7AgACAAAACjI0MjI5LDkyMzUBDgAAAAUAAAACMTEBAAAAATACAAAACTQxMDU4MjA5NwMAAAAGMTAwMjE1BAAAAAEzBgAAAAEwBwAAAAI1MAgAAAABMAkAAAABMQoAAAABMAsAAAALMTM4MDcwNzY4NDkMAAAAAjEyDQAAAAg2LzYvMjAyNBAAAAAINi81LzIwMjRyez3TeYXcCHJ7PdN5hdwIJENJUS5YVFJBOkRVRS5JUV9FQklUREEuRlkyMDIzLi4uLkVVUgEAAAC0cw0AAgAAAAcyODUsNjA0AQgAAAAFAAAAATEBAAAACy0yMDA0MTQ5OTI3AwAAAAI1MAIAAAAENDA1MQQAAAABMAcAAAAINi82LzIwMjQIAAAACjEyLzMxLzIwMjMJAAAAATD6xQR0NobcCJUmWXQ2htwIIUNJUS5YVFJBOk1CRy5JUV9SRVYuRlkyMDIyLi4uLkVVUgEAAAAUoQEAAgAAAAYxMjMwNjMBCAAAAAUAAAABMQEAAAALLTIwMDU5OTUwMTQDAAAAAjUwAgAAAAMxMTIEAAAAATAHAAAACDYvNS8yMDI0CAAAAAoxMi8zMS8yMDIyCQAAAAEwLAm50nmF3AhP/PbSeYXcCClDSVEuVFNFOjY0MDcuSVFfTklfRVNUX05PVEUuRlkyMDI0Li4uLkVVUgEAAACXXQ0AAwAAAAAA/j0tK3qF3AgtsDgreoXcCC1DSVEuVFNFOjY3NzAuSVFfUkVWRU5VRV9FU1RfQ0lRLkZZMjAyMy4uLi5FVVIBAAAAT1gNAAIAAAAQNjI1 | J1: Nyw4NjY2Mjc2OTI4MwEOAAAABQAAAAEzAQAAAAEwAgAAAAoxMDAxOTcxNjI0AwAAAAYxMDAxODAEAAAAAjU2BgAAAAEwBwAAAAI1MAgAAAABMAkAAAABMQoAAAABMAsAAAALMTMzMDEzMjYzNTYMAAAAATENAAAACDYvNi8yMDI0EAAAAAkzLzMxLzIwMjP0L7nSeYXcCKLm99J5hdwIG0NJUS5UU0U6NjE0MS5JUV9SRVYuLi4uLkVVUgEAAADQXA0AAgAAAAszMzY0LDc3MTc3MQEIAAAABQAAAAExAQAAAAstMTk5Mzk2NzMwMgMAAAACNTACAAAAAzExMgQAAAABMAcAAAAINi82LzIwMjQIAAAACTMvMzEvMjAyNAkAAAABMGeyOHU2htwIZ7I4dTaG3AgWQ0lRLi5JUV9OSV9FU1QuLi4uLkVVUgUAAAAAAAAACAAAABQoSW52YWxpZCBJZGVudGlmaWVyKWBB3HZ6hdwI0ghVdDaG3AgsQ0lRLlhUUkE6S1JOLklRX0VCSVREQV9FU1RfQ0lRLkZZMjAyNi4uLi5FVVIBAAAAwWENAAIAAAAJNjcyLDIwMzgxAQ4AAAAFAAAAATMBAAAAATACAAAACjEwMDI2MDY1NDkDAAAABjEwMDE4NwQAAAABMwYAAAABMAcAAAACNTAIAAAAATAJAAAAATEKAAAAATALAAAACzEzNzk0OTgxMjMzDAAAAAExDQAAAAg2LzcvMjAyNBAAAAAINi82LzIwMjQ4EwV0NobcCNWmR3U2htwIKUNJUS5PVENDSDowMDEyNjg0NjUuSVFfRUJJVC5GWTIwMjMuLi4uRVVSAQAAAH5ZDQACAAAACjE2MCw4MzYwMzMBCAAAAAUAAAABMQEAAAALLTIwMDgzMjIz | K1: MTkDAAAAAjUwAgAAAAM0MDAEAAAAATAHAAAACDYvNi8yMDI0CAAAAAoxMi8zMS8yMDIzCQAAAAEw+sUEdDaG3Aj1TVl0NobcCCRDSVEuVFNFOjY5MDIuSVFfRUJJVERBLkZZMjAyMi4uLi5FVVIBAAAAPFYNAAIAAAALNTIwMCwzMjAwOTgBCAAAAAUAAAABMQEAAAALLTIwOTA4NzA5MzYDAAAAAjUwAgAAAAQ0MDUxBAAAAAEwBwAAAAg2LzUvMjAyNAgAAAAJMy8zMS8yMDIyCQAAAAEw9C+50nmF3AjSS/fSeYXcCClDSVEuRU5YVFBBOk1DLklRX01BUktFVENBUC4zMS4wNS4yMDIzLkVVUgEAAACg+wIAAgAAAA00MDc4MjYsNTIxNDY2AQYAAAAFAAAAATEBAAAACy0yMDYwNjUxMjIzAwAAAAI1MAIAAAAGMTAwMDU0BAAAAAEwBwAAAAk1LzMxLzIwMjMsCbnSeYXcCBxc+NJ5hdwIIUNJUS5UU1g6TE5SLklRX0VCSVQuRlkyMDIyLi4uLkVVUgEAAAB2Xw0AAgAAAAozOTAsNjcxNDQ3AQgAAAAFAAAAATEBAAAACy0yMDA0MTQ4NDEzAwAAAAI1MAIAAAADNDAwBAAAAAEwBwAAAAg2LzUvMjAyNAgAAAAKMTIvMzEvMjAyMgkAAAABMPQvudJ5hdwITW5D03mF3AgqQ0lRLlRTRTo2NDA3LklRX0VCSVRfRVNUX0NJUS5GWTIwMjYuLi4uRVVSAQAAAJddDQACAAAAEDE0NCwwMTExMzY1ODk1NTgBDgAAAAUAAAABMwEAAAABMAIAAAAKMTAwMzg5OTk5NAMAAAAGMTAwMjE1BAAAAAI1NgYAAAABMAcAAAACNTAIAAAAATAJAAAA | L1: ATEKAAAAATALAAAACzEzODAzMjE1NTM1DAAAAAExDQAAAAg2LzcvMjAyNBAAAAAINi82LzIwMjRx7AR0NobcCF7uV3Q2htwIKkNJUS5UU0U6NjE0MS5JUV9FQklUX0VTVF9DSVEuRlkyMDI2Li4uLkVVUgEAAADQXA0AAgAAABA0NDEsODU3MDUwNzE5MDA4AQ4AAAAFAAAAATMBAAAAATACAAAACjEwMDUzMTk5MzIDAAAABjEwMDIxNQQAAAABMwYAAAABMAcAAAACNTAIAAAAATAJAAAAATEKAAAAATALAAAACzEzNzU4MjUyNjA3DAAAAAExDQAAAAg2LzcvMjAyNBAAAAAINi82LzIwMjRx7AR0NobcCF7uV3Q2htwIIkNJUS5YVFJBOkcxQS5JUV9FQklULkZZMjAyMy4uLi5FVVIBAAAAMlcNAAIAAAAHNTEyLDUyMQEIAAAABQAAAAExAQAAAAstMjAwNzAzMzYzMgMAAAACNTACAAAAAzQwMAQAAAABMAcAAAAINi82LzIwMjQIAAAACjEyLzMxLzIwMjMJAAAAATD6xQR0NobcCPVNWXQ2htwIKUNJUS5YVFJBOkcxQS5JUV9OSV9FU1RfTk9URS5GWTIwMjUuLi4uRVVSAQAAADJXDQADAAAAKkluY2x1ZGVzIEFtb3J0aXphdGlvbiBvZiBJbnRhbmdpYmxlIEFzc2V0cwD+PS0reoXcCByJOCt6hdwILENJUS5YVFJBOk1CRy5JUV9FQklUREFfRVNUX0NJUS5GWTIwMjUuLi4uRVVSAQAAABShAQACAAAACzIzODY1LDI3NDg3AQ4AAAAFAAAAATMBAAAAATACAAAACjEwMDE2NTg3ODUDAAAABjEwMDE4NwQAAAABMwYAAAABMAcA | M1: AAACNTAIAAAAATAJAAAAATEKAAAAATALAAAACzEzODA2NjgzOTk4DAAAAAExDQAAAAg2LzYvMjAyNBAAAAAINi81LzIwMjT0L7nSeYXcCJfR+NJ5hdwIG0NJUS5YVFJBOkcxQS5JUV9SRVYuLi4uLkVVUgEAAAAyVw0AAgAAAAg1MzQzLDc4OAEIAAAABQAAAAExAQAAAAstMTk5NTcxNzg1NAMAAAACNTACAAAAAzExMgQAAAABMAcAAAAINi82LzIwMjQIAAAACTMvMzEvMjAyNAkAAAABMGeyOHU2htwIZ7I4dTaG3AgrQ0lRLk9NOkFMRkEuSVFfRUJJVERBX0VTVF9DSVEuRlkyMDI0Li4uLkVVUgEAAAA4aAYAAgAAABAxMTgxLDE4ODg5OTQzMTM4AQ4AAAAFAAAAATMBAAAAATACAAAACjEwMDExNjA1NTADAAAABjEwMDE4NwQAAAABMwYAAAABMAcAAAACNTAIAAAAATAJAAAAATEKAAAAATALAAAACzEzODAzMzE4NjI4DAAAAAExDQAAAAg2LzcvMjAyNBAAAAAINi82LzIwMjRx7AR0NobcCEvjRnU2htwIJUNJUS5PTTpBTEZBLklRX0VCSVREQV9FU1RfQ0lRLi4uLi5FVVIBAAAAOGgGAAIAAAAQMTI3NiwxNzczMzYwNDk1NwEOAAAABQAAAAIxMQEAAAABMAIAAAAIMjkzODU2NDkDAAAABjEwMDE4NwQAAAABMwYAAAABMAcAAAACNTAIAAAAATAJAAAAATEKAAAAATALAAAACzEzNzk5NTY0OTU2DAAAAAIxMg0AAAAINi83LzIwMjQQAAAACDYvNi8yMDI0Vtk4dTaG3AhW2Th1NobcCCtDSVEuT1RDQ0g6MDAxMjY4NDY1 | N1: LklRX05JX0VTVC5GWTIwMjQuLi4uRVVSAQAAAH5ZDQADAAAAAABx7AR0NobcCPVNWXQ2htwIKUNJUS5YVFJBOktSTi5JUV9OSV9FU1RfTk9URS5GWTIwMjQuLi4uRVVSAQAAAMFhDQADAAAAKkluY2x1ZGVzIEFtb3J0aXphdGlvbiBvZiBJbnRhbmdpYmxlIEFzc2V0cwD+PS0reoXcCC2wOCt6hdwIHkNJUS5UU0U6NjQwNy5JUV9OSV9FU1QuLi4uLkVVUgEAAACXXQ0AAwAAAAAAYEHcdnqF3Aj4uVR0NobcCCNDSVEuT006QUxGQS5JUV9FQklUREEuRlkyMDIzLi4uLkVVUgEAAAA4aAYAAgAAAAo5OTYsNDg4MDk0AQgAAAAFAAAAATEBAAAACy0yMDA0MTc1MDY4AwAAAAI1MAIAAAAENDA1MQQAAAABMAcAAAAINi82LzIwMjQIAAAACjEyLzMxLzIwMjMJAAAAATD6xQR0NobcCLH/WHQ2htwIIENJUS5UU1g6TE5SLklRX1JFVi5GWTIwMjIuLi4uRVVSAQAAAHZfDQACAAAACzU0NzQsMTI0MzEyAQgAAAAFAAAAATEBAAAACy0yMDA0MTQ4NDEzAwAAAAI1MAIAAAADMTEyBAAAAAEwBwAAAAg2LzUvMjAyNAgAAAAKMTIvMzEvMjAyMgkAAAABMPQvudJ5hdwIHFz40nmF3AgkQ0lRLlRTRTo2NzcwLklRX0VCSVREQS5GWTIwMjIuLi4uRVVSAQAAAE9YDQACAAAACjU5NCw5NTE1NjIBCAAAAAUAAAABMQEAAAALLTIwOTAzNDA4ODkDAAAAAjUwAgAAAAQ0MDUxBAAAAAEwBwAAAAg2LzUvMjAyNAgAAAAJMy8zMS8yMDIyCQAA | O1: AAEwLAm50nmF3AgcXPjSeYXcCClDSVEuVFNFOjY0MDcuSVFfTklfRVNUX05PVEUuRlkyMDI2Li4uLkVVUgEAAACXXQ0AAwAAAAAAMRctK3qF3AgtsDgreoXcCBpDSVEuWFRSQTpERVouSVFfTkkuLi4uLkVVUgEAAABWcAkAAgAAAAQ2Niw5AQgAAAAFAAAAATEBAAAACy0xOTk3NTAwNDU2AwAAAAI1MAIAAAACMTUEAAAAATAHAAAACDYvNS8yMDI0CAAAAAkzLzMxLzIwMjQJAAAAATBgQdx2eoXcCO1rVHQ2htwIM0NJUS5PVENDSDowMDEyNjg0NjUuSVFfRUJJVERBX0VTVF9DSVEuRlkyMDI1Li4uLkVVUgEAAAB+WQ0AAwAAAAAAcewEdDaG3AgxCkd1NobcCC5DSVEuRU5YVFBBOk1DLklRX1JFVkVOVUVfRVNUX0NJUS5GWTIwMjMuLi4uRVVSAQAAAKD7AgACAAAACzg1ODAwLDI5MjI4AQ4AAAAFAAAAATMBAAAAATACAAAACjEwMDE3NjMwODIDAAAABjEwMDE4MAQAAAABMwYAAAABMAcAAAACNTAIAAAAATAJAAAAATEKAAAAATALAAAACzEzNjMxODM3MDg5DAAAAAExDQAAAAg2LzYvMjAyNBAAAAAKMTIvMzEvMjAyM/FWudJ5hdwIeJj30nmF3AgtQ0lRLlRTRTo2NDA3LklRX1JFVkVOVUVfRVNUX0NJUS5GWTIwMjYuLi4uRVVSAQAAAJddDQACAAAAEDk5NiwzNDk3NDI1NTg4MzUBDgAAAAUAAAABMwEAAAABMAIAAAAKMTAwMzg5OTk5NAMAAAAGMTAwMTgwBAAAAAI1NgYAAAABMAcAAAACNTAIAAAAATAJAAAAATEK | P1: AAAAATALAAAACzEzODAzMjE1NTQxDAAAAAExDQAAAAg2LzcvMjAyNBAAAAAINi82LzIwMjRx7AR0NobcCMIxR3U2htwILENJUS5YVFJBOktSTi5JUV9FQklUREFfRVNUX0NJUS5GWTIwMjQuLi4uRVVSAQAAAMFhDQACAAAACTUzNywzOTQ3NgEOAAAABQAAAAEzAQAAAAEwAgAAAAoxMDAxNTgyMDE2AwAAAAYxMDAxODcEAAAAATMGAAAAATAHAAAAAjUwCAAAAAEwCQAAAAExCgAAAAEwCwAAAAsxMzc5NDk4MTM0NwwAAAABMQ0AAAAINi83LzIwMjQQAAAACDYvNi8yMDI0OBMFdDaG3AjVpkd1NobcCCpDSVEuVFNFOjY0MDcuSVFfRUJJVF9FU1RfQ0lRLkZZMjAyNC4uLi5FVVIBAAAAl10NAAIAAAAQNzUsNjEyNzY5OTI5MzA2MgEOAAAABQAAAAEzAQAAAAEwAgAAAAoxMDAzNzM2Mjg2AwAAAAYxMDAyMTUEAAAAAjU2BgAAAAEwBwAAAAI1MAgAAAABMAkAAAABMQoAAAABMAsAAAALMTM3MzE4Mjk2MjgMAAAAATENAAAACDYvNy8yMDI0EAAAAAkzLzMxLzIwMjRx7AR0NobcCJUmWXQ2htwIKUNJUS5PTTpBTEZBLklRX0VCSVRfRVNUX0NJUS5GWTIwMjYuLi4uRVVSAQAAADhoBgACAAAAEDExNTMsMDI4Mzc0MzU2MzEBDgAAAAUAAAABMwEAAAABMAIAAAAKMTAwMTE2MDU1MgMAAAAGMTAwMjE1BAAAAAEzBgAAAAEwBwAAAAI1MAgAAAABMAkAAAABMQoAAAABMAsAAAALMTM4MDMzMjAzODUMAAAAATENAAAACDYvNy8y | Q1: MDI0EAAAAAg2LzYvMjAyNHHsBHQ2htwImsdXdDaG3AglQ0lRLk5ZU0U6QVBUVi5JUV9FQklUREEuRlkyMDIyLi4uLkVVUgEAAABU74sDAgAAAAkxOTg3LDQyNjgBCAAAAAUAAAABMQEAAAALLTIwMTE0OTMwMDYDAAAAAjUwAgAAAAQ0MDUxBAAAAAEwBwAAAAg2LzUvMjAyNAgAAAAKMTIvMzEvMjAyMgkAAAABMCwJudJ5hdwIzg340nmF3AgaQ0lRLlhUUkE6S1JOLklRX05JLi4uLi5FVVIBAAAAwWENAAIAAAAHMjI2LDgxMQEIAAAABQAAAAExAQAAAAstMTk5NzA1NDY2MAMAAAACNTACAAAAAjE1BAAAAAEwBwAAAAg2LzUvMjAyNAgAAAAJMy8zMS8yMDI0CQAAAAEwYEHcdnqF3AhGDFN0NobcCCxDSVEuVFNYOkxOUi5JUV9SRVZFTlVFX0VTVF9DSVEuRlkyMDI1Li4uLkVVUgEAAAB2Xw0AAgAAABA3ODQyLDc5OTkyMTM0MzExAQ4AAAAFAAAAATMBAAAAATACAAAACjEwMDIzNzkzNDYDAAAABjEwMDE4MAQAAAABMwYAAAABMAcAAAACNTAIAAAAATAJAAAAATEKAAAAATALAAAACzEzODAwNzk1OTIzDAAAAAExDQAAAAg2LzYvMjAyNBAAAAAINi81LzIwMjTxVrnSeYXcCMNx99J5hdwIK0NJUS5FTlhUUEE6TUMuSVFfRUJJVF9FU1RfQ0lRLkZZMjAyNS4uLi5FVVIBAAAAoPsCAAIAAAALMjYwMTYsMDM1MjEBDgAAAAUAAAABMwEAAAABMAIAAAAKMTAwMTc2MzA4NAMAAAAGMTAwMjE1BAAAAAEzBgAAAAEwBwAAAAI1 | R1: MAgAAAABMAkAAAABMQoAAAABMAsAAAALMTM4MDcwNzU5NzgMAAAAATENAAAACDYvNi8yMDI0EAAAAAg2LzUvMjAyNPFWudJ5hdwIjLxD03mF3AgmQ0lRLk9NOkFMRkEuSVFfUkVWRU5VRV9FU1RfQ0lRLi4uLi5FVVIBAAAAOGgGAAIAAAAQNjQyNywxNTg2MzMwNjIxMQEOAAAABQAAAAIxMQEAAAABMAIAAAAIMjkzODU2NDkDAAAABjEwMDE4MAQAAAABMwYAAAABMAcAAAACNTAIAAAAATAJAAAAATEKAAAAATALAAAACzEzNzk5NTY0OTY4DAAAAAIxMg0AAAAINi83LzIwMjQQAAAACDYvNi8yMDI0Vtk4dTaG3AhW2Th1NobcCClDSVEuTllTRTpBUFRWLklRX01BUktFVENBUC4zMS4wNS4yMDIzLkVVUgEAAABU74sDAgAAABAyMjM1NiwxMjY3Nzc4Mjg4AQYAAAAFAAAAATEBAAAACy0yMDQ3MzE0NTM5AwAAAAI1MAIAAAAGMTAwMDU0BAAAAAEwBwAAAAk1LzMxLzIwMjMsCbnSeYXcCHiY99J5hdwIG0NJUS5UU0U6NjQwNy5JUV9SRVYuLi4uLkVVUgEAAACXXQ0AAgAAAAo4MjMsNzY0NzM0AQgAAAAFAAAAATEBAAAACy0xOTk1MjM2MjQwAwAAAAI1MAIAAAADMTEyBAAAAAEwBwAAAAg2LzYvMjAyNAgAAAAJMy8zMS8yMDI0CQAAAAEwZ7I4dTaG3Ahnsjh1NobcCCxDSVEuVFNFOjY5MDIuSVFfRUJJVERBX0VTVF9DSVEuRlkyMDIzLi4uLkVVUgEAAAA8Vg0AAgAAABA1MzYxLDQ1MTUzNzE1OTY2AQ4AAAAFAAAAATMB | S1: AAAAATACAAAACjEwMDI4ODU3MjADAAAABjEwMDE4NwQAAAABMwYAAAABMAcAAAACNTAIAAAAATAJAAAAATEKAAAAATALAAAACzEzMjg4MTY1NTU4DAAAAAExDQAAAAg2LzYvMjAyNBAAAAAJMy8zMS8yMDIz9C+50nmF3AhjI/fSeYXcCC1DSVEuWFRSQTpNQkcuSVFfUkVWRU5VRV9FU1RfQ0lRLkZZMjAyNS4uLi5FVVIBAAAAFKEBAAIAAAAMMTU2MTI3LDI0NjMxAQ4AAAAFAAAAATMBAAAAATACAAAACjEwMDE2NTg3ODUDAAAABjEwMDE4MAQAAAABMwYAAAABMAcAAAACNTAIAAAAATAJAAAAATEKAAAAATALAAAACzEzODA2NjgyNDU2DAAAAAExDQAAAAg2LzYvMjAyNBAAAAAINi81LzIwMjT0L7nSeYXcCE/89tJ5hdwIJ0NJUS5YVFJBOkRFWi5JUV9SRVZFTlVFX0VTVF9DSVEuLi4uLkVVUgEAAABWcAkAAgAAAAcyMDgyLDQ1AQ4AAAAFAAAAAjExAQAAAAEwAgAAAAcxOTI0OTY1AwAAAAYxMDAxODAEAAAAATMGAAAAATAHAAAAAjUwCAAAAAEwCQAAAAExCgAAAAEwCwAAAAsxMzc5NTMwNDg5NQwAAAACMTINAAAACDYvNy8yMDI0EAAAAAg2LzYvMjAyNFbZOHU2htwIVtk4dTaG3AgaQ0lRLlhUUkE6RzFBLklRX05JLi4uLi5FVVIBAAAAMlcNAAIAAAAHNDAxLDYzOAEIAAAABQAAAAExAQAAAAstMTk5NTcxNzg1NAMAAAACNTACAAAAAjE1BAAAAAEwBwAAAAg2LzUvMjAyNAgAAAAJMy8zMS8yMDI0CQAAAAEwYEHc | T1: dnqF3AiBWlN0NobcCCFDSVEuVFNFOjY0MDcuSVFfUkVWLkZZMjAyMy4uLi5FVVIBAAAAl10NAAIAAAALMTEwNCwwMzgzMzEBCAAAAAUAAAABMQEAAAALLTIwMzk1NTcxMDQDAAAAAjUwAgAAAAMxMTIEAAAAATAHAAAACDYvNi8yMDI0CAAAAAkzLzMxLzIwMjMJAAAAATD6xQR0NobcCDEKR3U2htwIK0NJUS5UU1g6TE5SLklRX0VCSVREQV9FU1RfQ0lRLkZZMjAyNS4uLi5FVVIBAAAAdl8NAAIAAAAQMTA5MSwwOTIzNjQ4NjY3NwEOAAAABQAAAAEzAQAAAAEwAgAAAAoxMDAyMzc5MzQ2AwAAAAYxMDAxODcEAAAAATMGAAAAATAHAAAAAjUwCAAAAAEwCQAAAAExCgAAAAEwCwAAAAsxMzgwMDc5NTkxNwwAAAABMQ0AAAAINi82LzIwMjQQAAAACDYvNS8yMDI08Va50nmF3Ah4mPfSeYXcCClDSVEuWFRSQTpERVouSVFfTklfRVNUX05PVEUuRlkyMDI1Li4uLkVVUgEAAABWcAkAAwAAAE9JbmNsdWRlcyBBbW9ydGl6YXRpb24gb2YgSW50YW5naWJsZSBBc3NldHMgYW5kIFN0b2NrIEJhc2VkIENvbXBlbnNhdGlvbiBFeHBlbnNlAP49LSt6hdwIHIk4K3qF3AgpQ0lRLlhUUkE6S1JOLklRX05JX0VTVF9OT1RFLkZZMjAyNi4uLi5FVVIBAAAAwWENAAMAAAAqSW5jbHVkZXMgQW1vcnRpemF0aW9uIG9mIEludGFuZ2libGUgQXNzZXRzAP49LSt6hdwIHIk4K3qF3AgkQ0lRLlhUUkE6REVaLklRX0VCSVREQS5GWTIwMjMu | U1: Li4uRVVSAQAAAFZwCQACAAAABTE4OCw3AQgAAAAFAAAAATEBAAAACy0yMDA1NjM1MDIyAwAAAAI1MAIAAAAENDA1MQQAAAABMAcAAAAINi82LzIwMjQIAAAACjEyLzMxLzIwMjMJAAAAATD6xQR0NobcCJUmWXQ2htwIEkNJUS4uSVFfTkkuLi4uLkVVUgUAAAAAAAAACAAAABQoSW52YWxpZCBJZGVudGlmaWVyKWBB3HZ6hdwI0ghVdDaG3AgeQ0lRLlhUUkE6RFVFLklRX0VCSVREQS4uLi4uRVVSAQAAALRzDQACAAAABzI5OSw1NjEBCAAAAAUAAAABMQEAAAALLTE5OTQ0NzE2NDIDAAAAAjUwAgAAAAQ0MDUxBAAAAAEwBwAAAAg2LzUvMjAyNAgAAAAJMy8zMS8yMDI0CQAAAAEwYEHcdnqF3Aib9lN0NobcCCNDSVEuTllTRTpBUFRWLklRX0VCSVQuRlkyMDIyLi4uLkVVUgEAAABU74sDAgAAAAgxMjgxLDkwOQEIAAAABQAAAAExAQAAAAstMjAxMTQ5MzAwNgMAAAACNTACAAAAAzQwMAQAAAABMAcAAAAINi81LzIwMjQIAAAACjEyLzMxLzIwMjIJAAAAATAsCbnSeYXcCKSVQ9N5hdwILUNJUS5YVFJBOkcxQS5JUV9SRVZFTlVFX0VTVF9DSVEuRlkyMDIzLi4uLkVVUgEAAAAyVw0AAgAAAAo1NDU2LDQ5NDM4AQ4AAAAFAAAAATMBAAAAATACAAAACjEwMDE1NDgwNzQDAAAABjEwMDE4MAQAAAABMwYAAAABMAcAAAACNTAIAAAAATAJAAAAATEKAAAAATALAAAACzEzNjM3NDg4NDg2DAAAAAExDQAAAAg2LzYvMjAyNBAA | V1: AAAKMTIvMzEvMjAyM/QvudJ5hdwIT/z20nmF3AgiQ0lRLkVOWFRQQTpNQy5JUV9SRVYuRlkyMDIyLi4uLkVVUgEAAACg+wIAAgAAAAU3OTE4NAEIAAAABQAAAAExAQAAAAstMjAxMDYwMDY3MAMAAAACNTACAAAAAzExMgQAAAABMAcAAAAINi81LzIwMjQIAAAACjEyLzMxLzIwMjIJAAAAATD0L7nSeYXcCM4N+NJ5hdwIKkNJUS5YVFJBOkcxQS5JUV9FQklUX0VTVF9DSVEuRlkyMDI2Li4uLkVVUgEAAAAyVw0AAgAAAAk2NjYsNjYzMDQBDgAAAAUAAAABMwEAAAABMAIAAAAKMTAwMTU0ODA4OQMAAAAGMTAwMjE1BAAAAAEzBgAAAAEwBwAAAAI1MAgAAAABMAkAAAABMQoAAAABMAsAAAALMTM3OTQyMzg3MjgMAAAAATENAAAACDYvNy8yMDI0EAAAAAg2LzYvMjAyNDgTBXQ2htwIXu5XdDaG3AgiQ0lRLlRTRTo2NzcwLklRX0VCSVQuRlkyMDIyLi4uLkVVUgEAAABPWA0AAgAAAAkyNTYsMTM2NzQBCAAAAAUAAAABMQEAAAALLTIwOTAzNDA4ODkDAAAAAjUwAgAAAAM0MDAEAAAAATAHAAAACDYvNS8yMDI0CAAAAAkzLzMxLzIwMjIJAAAAATAsCbnSeYXcCIy8Q9N5hdwIIkNJUS5YVFJBOkRVRS5JUV9FQklULkZZMjAyMy4uLi5FVVIBAAAAtHMNAAIAAAAHMjA1LDYyNAEIAAAABQAAAAExAQAAAAstMjAwNDE0OTkyNwMAAAACNTACAAAAAzQwMAQAAAABMAcAAAAINi82LzIwMjQIAAAACjEyLzMxLzIwMjMJAAAAATD6 | W1: xQR0NobcCPVNWXQ2htwIK0NJUS5FTlhUUEE6RlIuSVFfRUJJVF9FU1RfQ0lRLkZZMjAyMy4uLi5FVVIBAAAAhoAKAAIAAAAJODA0LDA0Mjk0AQ4AAAAFAAAAATMBAAAAATACAAAACjEwMDIwOTk3MDgDAAAABjEwMDIxNQQAAAABMwYAAAABMAcAAAACNTAIAAAAATAJAAAAATEKAAAAATALAAAACzEzNjY5NDAzNjkzDAAAAAExDQAAAAg2LzYvMjAyNBAAAAAKMTIvMzEvMjAyM/FWudJ5hdwIO9X20nmF3AgpQ0lRLkVOWFRQQTpGUi5JUV9NQVJLRVRDQVAuMzEuMDUuMjAyMy5FVVIBAAAAhoAKAAIAAAALNDMzMCw0NDk5NTEBBgAAAAUAAAABMQEAAAALLTIwNTk4MjI4MDADAAAAAjUwAgAAAAYxMDAwNTQEAAAAATAHAAAACTUvMzEvMjAyMywJudJ5hdwIl9H40nmF3AgsQ0lRLlRTRTo2OTAyLklRX0VCSVREQV9FU1RfQ0lRLkZZMjAyNS4uLi5FVVIBAAAAPFYNAAIAAAAQNjQ5NCw0OTQ2NjM1NzI5MwEOAAAABQAAAAEzAQAAAAEwAgAAAAoxMDAzMTk3MzU0AwAAAAYxMDAxODcEAAAAATMGAAAAATAHAAAAAjUwCAAAAAEwCQAAAAExCgAAAAEwCwAAAAsxMzgwODQ1ODE4NgwAAAABMQ0AAAAINi82LzIwMjQQAAAACDYvNS8yMDI09C+50nmF3AjSS/fSeYXcCCxDSVEuT006QUxGQS5JUV9SRVZFTlVFX0VTVF9DSVEuRlkyMDI2Li4uLkVVUgEAAAA4aAYAAgAAABA2NzUxLDM3NjE2MzA5Njg5AQ4AAAAFAAAAATMBAAAA | X1: ATACAAAACjEwMDExNjA1NTIDAAAABjEwMDE4MAQAAAABMwYAAAABMAcAAAACNTAIAAAAATAJAAAAATEKAAAAATALAAAACzEzODAzMzE4NjQxDAAAAAExDQAAAAg2LzcvMjAyNBAAAAAINi82LzIwMjRx7AR0NobcCEvjRnU2htwIKkNJUS5YVFJBOkJNVy5JUV9FQklUX0VTVF9DSVEuRlkyMDI0Li4uLkVVUgEAAAB6wAoAAgAAAAsxNjEwNiwxNzY2MgEOAAAABQAAAAEzAQAAAAEwAgAAAAoxMDAxNTg3MTMyAwAAAAYxMDAyMTUEAAAAATMGAAAAATAHAAAAAjUwCAAAAAEwCQAAAAExCgAAAAEwCwAAAAsxMzgwNzg0MzY0NQwAAAABMQ0AAAAINi82LzIwMjQQAAAACDYvNS8yMDI09C+50nmF3AgcXPjSeYXcCCRDSVEuVFNFOjY0MDcuSVFfTklfRVNULkZZMjAyNS4uLi5FVVIBAAAAl10NAAMAAAAAAHHsBHQ2htwImdhYdDaG3AgpQ0lRLlhUUkE6RFVFLklRX05JX0VTVF9OT1RFLkZZMjAyNC4uLi5FVVIBAAAAtHMNAAMAAABPSW5jbHVkZXMgQW1vcnRpemF0aW9uIG9mIEludGFuZ2libGUgQXNzZXRzIGFuZCBTdG9jayBCYXNlZCBDb21wZW5zYXRpb24gRXhwZW5zZQD+PS0reoXcCC2wOCt6hdwIIkNJUS5FTlhUUEE6RlIuSVFfUkVWLkZZMjAyMi4uLi5FVVIBAAAAhoAKAAIAAAAFMjAwMzcBCAAAAAUAAAABMQEAAAALLTIwMDc5NzM1NTYDAAAAAjUwAgAAAAMxMTIEAAAAATAHAAAACDYvNS8yMDI0CAAAAAoxMi8z | Y1: MS8yMDIyCQAAAAEw9C+50nmF3Ah4mPfSeYXcCCdDSVEuJEVVUlVTRC5JUV9MQVNUU0FMRVBSSUNFLjMxLjA1LjIwMjMBAAAAuOtaAAIAAAAGMCw5MzgzAPQvudJ5hdwIw3H30nmF3AggQ0lRLlRTRTo2MTQxLklRX05JLkZZMjAyMy4uLi5FVVIBAAAA0FwNAAIAAAAKMjE3LDg1NDAxOAEIAAAABQAAAAExAQAAAAstMjAwMjk2ODgwMAMAAAACNTACAAAAAjE1BAAAAAEwBwAAAAg2LzYvMjAyNAgAAAAKMTIvMzEvMjAyMwkAAAABMPrFBHQ2htwIw3RZdDaG3AgqQ0lRLlhUUkE6REVaLklRX0VCSVRfRVNUX0NJUS5GWTIwMjUuLi4uRVVSAQAAAFZwCQACAAAABTE1MCw5AQ4AAAAFAAAAATMBAAAAATACAAAACjEwMDM0NDgxNTQDAAAABjEwMDIxNQQAAAABMwYAAAABMAcAAAACNTAIAAAAATAJAAAAATEKAAAAATALAAAACzEzNzUzMTUzNDcxDAAAAAExDQAAAAg2LzcvMjAyNBAAAAAINi82LzIwMjRx7AR0NobcCDKOWHQ2htwIKkNJUS5UU0U6Njc3MC5JUV9FQklUX0VTVF9DSVEuRlkyMDI1Li4uLkVVUgEAAABPWA0AAgAAABAxMjcsNDk0OTI4MzU1NTkyAQ4AAAAFAAAAATMBAAAAATACAAAACjEwMDE5NzE2MzQDAAAABjEwMDIxNQQAAAACNTYGAAAAATAHAAAAAjUwCAAAAAEwCQAAAAExCgAAAAEwCwAAAAsxMzgwODcyMjg3NQwAAAABMQ0AAAAINi82LzIwMjQQAAAACDYvNS8yMDI09C+50nmF3AiMvEPTeYXcCClD | Z1: SVEuT1RDQ0g6MDAxMjY4NDY1LlFfTklfRVNUX05PVEUuLi4uLkVVUgUAAAAAAAAACAAAABYoSW52YWxpZCBGb3JtdWxhIE5hbWUp2rCxEXqF3AgvUbkReoXcCCRDSVEuVFNFOjY3NzAuSVFfRUJJVF9FU1RfQ0lRLi4uLi5FVVIBAAAAT1gNAAIAAAAQMTI3LDQ5NDkyODM1NTU5MgEOAAAABQAAAAIxMQEAAAABMAIAAAAKMTAwMTk3MTYzNAMAAAAGMTAwMjE1BAAAAAI1NgYAAAABMAcAAAACNTAIAAAAATAJAAAAATEKAAAAATALAAAACzEzODA4NzIyODc1DAAAAAIxMg0AAAAINi82LzIwMjQQAAAACDYvNS8yMDI0cns903mF3Ahyez3TeYXcCCxDSVEuWFRSQTpHMUEuSVFfRUJJVERBX0VTVF9DSVEuRlkyMDI0Li4uLkVVUgEAAAAyVw0AAgAAAAk4MDEsOTMwODQBDgAAAAUAAAABMwEAAAABMAIAAAAKMTAwMTU0ODA3OQMAAAAGMTAwMTg3BAAAAAEzBgAAAAEwBwAAAAI1MAgAAAABMAkAAAABMQoAAAABMAsAAAALMTM4MDA3NDY5NTUMAAAAATENAAAACDYvNy8yMDI0EAAAAAg2LzYvMjAyNDgTBXQ2htwIL39HdTaG3AgaQ0lRLk9NOkFMRkEuSVFfUkVWLi4uLi5FVVIBAAAAOGgGAAIAAAALNTU4MiwxOTMzMDMBCAAAAAUAAAABMQEAAAALLTE5OTk2MjQyMjIDAAAAAjUwAgAAAAMxMTIEAAAAATAHAAAACDYvNi8yMDI0CAAAAAkzLzMxLzIwMjQJAAAAATBnsjh1NobcCGeyOHU2htwILUNJUS5YVFJBOkcxQS5JUV9S | AA1: RVZFTlVFX0VTVF9DSVEuRlkyMDI1Li4uLkVVUgEAAAAyVw0AAgAAAAo1NjMwLDMxNTA2AQ4AAAAFAAAAATMBAAAAATACAAAACjEwMDE1NDgwODQDAAAABjEwMDE4MAQAAAABMwYAAAABMAcAAAACNTAIAAAAATAJAAAAATEKAAAAATALAAAACzEzODAwNzQ3Njk2DAAAAAExDQAAAAg2LzcvMjAyNBAAAAAINi82LzIwMjQ4EwV0NobcCC9/R3U2htwIKENJUS5YVFJBOktSTi5JUV9NQVJLRVRDQVAuMzEuMDUuMjAyNC5FVVIBAAAAwWENAAIAAAALMzk4MCw3MjcwNzIBBgAAAAUAAAABMQEAAAALLTE5OTcwNTUwMzADAAAAAjUwAgAAAAYxMDAwNTQEAAAAATAHAAAACTUvMzEvMjAyNPrFBHQ2htwIgVpTdDaG3AgoQ0lRLlRTRTo2MTQxLklRX01BUktFVENBUC4zMS4wNS4yMDI0LkVVUgEAAADQXA0AAgAAABAzNzA2LDAyNDQ3ODE4OTE3AQYAAAAFAAAAATEBAAAACy0xOTkzOTc0OTk1AwAAAAI1MAIAAAAGMTAwMDU0BAAAAAEwBwAAAAk1LzMxLzIwMjT6xQR0NobcCO1rVHQ2htwIHkNJUS5YVFJBOkcxQS5JUV9FQklUREEuLi4uLkVVUgEAAAAyVw0AAgAAAAc2MDAsMjAxAQgAAAAFAAAAATEBAAAACy0xOTk1NzE3ODU0AwAAAAI1MAIAAAAENDA1MQQAAAABMAcAAAAINi81LzIwMjQIAAAACTMvMzEvMjAyNAkAAAABMGBB3HZ6hdwItahTdDaG3AgjQ0lRLk9NOkFMRkEuSVFfTklfRVNULkZZMjAyNS4uLi5FVVIBAAAA | AB1: OGgGAAIAAAAQNzgzLDcwMzI5MTY2Mjk2NgEOAAAABQAAAAEzAQAAAAEwAgAAAAoxMDAxMTYwNTUxAwAAAAYxMDAyNTAEAAAAATMGAAAAATAHAAAAAjUwCAAAAAEwCQAAAAExCgAAAAEwCwAAAAsxMzgwMzMyMDQwMwwAAAABMQ0AAAAINi83LzIwMjQQAAAACDYvNi8yMDI0cewEdDaG3AiZ2Fh0NobcCC1DSVEuVFNFOjYxNDEuSVFfUkVWRU5VRV9FU1RfQ0lRLkZZMjAyNS4uLi5FVVIBAAAA0FwNAAIAAAAQMzQzOSwzOTkzNzMyOTEzNQEOAAAABQAAAAEzAQAAAAEwAgAAAAoxMDAzNzU5NTc0AwAAAAYxMDAxODAEAAAAATMGAAAAATAHAAAAAjUwCAAAAAEwCQAAAAExCgAAAAEwCwAAAAsxMzc1ODI1MjY0OQwAAAABMQ0AAAAINi83LzIwMjQQAAAACDYvNi8yMDI0cewEdDaG3AhIWEd1NobcCCtDSVEuVFNYOkxOUi5JUV9FQklUREFfRVNUX0NJUS5GWTIwMjMuLi4uRVVSAQAAAHZfDQACAAAAEDg3Miw3NDgxNTU0OTE2MzIBDgAAAAUAAAABMwEAAAABMAIAAAAKMTAwMjM3OTM0NAMAAAAGMTAwMTg3BAAAAAEzBgAAAAEwBwAAAAI1MAgAAAABMAkAAAABMQoAAAABMAsAAAALMTM2Nzk1NjI4NTUMAAAAATENAAAACDYvNi8yMDI0EAAAAAoxMi8zMS8yMDIz8Va50nmF3AjVv/fSeYXcCCRDSVEuWFRSQTpHMUEuSVFfTklfRVNULkZZMjAyNC4uLi5FVVIBAAAAMlcNAAIAAAAJNDM5LDg5MDEzAQ4AAAAFAAAAATMBAAAA | AC1: ATACAAAACjEwMDE1NDgwNzkDAAAABjEwMDI1MAQAAAABMwYAAAABMAcAAAACNTAIAAAAATAJAAAAATEKAAAAATALAAAACzEzODAwNzQ3NzAyDAAAAAExDQAAAAg2LzcvMjAyNBAAAAAINi82LzIwMjQ4EwV0NobcCMN0WXQ2htwIKENJUS5YVFJBOkRVRS5JUV9NQVJLRVRDQVAuMzEuMDUuMjAyNC5FVVIBAAAAtHMNAAIAAAALMTYyMiwwOTY3NTUBBgAAAAUAAAABMQEAAAALLTE5OTQ0NzE3NzcDAAAAAjUwAgAAAAYxMDAwNTQEAAAAATAHAAAACTUvMzEvMjAyNPrFBHQ2htwI0B1UdDaG3AgnQ0lRLlRTRTo2MTQxLklRX1JFVkVOVUVfRVNUX0NJUS4uLi4uRVVSAQAAANBcDQACAAAAEDMyNzksNDIwNDU3Nzc4NDgBDgAAAAUAAAACMTEBAAAAATACAAAABzM4MDY2MDUDAAAABjEwMDE4MAQAAAABMwYAAAABMAcAAAACNTAIAAAAATAJAAAAATEKAAAAATALAAAACzEzNzU4MjUzODEwDAAAAAIxMg0AAAAINi83LzIwMjQQAAAACDYvNi8yMDI0Vtk4dTaG3AhW2Th1NobcCCpDSVEuWFRSQTpHMUEuSVFfRUJJVF9FU1RfQ0lRLkZZMjAyNC4uLi5FVVIBAAAAMlcNAAIAAAAJNjE4LDEyMTczAQ4AAAAFAAAAATMBAAAAATACAAAACjEwMDE1NDgwNzkDAAAABjEwMDIxNQQAAAABMwYAAAABMAcAAAACNTAIAAAAATAJAAAAATEKAAAAATALAAAACzEzODAwNzQ2MzY3DAAAAAExDQAAAAg2LzcvMjAyNBAAAAAINi82LzIwMjQ4 | AD1: EwV0NobcCJUmWXQ2htwIHkNJUS5UU0U6NjQwNy5JUV9FQklUREEuLi4uLkVVUgEAAACXXQ0AAgAAAAoxMjIsMTI2MTQ4AQgAAAAFAAAAATEBAAAACy0xOTk1MjM2MjQwAwAAAAI1MAIAAAAENDA1MQQAAAABMAcAAAAINi81LzIwMjQIAAAACTMvMzEvMjAyNAkAAAABMGBB3HZ6hdwI+LlUdDaG3AgmQ0lRLlRTRTo2MTQxLklRX0VCSVREQV9FU1RfQ0lRLi4uLi5FVVIBAAAA0FwNAAIAAAAQNTI4LDM5MDAyOTEyNjUyOQEOAAAABQAAAAIxMQEAAAABMAIAAAAHMzgwNjYwNQMAAAAGMTAwMTg3BAAAAAEzBgAAAAEwBwAAAAI1MAgAAAABMAkAAAABMQoAAAABMAsAAAALMTM3NTcwOTE3MTYMAAAAAjEyDQAAAAg2LzcvMjAyNBAAAAAINi82LzIwMjRW2Th1NobcCFbZOHU2htwIJENJUS5YVFJBOkRFWi5JUV9OSV9FU1QuRlkyMDI1Li4uLkVVUgEAAABWcAkAAgAAAAYxMTIsNjYBDgAAAAUAAAABMwEAAAABMAIAAAAKMTAwMzQ0ODE1NAMAAAAGMTAwMjUwBAAAAAEzBgAAAAEwBwAAAAI1MAgAAAABMAkAAAABMQoAAAABMAsAAAALMTM3NTMxNTMzODEMAAAAATENAAAACDYvNy8yMDI0EAAAAAg2LzYvMjAyNHHsBHQ2htwImdhYdDaG3AgsQ0lRLlhUUkE6RFVFLklRX0VCSVREQV9FU1RfQ0lRLkZZMjAyNS4uLi5FVVIBAAAAtHMNAAIAAAAJNDU2LDA3NjYzAQ4AAAAFAAAAATMBAAAAATACAAAACjEwMDE0NzAzODQDAAAA | AE1: BjEwMDE4NwQAAAABMwYAAAABMAcAAAACNTAIAAAAATAJAAAAATEKAAAAATALAAAACzEzODA4MjQwNzYzDAAAAAExDQAAAAg2LzcvMjAyNBAAAAAINi82LzIwMjRx7AR0NobcCC9/R3U2htwIKkNJUS5YVFJBOk1CRy5JUV9FQklUX0VTVF9DSVEuRlkyMDIzLi4uLkVVUgEAAAAUoQEAAgAAAAsxOTUxMyw3MTk0NwEOAAAABQAAAAEzAQAAAAEwAgAAAAoxMDAxNTc2MjMyAwAAAAYxMDAyMTUEAAAAATMGAAAAATAHAAAAAjUwCAAAAAEwCQAAAAExCgAAAAEwCwAAAAsxMzY5MTE4MjMyMgwAAAABMQ0AAAAINi82LzIwMjQQAAAACjEyLzMxLzIwMjP0L7nSeYXcCM4N+NJ5hdwIHENJUS5YVFJBOk1CRy5JUV9FQklULi4uLi5FVVIBAAAAFKEBAAIAAAAFMTU3MzMBCAAAAAUAAAABMQEAAAALLTE5OTc4MzQ4NTUDAAAAAjUwAgAAAAM0MDAEAAAAATAHAAAACDYvNS8yMDI0CAAAAAkzLzMxLzIwMjQJAAAAATByez3TeYXcCHJ7PdN5hdwILENJUS5PTTpBTEZBLklRX1JFVkVOVUVfRVNUX0NJUS5GWTIwMjQuLi4uRVVSAQAAADhoBgACAAAAEDYxNDUsNzc3NDE2NTEwMDkBDgAAAAUAAAABMwEAAAABMAIAAAAKMTAwMTE2MDU1MAMAAAAGMTAwMTgwBAAAAAEzBgAAAAEwBwAAAAI1MAgAAAABMAkAAAABMQoAAAABMAsAAAALMTM4MDMzMTg2NjQMAAAAATENAAAACDYvNy8yMDI0EAAAAAg2LzYvMjAyNPrFBHQ2htwIS+NGdTaG | AF1: 3AgjQ0lRLk9NOkFMRkEuSVFfRUJJVF9FU1RfQ0lRLi4uLi5FVVIBAAAAOGgGAAIAAAAQMTA3MiwyNzU2NTk3MDk3NQEOAAAABQAAAAIxMQEAAAABMAIAAAAIMjkzODU2NDkDAAAABjEwMDIxNQQAAAABMwYAAAABMAcAAAACNTAIAAAAATAJAAAAATEKAAAAATALAAAACzEzNzk5NTY5MDU5DAAAAAIxMg0AAAAINi82LzIwMjQQAAAACDYvNS8yMDI0NdaPunmF3Ah3fVV0NobcCB1DSVEuRU5YVFBBOk1DLklRX0VCSVQuLi4uLkVVUgEAAACg+wIAAgAAAAUyMjc5NQEIAAAABQAAAAExAQAAAAstMjAxMDU5MzczNQMAAAACNTACAAAAAzQwMAQAAAABMAcAAAAINi81LzIwMjQIAAAACjEyLzMxLzIwMjMJAAAAATByez3TeYXcCHJ7PdN5hdwILUNJUS5YVFJBOkRFWi5JUV9SRVZFTlVFX0VTVF9DSVEuRlkyMDI1Li4uLkVVUgEAAABWcAkAAgAAAAYyMzA0LDkBDgAAAAUAAAABMwEAAAABMAIAAAAKMTAwMzQ0ODE1NAMAAAAGMTAwMTgwBAAAAAEzBgAAAAEwBwAAAAI1MAgAAAABMAkAAAABMQoAAAABMAsAAAALMTM3NTYxNzMzMzEMAAAAATENAAAACDYvNy8yMDI0EAAAAAg2LzYvMjAyNHHsBHQ2htwIwjFHdTaG3AggQ0lRLlRTRTo2NDA3LklRX05JLkZZMjAyMy4uLi5FVVIBAAAAl10NAAIAAAAKMTAyLDM4ODIyMwEIAAAABQAAAAExAQAAAAstMjAzOTU1NzEwNAMAAAACNTACAAAAAjE1BAAAAAEwBwAAAAg2LzYvMjAy | AG1: NAgAAAAJMy8zMS8yMDIzCQAAAAEw+sUEdDaG3AjDdFl0NobcCClDSVEuVFNYOkxOUi5JUV9FQklUX0VTVF9DSVEuRlkyMDI0Li4uLkVVUgEAAAB2Xw0AAgAAABA2NjQsNDQyMzg2NzQ4ODEzAQ4AAAAFAAAAATMBAAAAATACAAAACjEwMDIzNzkzNDUDAAAABjEwMDIxNQQAAAABMwYAAAABMAcAAAACNTAIAAAAATAJAAAAATEKAAAAATALAAAACzEzODAwNzk1OTY1DAAAAAExDQAAAAg2LzYvMjAyNBAAAAAINi81LzIwMjTxVrnSeYXcCHiY99J5hdwIK0NJUS5PVENDSDowMDEyNjg0NjUuSVFfTklfRVNULkZZMjAyNi4uLi5FVVIBAAAAflkNAAMAAAAAAHHsBHQ2htwI3RVYdDaG3AgkQ0lRLlhUUkE6S1JOLklRX05JX0VTVC5GWTIwMjUuLi4uRVVSAQAAAMFhDQACAAAACTMzNSw1MzE3MgEOAAAABQAAAAEzAQAAAAEwAgAAAAoxMDAxNjgwNDU3AwAAAAYxMDAyNTAEAAAAATMGAAAAATAHAAAAAjUwCAAAAAEwCQAAAAExCgAAAAEwCwAAAAsxMzc5MTg3NDIwNAwAAAABMQ0AAAAINi83LzIwMjQQAAAACDYvNi8yMDI0OBMFdDaG3Aix/1h0NobcCC1DSVEuWFRSQTpLUk4uSVFfUkVWRU5VRV9FU1RfQ0lRLkZZMjAyNi4uLi5FVVIBAAAAwWENAAIAAAAKNTk1MywxOTAzNgEOAAAABQAAAAEzAQAAAAEwAgAAAAoxMDAyNjA2NTQ5AwAAAAYxMDAxODAEAAAAATMGAAAAATAHAAAAAjUwCAAAAAEwCQAAAAExCgAAAAEwCwAA | AH1: AAsxMzc5NDk4MTIyNwwAAAABMQ0AAAAINi83LzIwMjQQAAAACDYvNi8yMDI0OBMFdDaG3Agvf0d1NobcCCFDSVEuWFRSQTpLUk4uSVFfUkVWLkZZMjAyMy4uLi5FVVIBAAAAwWENAAIAAAAINDc2NSw0NzkBCAAAAAUAAAABMQEAAAALLTIwMDUwODcwMDQDAAAAAjUwAgAAAAMxMTIEAAAAATAHAAAACDYvNi8yMDI0CAAAAAoxMi8zMS8yMDIzCQAAAAEw+sUEdDaG3Agvf0d1NobcCChDSVEuVFNFOjY5MDIuSVFfTUFSS0VUQ0FQLjMxLjA1LjIwMjMuRVVSAQAAADxWDQACAAAAEDQzMzAzLDM1NDgwMjc4NDgBBgAAAAUAAAABMQEAAAALLTIwNDkzMzEzNzEDAAAAAjUwAgAAAAYxMDAwNTQEAAAAATAHAAAACTUvMzEvMjAyMywJudJ5hdwI1b/30nmF3AguQ0lRLkVOWFRQQTpNQy5JUV9SRVZFTlVFX0VTVF9DSVEuRlkyMDI0Li4uLkVVUgEAAACg+wIAAgAAAAs4OTgwNSw4Njg1MQEOAAAABQAAAAEzAQAAAAEwAgAAAAoxMDAxNzYzMDgzAwAAAAYxMDAxODAEAAAAATMGAAAAATAHAAAAAjUwCAAAAAEwCQAAAAExCgAAAAEwCwAAAAsxMzgwNzA3NjA1NgwAAAABMQ0AAAAINi82LzIwMjQQAAAACDYvNS8yMDI08Va50nmF3Aj3NPjSeYXcCC1DSVEuRU5YVFBBOk1DLklRX0VCSVREQV9FU1RfQ0lRLkZZMjAyMy4uLi5FVVIBAAAAoPsCAAIAAAALMjg4MTgsNDA3NTIBDgAAAAUAAAABMwEAAAABMAIAAAAKMTAwMTc2MzA4 | AI1: MgMAAAAGMTAwMTg3BAAAAAEzBgAAAAEwBwAAAAI1MAgAAAABMAkAAAABMQoAAAABMAsAAAALMTM2MjU5Mjc0NTAMAAAAATENAAAACDYvNi8yMDI0EAAAAAoxMi8zMS8yMDIz8Va50nmF3AjVv/fSeYXcCCdDSVEuT006QUxGQS5JUV9NQVJLRVRDQVAuMzEuMDUuMjAyNC5FVVIBAAAAOGgGAAIAAAAQMTc1NTQsNTkxMjc1Nzk2OQEGAAAABQAAAAExAQAAAAstMTk5OTYyNDMwMwMAAAACNTACAAAABjEwMDA1NAQAAAABMAcAAAAJNS8zMS8yMDI0+sUEdDaG3AhroFd0NobcCC1DSVEuWFRSQTpEVUUuSVFfUkVWRU5VRV9FU1RfQ0lRLkZZMjAyNC4uLi5FVVIBAAAAtHMNAAIAAAAKNDgzMCw3NzY2MwEOAAAABQAAAAEzAQAAAAEwAgAAAAoxMDAxMzYxOTIwAwAAAAYxMDAxODAEAAAAATMGAAAAATAHAAAAAjUwCAAAAAEwCQAAAAExCgAAAAEwCwAAAAsxMzgwODI0MDk0NQwAAAABMQ0AAAAINi83LzIwMjQQAAAACDYvNi8yMDI0cewEdDaG3AhIWEd1NobcCC1DSVEuVFNFOjY0MDcuSVFfUkVWRU5VRV9FU1RfQ0lRLkZZMjAyNC4uLi5FVVIBAAAAl10NAAIAAAAPODIzLDc1NjMwMDMwMzEyAQ4AAAAFAAAAATMBAAAAATACAAAACjEwMDM3MzYyODYDAAAABjEwMDE4MAQAAAACNTYGAAAAATAHAAAAAjUwCAAAAAEwCQAAAAExCgAAAAEwCwAAAAsxMzczMTgyOTY0MAwAAAABMQ0AAAAINi83LzIwMjQQAAAACTMvMzEvMjAy | AJ1: NHHsBHQ2htwIwjFHdTaG3AgpQ0lRLk9NOkFMRkEuSVFfRUJJVF9FU1RfQ0lRLkZZMjAyNC4uLi5FVVIBAAAAOGgGAAIAAAAQMTAwNSwxNjczODExNzQyMgEOAAAABQAAAAEzAQAAAAEwAgAAAAoxMDAxMTYwNTUwAwAAAAYxMDAyMTUEAAAAATMGAAAAATAHAAAAAjUwCAAAAAEwCQAAAAExCgAAAAEwCwAAAAsxMzgwMzMxODU2MgwAAAABMQ0AAAAINi83LzIwMjQQAAAACDYvNi8yMDI0cewEdDaG3AiVJll0NobcCCxDSVEuWFRSQTpERVouSVFfRUJJVERBX0VTVF9DSVEuRlkyMDI1Li4uLkVVUgEAAABWcAkAAgAAAAgyNDYsMzczMQEOAAAABQAAAAEzAQAAAAEwAgAAAAoxMDAzNDQ4MTU0AwAAAAYxMDAxODcEAAAAATMGAAAAATAHAAAAAjUwCAAAAAEwCQAAAAExCgAAAAEwCwAAAAsxMzc1NjM0MTg5MgwAAAABMQ0AAAAINi83LzIwMjQQAAAACDYvNi8yMDI0cewEdDaG3AhIWEd1NobcCCxDSVEuWFRSQTpCTVcuSVFfRUJJVERBX0VTVF9DSVEuRlkyMDI0Li4uLkVVUgEAAAB6wAoAAgAAAAsyNTAzMiwwMDIzMwEOAAAABQAAAAEzAQAAAAEwAgAAAAoxMDAxNTg3MTMyAwAAAAYxMDAxODcEAAAAATMGAAAAATAHAAAAAjUwCAAAAAEwCQAAAAExCgAAAAEwCwAAAAsxMzgwNzg0MzY1NwwAAAABMQ0AAAAINi82LzIwMjQQAAAACDYvNS8yMDI09C+50nmF3Ah4mPfSeYXcCCpDSVEuWFRSQTpHMUEuSVFfRUJJVF9FU1Rf | AK1: Q0lRLkZZMjAyMy4uLi5FVVIBAAAAMlcNAAIAAAAJNTg4LDg2NzI0AQ4AAAAFAAAAATMBAAAAATACAAAACjEwMDE1NDgwNzQDAAAABjEwMDIxNQQAAAABMwYAAAABMAcAAAACNTAIAAAAATAJAAAAATEKAAAAATALAAAACzEzNjY5MjA0MTgzDAAAAAExDQAAAAg2LzYvMjAyNBAAAAAKMTIvMzEvMjAyM/QvudJ5hdwIYyP30nmF3AgxQ0lRLk9UQ0NIOjAwMTI2ODQ2NS5JUV9FQklUX0VTVF9DSVEuRlkyMDI1Li4uLkVVUgEAAAB+WQ0AAwAAAAAAcewEdDaG3Agyjlh0NobcCB5DSVEuWFRSQTpEVUUuSVFfTklfRVNULi4uLi5FVVIBAAAAtHMNAAIAAAAIMTY0LDk5NDQBDgAAAAUAAAACMTEBAAAAATACAAAACDU3NDc2NTQzAwAAAAYxMDAyNTAEAAAAATMGAAAAATAHAAAAAjUwCAAAAAEwCQAAAAExCgAAAAEwCwAAAAsxMzgwODI0MTM4OQwAAAACMTINAAAACDYvNi8yMDI0EAAAAAg2LzUvMjAyNGBB3HZ6hdwIjM9TdDaG3AgsQ0lRLlRTRTo2OTAyLklRX0VCSVREQV9FU1RfQ0lRLkZZMjAyNC4uLi5FVVIBAAAAPFYNAAIAAAAQNTE0NSw3NTY5NzI4NDAzMwEOAAAABQAAAAEzAQAAAAEwAgAAAAoxMDAyODg1NzIxAwAAAAYxMDAxODcEAAAAATMGAAAAATAHAAAAAjUwCAAAAAEwCQAAAAExCgAAAAEwCwAAAAsxMzc0NTkxODkzOQwAAAABMQ0AAAAINi82LzIwMjQQAAAACTMvMzEvMjAyNPQvudJ5hdwI6Kr40nmF3Agt | AL1: Q0lRLlRTRTo2NzcwLklRX1JFVkVOVUVfRVNUX0NJUS5GWTIwMjQuLi4uRVVSAQAAAE9YDQACAAAADzU4MzAsOTU4NjA5MDk4MgEOAAAABQAAAAEzAQAAAAEwAgAAAAoxMDAxOTcxNjI5AwAAAAYxMDAxODAEAAAAAjU2BgAAAAEwBwAAAAI1MAgAAAABMAkAAAABMQoAAAABMAsAAAALMTM3NDg1NDEwMDAMAAAAATENAAAACDYvNi8yMDI0EAAAAAkzLzMxLzIwMjT0L7nSeYXcCGMj99J5hdwIK0NJUS5FTlhUUEE6TUMuSVFfRUJJVF9FU1RfQ0lRLkZZMjAyMy4uLi5FVVIBAAAAoPsCAAIAAAALMjI1NzEsNzg0MzQBDgAAAAUAAAABMwEAAAABMAIAAAAKMTAwMTc2MzA4MgMAAAAGMTAwMjE1BAAAAAEzBgAAAAEwBwAAAAI1MAgAAAABMAkAAAABMQoAAAABMAsAAAALMTM2MzE4MzcwODMMAAAAATENAAAACDYvNi8yMDI0EAAAAAoxMi8zMS8yMDIz8Va50nmF3Ag71fbSeYXcCCNDSVEuVFNYOkxOUi5JUV9FQklUX0VTVF9DSVEuLi4uLkVVUgEAAAB2Xw0AAgAAABA2NzQsNDg3MDAxODA4MzgyAQ4AAAAFAAAAAjExAQAAAAEwAgAAAAk2NTIxMjM5NDYDAAAABjEwMDIxNQQAAAABMwYAAAABMAcAAAACNTAIAAAAATAJAAAAATEKAAAAATALAAAACzEzODAwNzk3ODU3DAAAAAIxMg0AAAAINi82LzIwMjQQAAAACDYvNS8yMDI0cns903mF3Ahyez3TeYXcCC1DSVEuWFRSQTpNQkcuSVFfUkVWRU5VRV9FU1RfQ0lRLkZZMjAy | AM1: My4uLi5FVVIBAAAAFKEBAAIAAAAMMTUyMzI4LDY1Mzk5AQ4AAAAFAAAAATMBAAAAATACAAAACjEwMDE1NzYyMzIDAAAABjEwMDE4MAQAAAABMwYAAAABMAcAAAACNTAIAAAAATAJAAAAATEKAAAAATALAAAACzEzNjkxMTgyMjgwDAAAAAExDQAAAAg2LzYvMjAyNBAAAAAKMTIvMzEvMjAyM/QvudJ5hdwIl9H40nmF3AgiQ0lRLlhUUkE6Qk1XLklRX0VCSVQuRlkyMDIyLi4uLkVVUgEAAAB6wAoAAgAAAAUxNDA1OQEIAAAABQAAAAExAQAAAAstMjAwNTIyODMzOAMAAAACNTACAAAAAzQwMAQAAAABMAcAAAAINi81LzIwMjQIAAAACjEyLzMxLzIwMjIJAAAAATAsCbnSeYXcCE1uQ9N5hdwIKENJUS5YVFJBOkcxQS5JUV9NQVJLRVRDQVAuMzEuMDUuMjAyMy5FVVIBAAAAMlcNAAIAAAALNjc3MCw4ODc5NzYBBgAAAAUAAAABMQEAAAALLTIwNDUzMTU5MDQDAAAAAjUwAgAAAAYxMDAwNTQEAAAAATAHAAAACTUvMzEvMjAyMywJudJ5hdwIYyP30nmF3AgtQ0lRLlhUUkE6RFVFLklRX1JFVkVOVUVfRVNUX0NJUS5GWTIwMjYuLi4uRVVSAQAAALRzDQACAAAACjUxOTgsMzY0MzkBDgAAAAUAAAABMwEAAAABMAIAAAAKMTAwMTQ3MDM4NQMAAAAGMTAwMTgwBAAAAAEzBgAAAAEwBwAAAAI1MAgAAAABMAkAAAABMQoAAAABMAsAAAALMTM4MDgyNDA2MTMMAAAAATENAAAACDYvNy8yMDI0EAAAAAg2LzYvMjAyNHHsBHQ2htwI | AN1: SFhHdTaG3AgwQ0lRLk9UQ0NIOjAwMTI2ODQ2NS5JUV9OSV9FU1RfTk9URS5GWTIwMjUuLi4uRVVSAQAAAH5ZDQADAAAAAAB3jE0oeoXcCFQCVyh6hdwILUNJUS5FTlhUUEE6TUMuSVFfRUJJVERBX0VTVF9DSVEuRlkyMDI1Li4uLkVVUgEAAACg+wIAAgAAAAszMTkxNSwwMTUyOQEOAAAABQAAAAEzAQAAAAEwAgAAAAoxMDAxNzYzMDg0AwAAAAYxMDAxODcEAAAAATMGAAAAATAHAAAAAjUwCAAAAAEwCQAAAAExCgAAAAEwCwAAAAsxMzgwNzA3NTk4NAwAAAABMQ0AAAAINi82LzIwMjQQAAAACDYvNS8yMDI08Va50nmF3Aii5vfSeYXcCC1DSVEuWFRSQTpCTVcuSVFfUkVWRU5VRV9FU1RfQ0lRLkZZMjAyNS4uLi5FVVIBAAAAesAKAAIAAAAMMTYyMzMxLDE1MjA5AQ4AAAAFAAAAATMBAAAAATACAAAACjEwMDE2NjY0NTgDAAAABjEwMDE4MAQAAAABMwYAAAABMAcAAAACNTAIAAAAATAJAAAAATEKAAAAATALAAAACzEzODA3OTY2NDQyDAAAAAExDQAAAAg2LzYvMjAyNBAAAAAINi81LzIwMjT0L7nSeYXcCPc0+NJ5hdwIK0NJUS5FTlhUUEE6RlIuSVFfRUJJVF9FU1RfQ0lRLkZZMjAyNS4uLi5FVVIBAAAAhoAKAAIAAAAKMTI5MCwyNTM1NgEOAAAABQAAAAEzAQAAAAEwAgAAAAoxMDAzNTAwNjUyAwAAAAYxMDAyMTUEAAAAATMGAAAAATAHAAAAAjUwCAAAAAEwCQAAAAExCgAAAAEwCwAAAAsxMzgwNzg0MTc2NAwA | AO1: AAABMQ0AAAAINi82LzIwMjQQAAAACDYvNS8yMDI08Va50nmF3AiklUPTeYXcCB1DSVEuT006QUxGQS5JUV9FQklUREEuLi4uLkVVUgEAAAA4aAYAAgAAAAo5NzAsOTIxNzYyAQgAAAAFAAAAATEBAAAACy0xOTk5NjI0MjIyAwAAAAI1MAIAAAAENDA1MQQAAAABMAcAAAAINi81LzIwMjQIAAAACTMvMzEvMjAyNAkAAAABMGBB3HZ6hdwIs6RVdDaG3AgsQ0lRLlhUUkE6TUJHLklRX0VCSVREQV9FU1RfQ0lRLkZZMjAyMy4uLi5FVVIBAAAAFKEBAAIAAAALMjUyNDUsNDczNjkBDgAAAAUAAAABMwEAAAABMAIAAAAKMTAwMTU3NjIzMgMAAAAGMTAwMTg3BAAAAAEzBgAAAAEwBwAAAAI1MAgAAAABMAkAAAABMQoAAAABMAsAAAALMTM2OTExODIyOTgMAAAAATENAAAACDYvNi8yMDI0EAAAAAoxMi8zMS8yMDIz9C+50nmF3AjoqvjSeYXcCCxDSVEuWFRSQTpHMUEuSVFfRUJJVERBX0VTVF9DSVEuRlkyMDI2Li4uLkVVUgEAAAAyVw0AAgAAAAk4NzcsMDM0NzIBDgAAAAUAAAABMwEAAAABMAIAAAAKMTAwMTU0ODA4OQMAAAAGMTAwMTg3BAAAAAEzBgAAAAEwBwAAAAI1MAgAAAABMAkAAAABMQoAAAABMAsAAAALMTM3OTQyMzg3MzQMAAAAATENAAAACDYvNy8yMDI0EAAAAAg2LzYvMjAyNDgTBXQ2htwIL39HdTaG3AgTQ0lRLi5JUV9SRVYuLi4uLkVVUgUAAAABAAAACAAAABQoSW52YWxpZCBJZGVudGlmaWVyKWeyOHU2 | AP1: htwIZ7I4dTaG3AgnQ0lRLiRFVVJDQUQuSVFfTEFTVFNBTEVQUklDRS4zMS4wNS4yMDIzAQAAALjrWgACAAAACzAsNjkwNTUxMDEzAPQvudJ5hdwIYyP30nmF3AgkQ0lRLlhUUkE6S1JOLklRX0VCSVRfRVNUX0NJUS4uLi4uRVVSAQAAAMFhDQACAAAACDM5NSwwNDY5AQ4AAAAFAAAAAjExAQAAAAEwAgAAAAkxODAxMzU5MjQDAAAABjEwMDIxNQQAAAABMwYAAAABMAcAAAACNTAIAAAAATAJAAAAATEKAAAAATALAAAACzEzNzk0OTgzMjIyDAAAAAIxMg0AAAAINi82LzIwMjQQAAAACDYvNS8yMDI0NdaPunmF3AjbM1N0NobcCCRDSVEuWFRSQTpNQkcuSVFfRUJJVF9FU1RfQ0lRLi4uLi5FVVIBAAAAFKEBAAIAAAAKMTY3MjEsODA1MwEOAAAABQAAAAIxMQEAAAABMAIAAAAJMTc0NjQ2MDY1AwAAAAYxMDAyMTUEAAAAATMGAAAAATAHAAAAAjUwCAAAAAEwCQAAAAExCgAAAAEwCwAAAAsxMzgwNjY4MzAzNgwAAAACMTINAAAACDYvNi8yMDI0EAAAAAg2LzUvMjAyNHJ7PdN5hdwIcns903mF3AghQ0lRLlRTRTo2NzcwLklRX1JFVi5GWTIwMjIuLi4uRVVSAQAAAE9YDQACAAAACjU5NTEsNjIwOTMBCAAAAAUAAAABMQEAAAALLTIwOTAzNDA4ODkDAAAAAjUwAgAAAAMxMTIEAAAAATAHAAAACDYvNS8yMDI0CAAAAAkzLzMxLzIwMjIJAAAAATAsCbnSeYXcCDT4+NJ5hdwIKkNJUS5YVFJBOk1CRy5JUV9FQklUX0VTVF9D | AQ1: SVEuRlkyMDI1Li4uLkVVUgEAAAAUoQEAAgAAAAsxNjgzNSw1ODQ1OQEOAAAABQAAAAEzAQAAAAEwAgAAAAoxMDAxNjU4Nzg1AwAAAAYxMDAyMTUEAAAAATMGAAAAATAHAAAAAjUwCAAAAAEwCQAAAAExCgAAAAEwCwAAAAsxMzgwNjY4MjM5MAwAAAABMQ0AAAAINi82LzIwMjQQAAAACDYvNS8yMDI09C+50nmF3AiklUPTeYXcCCJDSVEuVFNFOjYxNDEuSVFfRUJJVC5GWTIwMjMuLi4uRVVSAQAAANBcDQACAAAACjMyNSwzMzA1NDkBCAAAAAUAAAABMQEAAAALLTIwMDI5Njg4MDADAAAAAjUwAgAAAAM0MDAEAAAAATAHAAAACDYvNi8yMDI0CAAAAAoxMi8zMS8yMDIzCQAAAAEw+sUEdDaG3Aj1TVl0NobcCChDSVEuVFNFOjY3NzAuSVFfTUFSS0VUQ0FQLjMxLjA1LjIwMjMuRVVSAQAAAE9YDQACAAAAEDE3MDAsMDc2NDQzMjczMjEBBgAAAAUAAAABMQEAAAALLTIwNDg5MzkwNTQDAAAAAjUwAgAAAAYxMDAwNTQEAAAAATAHAAAACTUvMzEvMjAyMywJudJ5hdwI9zT40nmF3AgmQ0lRLlhUUkE6REVaLklRX0VCSVREQV9FU1RfQ0lRLi4uLi5FVVIBAAAAVnAJAAIAAAAIMjE4LDg2ODMBDgAAAAUAAAACMTEBAAAAATACAAAABzE5MjQ5NjUDAAAABjEwMDE4NwQAAAABMwYAAAABMAcAAAACNTAIAAAAATAJAAAAATEKAAAAATALAAAACzEzNzYwOTI2NjI1DAAAAAIxMg0AAAAINi83LzIwMjQQAAAACDYvNi8yMDI0Vtk4 | AR1: dTaG3AhW2Th1NobcCDBDSVEuT1RDQ0g6MDAxMjY4NDY1LklRX05JX0VTVF9OT1RFLkZZMjAyMy4uLi5FVVIBAAAAflkNAAMAAAAAAPQJ6CV6hdwI1mryJXqF3AgoQ0lRLk9NOkFMRkEuSVFfTklfRVNUX05PVEUuRlkyMDI1Li4uLkVVUgEAAAA4aAYAAwAAACpJbmNsdWRlcyBBbW9ydGl6YXRpb24gb2YgSW50YW5naWJsZSBBc3NldHMA/j0tK3qF3AgciTgreoXcCCdDSVEuJEVVUkVVUi5JUV9MQVNUU0FMRVBSSUNFLjMxLjA1LjIwMjQBAAAAuOtaAAIAAAABMQD6xQR0NobcCAiTVHQ2htwIHkNJUS5YVFJBOktSTi5JUV9OSV9FU1QuLi4uLkVVUgEAAADBYQ0AAgAAAAgyOTEsMTg3NAEOAAAABQAAAAIxMQEAAAABMAIAAAAJMTgwMTM1OTI0AwAAAAYxMDAyNTAEAAAAATMGAAAAATAHAAAAAjUwCAAAAAEwCQAAAAExCgAAAAEwCwAAAAsxMzc5MTg3ODM2MwwAAAACMTINAAAACDYvNi8yMDI0EAAAAAg2LzUvMjAyNGBB3HZ6hdwI2zNTdDaG3AgkQ0lRLlRTRTo2MTQxLklRX05JX0VTVC5GWTIwMjUuLi4uRVVSAQAAANBcDQADAAAAAABx7AR0NobcCJnYWHQ2htwIK0NJUS5PVENDSDowMDEyNjg0NjUuSVFfRUJJVF9FU1RfQ0lRLi4uLi5FVVIBAAAAflkNAAMAAAAAADXWj7p5hdwIIgqb2XmF3AgkQ0lRLlhUUkE6S1JOLklRX0VCSVREQS5GWTIwMjMuLi4uRVVSAQAAAMFhDQACAAAABzQ2Myw0MzQBCAAAAAUAAAAB | AS1: MQEAAAALLTIwMDUwODcwMDQDAAAAAjUwAgAAAAQ0MDUxBAAAAAEwBwAAAAg2LzYvMjAyNAgAAAAKMTIvMzEvMjAyMwkAAAABMPrFBHQ2htwIlSZZdDaG3AgfQ0lRLi5JUV9SRVZFTlVFX0VTVF9DSVEuLi4uLkVVUgUAAAABAAAACAAAABQoSW52YWxpZCBJZGVudGlmaWVyKWeyOHU2htwIZ7I4dTaG3AgsQ0lRLlhUUkE6RzFBLklRX0VCSVREQV9FU1RfQ0lRLkZZMjAyMy4uLi5FVVIBAAAAMlcNAAIAAAAJNzc3LDgwNjQ1AQ4AAAAFAAAAATMBAAAAATACAAAACjEwMDE1NDgwNzQDAAAABjEwMDE4NwQAAAABMwYAAAABMAcAAAACNTAIAAAAATAJAAAAATEKAAAAATALAAAACzEzNjY5MjA0NTY3DAAAAAExDQAAAAg2LzYvMjAyNBAAAAAKMTIvMzEvMjAyM/QvudJ5hdwI1b/30nmF3AgiQ0lRLk5ZU0U6QVBUVi5JUV9SRVYuRlkyMDIyLi4uLkVVUgEAAABU74sDAgAAAAoxNjM2NCw0NTczAQgAAAAFAAAAATEBAAAACy0yMDExNDkzMDA2AwAAAAI1MAIAAAADMTEyBAAAAAEwBwAAAAg2LzUvMjAyNAgAAAAKMTIvMzEvMjAyMgkAAAABMCwJudJ5hdwIl9H40nmF3AgpQ0lRLlhUUkE6RFVFLklRX05JX0VTVF9OT1RFLkZZMjAyNS4uLi5FVVIBAAAAtHMNAAMAAABPSW5jbHVkZXMgQW1vcnRpemF0aW9uIG9mIEludGFuZ2libGUgQXNzZXRzIGFuZCBTdG9jayBCYXNlZCBDb21wZW5zYXRpb24gRXhwZW5zZQAxFy0reoXc | AT1: CC2wOCt6hdwIKUNJUS5PTTpBTEZBLklRX0VCSVRfRVNUX0NJUS5GWTIwMjUuLi4uRVVSAQAAADhoBgACAAAAEDEwODcsODgwMzQxODA4NjQBDgAAAAUAAAABMwEAAAABMAIAAAAKMTAwMTE2MDU1MQMAAAAGMTAwMjE1BAAAAAEzBgAAAAEwBwAAAAI1MAgAAAABMAkAAAABMQoAAAABMAsAAAALMTM4MDMzMTg2MTcMAAAAATENAAAACDYvNy8yMDI0EAAAAAg2LzYvMjAyNHHsBHQ2htwIMo5YdDaG3AgtQ0lRLk5ZU0U6QVBUVi5JUV9FQklUREFfRVNUX0NJUS5GWTIwMjQuLi4uRVVSAQAAAFTviwMCAAAAEDI5NTcsMzIwMjEwMDQyNzQBDgAAAAUAAAABMwEAAAABMAIAAAAKMTAwMzM2ODA0NgMAAAAGMTAwMTg3BAAAAAEyBgAAAAEwBwAAAAI1MAgAAAABMAkAAAABMQoAAAABMAsAAAALMTM3OTgwNjcxMDIMAAAAATENAAAACDYvNi8yMDI0EAAAAAg2LzUvMjAyNPQvudJ5hdwIzg340nmF3AgtQ0lRLlhUUkE6S1JOLklRX1JFVkVOVUVfRVNUX0NJUS5GWTIwMjQuLi4uRVVSAQAAAMFhDQACAAAACjUyOTAsOTE5NDkBDgAAAAUAAAABMwEAAAABMAIAAAAKMTAwMTU4MjAxNgMAAAAGMTAwMTgwBAAAAAEzBgAAAAEwBwAAAAI1MAgAAAABMAkAAAABMQoAAAABMAsAAAALMTM3OTQ5ODEzNzcMAAAAATENAAAACDYvNy8yMDI0EAAAAAg2LzYvMjAyNDgTBXQ2htwIL39HdTaG3AgsQ0lRLlhUUkE6REVaLklRX0VCSVREQV9F | AU1: U1RfQ0lRLkZZMjAyNC4uLi5FVVIBAAAAVnAJAAIAAAAFMjA5LDcBDgAAAAUAAAABMwEAAAABMAIAAAAKMTAwMzQ0ODE1MwMAAAAGMTAwMTg3BAAAAAEzBgAAAAEwBwAAAAI1MAgAAAABMAkAAAABMQoAAAABMAsAAAALMTM3NjA5MjMwNTcMAAAAATENAAAACDYvNy8yMDI0EAAAAAg2LzYvMjAyNHHsBHQ2htwIwjFHdTaG3AgqQ0lRLlhUUkE6REVaLklRX0VCSVRfRVNUX0NJUS5GWTIwMjQuLi4uRVVSAQAAAFZwCQACAAAABjExNiw2OAEOAAAABQAAAAEzAQAAAAEwAgAAAAoxMDAzNDQ4MTUzAwAAAAYxMDAyMTUEAAAAATMGAAAAATAHAAAAAjUwCAAAAAEwCQAAAAExCgAAAAEwCwAAAAsxMzc1MzE1MzQ0MQwAAAABMQ0AAAAINi83LzIwMjQQAAAACDYvNi8yMDI0cewEdDaG3AiVJll0NobcCCZDSVEuWFRSQTpHMUEuSVFfRUJJVERBX0VTVF9DSVEuLi4uLkVVUgEAAAAyVw0AAgAAAAg4MTAsMDg5NwEOAAAABQAAAAIxMQEAAAABMAIAAAAJMTQ5NzU3NTAzAwAAAAYxMDAxODcEAAAAATMGAAAAATAHAAAAAjUwCAAAAAEwCQAAAAExCgAAAAEwCwAAAAsxMzgwMDc0NzIyOQwAAAACMTINAAAACDYvNy8yMDI0EAAAAAg2LzYvMjAyNFbZOHU2htwIVtk4dTaG3AgbQ0lRLlRTWDpMTlIuSVFfRUJJVC4uLi4uRVVSAQAAAHZfDQACAAAACjU5MywzOTQ3OTIBCAAAAAUAAAABMQEAAAALLTE5OTU5MTQ5NjQDAAAAAjUwAgAA | AV1: AAM0MDAEAAAAATAHAAAACDYvNS8yMDI0CAAAAAkzLzMxLzIwMjQJAAAAATByez3TeYXcCHJ7PdN5hdwILUNJUS5UU0U6NjkwMi5JUV9SRVZFTlVFX0VTVF9DSVEuRlkyMDI1Li4uLkVVUgEAAAA8Vg0AAgAAABA0NDEwNyw5MzQyNzM4OTYyAQ4AAAAFAAAAATMBAAAAATACAAAACjEwMDMxOTczNTQDAAAABjEwMDE4MAQAAAABMwYAAAABMAcAAAACNTAIAAAAATAJAAAAATEKAAAAATALAAAACzEzODA4NDU4MTkyDAAAAAExDQAAAAg2LzYvMjAyNBAAAAAINi81LzIwMjT0L7nSeYXcCE/89tJ5hdwIKENJUS5YVFJBOkcxQS5JUV9NQVJLRVRDQVAuMzEuMDUuMjAyNC5FVVIBAAAAMlcNAAIAAAAKNjQ0MSw0Njk5NgEGAAAABQAAAAExAQAAAAstMTk5NTcxODQ5MQMAAAACNTACAAAABjEwMDA1NAQAAAABMAcAAAAJNS8zMS8yMDI0+sUEdDaG3AiMz1N0NobcCB1DSVEuRU5YVFBBOkZSLklRX0VCSVQuLi4uLkVVUgEAAACGgAoAAgAAAAM3OTIBCAAAAAUAAAABMQEAAAALLTIwMDc5NzE1OTADAAAAAjUwAgAAAAM0MDAEAAAAATAHAAAACDYvNS8yMDI0CAAAAAoxMi8zMS8yMDIzCQAAAAEwcns903mF3Ahyez3TeYXcCCpDSVEuWFRSQTpLUk4uSVFfRUJJVF9FU1RfQ0lRLkZZMjAyNi4uLi5FVVIBAAAAwWENAAIAAAAJNTA2LDc5NjI0AQ4AAAAFAAAAATMBAAAAATACAAAACjEwMDI2MDY1NDkDAAAABjEwMDIxNQQAAAAB | AW1: MwYAAAABMAcAAAACNTAIAAAAATAJAAAAATEKAAAAATALAAAACzEzNzk0OTgxMjIxDAAAAAExDQAAAAg2LzcvMjAyNBAAAAAINi82LzIwMjQ4EwV0NobcCF7uV3Q2htwIHENJUS5YVFJBOkcxQS5JUV9FQklULi4uLi5FVVIBAAAAMlcNAAIAAAAHNTA5LDI3MQEIAAAABQAAAAExAQAAAAstMTk5NTcxNzg1NAMAAAACNTACAAAAAzQwMAQAAAABMAcAAAAINi81LzIwMjQIAAAACTMvMzEvMjAyNAkAAAABMHJ7PdN5hdwIlIFTdDaG3AgkQ0lRLlhUUkE6RzFBLklRX0VCSVREQS5GWTIwMjMuLi4uRVVSAQAAADJXDQACAAAABzU5NywwODEBCAAAAAUAAAABMQEAAAALLTIwMDcwMzM2MzIDAAAAAjUwAgAAAAQ0MDUxBAAAAAEwBwAAAAg2LzYvMjAyNAgAAAAKMTIvMzEvMjAyMwkAAAABMPrFBHQ2htwIlSZZdDaG3AgtQ0lRLlhUUkE6Qk1XLklRX1JFVkVOVUVfRVNUX0NJUS5GWTIwMjMuLi4uRVVSAQAAAHrACgACAAAACzE1MzU3MSw3OTA3AQ4AAAAFAAAAATMBAAAAATACAAAACjEwMDE1ODcxMzEDAAAABjEwMDE4MAQAAAABMwYAAAABMAcAAAACNTAIAAAAATAJAAAAATEKAAAAATALAAAACzEzNjk0NDc0NzIyDAAAAAExDQAAAAg2LzYvMjAyNBAAAAAKMTIvMzEvMjAyM/QvudJ5hdwI6Kr40nmF3AgpQ0lRLlRTRTo2MTQxLklRX05JX0VTVF9OT1RFLkZZMjAyNi4uLi5FVVIBAAAA0FwNAAMAAAAAAP49LSt6hdwIHIk4 | AX1: K3qF3AgtQ0lRLlhUUkE6RzFBLklRX1JFVkVOVUVfRVNUX0NJUS5GWTIwMjQuLi4uRVVSAQAAADJXDQACAAAACjU0NjgsOTk4MjIBDgAAAAUAAAABMwEAAAABMAIAAAAKMTAwMTU0ODA3OQMAAAAGMTAwMTgwBAAAAAEzBgAAAAEwBwAAAAI1MAgAAAABMAkAAAABMQoAAAABMAsAAAALMTM4MDA3NDY0MTUMAAAAATENAAAACDYvNy8yMDI0EAAAAAg2LzYvMjAyNDgTBXQ2htwIL39HdTaG3AgvQ0lRLk9UQ0NIOjAwMTI2ODQ2NS5JUV9NQVJLRVRDQVAuMzEuMDUuMjAyNC5FVVIBAAAAflkNAAIAAAAQOTY1LDk2MjEyMDA2NDM2NQEGAAAABQAAAAExAQAAAAstMjAwODMyMDMxOQMAAAACNTACAAAABjEwMDA1NAQAAAABMAcAAAAJNS8zMS8yMDI0+sUEdDaG3AgxCkd1NobcCCpDSVEuWFRSQTpHMUEuSVFfRUJJVF9FU1RfQ0lRLkZZMjAyNS4uLi5FVVIBAAAAMlcNAAIAAAAJNjQ3LDk5MTk0AQ4AAAAFAAAAATMBAAAAATACAAAACjEwMDE1NDgwODQDAAAABjEwMDIxNQQAAAABMwYAAAABMAcAAAACNTAIAAAAATAJAAAAATEKAAAAATALAAAACzEzODAwNzQ2MjY1DAAAAAExDQAAAAg2LzcvMjAyNBAAAAAINi82LzIwMjQ4EwV0NobcCL2xWHQ2htwIHkNJUS5YVFJBOkRFWi5JUV9OSV9FU1QuLi4uLkVVUgEAAABWcAkAAgAAAAY5NSwxNTUBDgAAAAUAAAACMTEBAAAAATACAAAABzE5MjQ5NjUDAAAABjEwMDI1MAQAAAAB | AY1: MwYAAAABMAcAAAACNTAIAAAAATAJAAAAATEKAAAAATALAAAACzEzODAwNzIxOTUyDAAAAAIxMg0AAAAINi82LzIwMjQQAAAACDYvNS8yMDI0YEHcdnqF3Ajta1R0NobcCCVDSVEuRU5YVFBBOkZSLklRX0VCSVRfRVNUX0NJUS4uLi4uRVVSAQAAAIaACgACAAAACTk3NCwxNTk4NwEOAAAABQAAAAIxMQEAAAABMAIAAAAKMTAwMjM1ODE5NQMAAAAGMTAwMjE1BAAAAAEzBgAAAAEwBwAAAAI1MAgAAAABMAkAAAABMQoAAAABMAsAAAALMTM4MDc4NDE4NDgMAAAAAjEyDQAAAAg2LzYvMjAyNBAAAAAINi81LzIwMjRyez3TeYXcCHJ7PdN5hdwIKkNJUS5YVFJBOkRVRS5JUV9FQklUX0VTVF9DSVEuRlkyMDI1Li4uLkVVUgEAAAC0cw0AAgAAAAYzMjIsNjUBDgAAAAUAAAABMwEAAAABMAIAAAAKMTAwMTQ3MDM4NAMAAAAGMTAwMjE1BAAAAAEzBgAAAAEwBwAAAAI1MAgAAAABMAkAAAABMQoAAAABMAsAAAALMTM4MDgyNDA3NDUMAAAAATENAAAACDYvNy8yMDI0EAAAAAg2LzYvMjAyNHHsBHQ2htwIMo5YdDaG3AgsQ0lRLlhUUkE6S1JOLklRX0VCSVREQV9FU1RfQ0lRLkZZMjAyNS4uLi5FVVIBAAAAwWENAAIAAAAJNjE2LDUxNDUxAQ4AAAAFAAAAATMBAAAAATACAAAACjEwMDE2ODA0NTcDAAAABjEwMDE4NwQAAAABMwYAAAABMAcAAAACNTAIAAAAATAJAAAAATEKAAAAATALAAAACzEzNzk0OTgxMjgxDAAAAAExDQAA | AZ1: AAg2LzcvMjAyNBAAAAAINi82LzIwMjQ4EwV0NobcCNWmR3U2htwIJENJUS5YVFJBOkRVRS5JUV9OSV9FU1QuRlkyMDI1Li4uLkVVUgEAAAC0cw0AAgAAAAgxOTgsMjUwOQEOAAAABQAAAAEzAQAAAAEwAgAAAAoxMDAxNDcwMzg0AwAAAAYxMDAyNTAEAAAAATMGAAAAATAHAAAAAjUwCAAAAAEwCQAAAAExCgAAAAEwCwAAAAsxMzgwODI0MDczOQwAAAABMQ0AAAAINi83LzIwMjQQAAAACDYvNi8yMDI0cewEdDaG3AiZ2Fh0NobcCCxDSVEuWFRSQTpERVouSVFfRUJJVERBX0VTVF9DSVEuRlkyMDI2Li4uLkVVUgEAAABWcAkAAgAAAAkyNzcsMTYwNTIBDgAAAAUAAAABMwEAAAABMAIAAAAKMTAwMzY2NDM3MwMAAAAGMTAwMTg3BAAAAAEzBgAAAAEwBwAAAAI1MAgAAAABMAkAAAABMQoAAAABMAsAAAALMTM3NTYzNDE4MTQMAAAAATENAAAACDYvNy8yMDI0EAAAAAg2LzYvMjAyNHHsBHQ2htwISFhHdTaG3AgqQ0lRLlRTRTo2NDA3LklRX0VCSVRfRVNUX0NJUS5GWTIwMjUuLi4uRVVSAQAAAJddDQACAAAAEDEwNiw5MjU5Mzg2NDk5ODUBDgAAAAUAAAABMwEAAAABMAIAAAAKMTAwMzg5OTk5MwMAAAAGMTAwMjE1BAAAAAI1NgYAAAABMAcAAAACNTAIAAAAATAJAAAAATEKAAAAATALAAAACzEzODAzMjE1NTcxDAAAAAExDQAAAAg2LzcvMjAyNBAAAAAINi82LzIwMjRx7AR0NobcCDKOWHQ2htwIKkNJUS5YVFJBOkRF | BA1: Wi5JUV9FQklUX0VTVF9DSVEuRlkyMDI2Li4uLkVVUgEAAABWcAkAAgAAAAUxODAsOAEOAAAABQAAAAEzAQAAAAEwAgAAAAoxMDAzNjY0MzczAwAAAAYxMDAyMTUEAAAAATMGAAAAATAHAAAAAjUwCAAAAAEwCQAAAAExCgAAAAEwCwAAAAsxMzc1MzE1MzUxOQwAAAABMQ0AAAAINi83LzIwMjQQAAAACDYvNi8yMDI0cewEdDaG3Ahe7ld0NobcCCxDSVEuVFNFOjY0MDcuSVFfRUJJVERBX0VTVF9DSVEuRlkyMDI1Li4uLkVVUgEAAACXXQ0AAgAAABAxNTMsMjYyMTg0NTQwOTMzAQ4AAAAFAAAAATMBAAAAATACAAAACjEwMDM4OTk5OTMDAAAABjEwMDE4NwQAAAACNTYGAAAAATAHAAAAAjUwCAAAAAEwCQAAAAExCgAAAAEwCwAAAAsxMzc5OTc3NjU2OQwAAAABMQ0AAAAINi83LzIwMjQQAAAACDYvNi8yMDI0cewEdDaG3AjCMUd1NobcCCtDSVEuTllTRTpBUFRWLklRX0VCSVRfRVNUX0NJUS5GWTIwMjMuLi4uRVVSAQAAAFTviwMCAAAADzE5MzAsNjg5MDQ5MzkzNAEOAAAABQAAAAEzAQAAAAEwAgAAAAoxMDAzMzY4MDQ1AwAAAAYxMDAyMTUEAAAAATIGAAAAATAHAAAAAjUwCAAAAAEwCQAAAAExCgAAAAEwCwAAAAsxMzYzMTEzNzM5OQwAAAABMQ0AAAAINi82LzIwMjQQAAAACjEyLzMxLzIwMjP0L7nSeYXcCKLm99J5hdwINENJUS5PVENDSDowMDEyNjg0NjUuSVFfUkVWRU5VRV9FU1RfQ0lRLkZZMjAyNS4uLi5F | BB1: VVIBAAAAflkNAAMAAAAAAHHsBHQ2htwIMQpHdTaG3AgqQ0lRLlhUUkE6S1JOLklRX0VCSVRfRVNUX0NJUS5GWTIwMjQuLi4uRVVSAQAAAMFhDQACAAAACTM3NSwxNDcwNwEOAAAABQAAAAEzAQAAAAEwAgAAAAoxMDAxNTgyMDE2AwAAAAYxMDAyMTUEAAAAATMGAAAAATAHAAAAAjUwCAAAAAEwCQAAAAExCgAAAAEwCwAAAAsxMzc5NDk4MTMzNQwAAAABMQ0AAAAINi83LzIwMjQQAAAACDYvNi8yMDI0OBMFdDaG3Aj1TVl0NobcCCNDSVEuRU5YVFBBOkZSLklRX0VCSVQuRlkyMDIyLi4uLkVVUgEAAACGgAoAAgAAAAM1OTQBCAAAAAUAAAABMQEAAAALLTIwMDc5NzM1NTYDAAAAAjUwAgAAAAM0MDAEAAAAATAHAAAACDYvNS8yMDI0CAAAAAoxMi8zMS8yMDIyCQAAAAEw9C+50nmF3AiklUPTeYXcCCpDSVEuVFNFOjY5MDIuSVFfRUJJVF9FU1RfQ0lRLkZZMjAyNC4uLi5FVVIBAAAAPFYNAAIAAAAQMjk0Myw2MTMwMTU5NDU5NgEOAAAABQAAAAEzAQAAAAEwAgAAAAoxMDAyODg1NzIxAwAAAAYxMDAyMTUEAAAAATMGAAAAATAHAAAAAjUwCAAAAAEwCQAAAAExCgAAAAEwCwAAAAsxMzc0NTkxODkxNQwAAAABMQ0AAAAINi82LzIwMjQQAAAACTMvMzEvMjAyNPQvudJ5hdwIl9H40nmF3AgcQ0lRLlRTRTo2MTQxLklRX0VCSVQuLi4uLkVVUgEAAADQXA0AAgAAAAozMTcsMjI1MjU3AQgAAAAFAAAAATEBAAAACy0xOTkz | BC1: OTY3MzAyAwAAAAI1MAIAAAADNDAwBAAAAAEwBwAAAAg2LzUvMjAyNAgAAAAJMy8zMS8yMDI0CQAAAAEwYEHcdnqF3AjSRFR0NobcCCtDSVEuVFNYOkxOUi5JUV9FQklUREFfRVNUX0NJUS5GWTIwMjQuLi4uRVVSAQAAAHZfDQACAAAAEDEwNDMsNjQ1NzU0MTU5MjcBDgAAAAUAAAABMwEAAAABMAIAAAAKMTAwMjM3OTM0NQMAAAAGMTAwMTg3BAAAAAEzBgAAAAEwBwAAAAI1MAgAAAABMAkAAAABMQoAAAABMAsAAAALMTM4MDA3OTU5NTkMAAAAATENAAAACDYvNi8yMDI0EAAAAAg2LzUvMjAyNPFWudJ5hdwIT/z20nmF3AgeQ0lRLlhUUkE6REVaLklRX0VCSVREQS4uLi4uRVVSAQAAAFZwCQACAAAABTE3NiwxAQgAAAAFAAAAATEBAAAACy0xOTk3NTAwNDU2AwAAAAI1MAIAAAAENDA1MQQAAAABMAcAAAAINi81LzIwMjQIAAAACTMvMzEvMjAyNAkAAAABMGBB3HZ6hdwICJNUdDaG3AgpQ0lRLlRTRTo2MTQxLklRX05JX0VTVF9OT1RFLkZZMjAyNC4uLi5FVVIBAAAA0FwNAAMAAAAAAP49LSt6hdwIHIk4K3qF3AgmQ0lRLlhUUkE6RFVFLklRX0VCSVREQV9FU1RfQ0lRLi4uLi5FVVIBAAAAtHMNAAIAAAAINDA2LDM2NzgBDgAAAAUAAAACMTEBAAAAATACAAAACDU3NDc2NTQzAwAAAAYxMDAxODcEAAAAATMGAAAAATAHAAAAAjUwCAAAAAEwCQAAAAExCgAAAAEwCwAAAAsxMzgwODI0MTM4MQwAAAACMTINAAAACDYv | BD1: Ny8yMDI0EAAAAAg2LzYvMjAyNFbZOHU2htwIVtk4dTaG3AgtQ0lRLlhUUkE6RzFBLklRX1JFVkVOVUVfRVNUX0NJUS5GWTIwMjYuLi4uRVVSAQAAADJXDQACAAAACjU4NDQsMjgxNjIBDgAAAAUAAAABMwEAAAABMAIAAAAKMTAwMTU0ODA4OQMAAAAGMTAwMTgwBAAAAAEzBgAAAAEwBwAAAAI1MAgAAAABMAkAAAABMQoAAAABMAsAAAALMTM3OTk2MTg2MDMMAAAAATENAAAACDYvNy8yMDI0EAAAAAg2LzYvMjAyNDgTBXQ2htwIL39HdTaG3AggQ0lRLlhUUkE6RzFBLklRX05JLkZZMjAyMy4uLi5FVVIBAAAAMlcNAAIAAAAHMzkyLDc2NQEIAAAABQAAAAExAQAAAAstMjAwNzAzMzYzMgMAAAACNTACAAAAAjE1BAAAAAEwBwAAAAg2LzYvMjAyNAgAAAAKMTIvMzEvMjAyMwkAAAABMPrFBHQ2htwIw3RZdDaG3AgeQ0lRLi5JUV9FQklUREFfRVNUX0NJUS4uLi4uRVVSBQAAAAEAAAAIAAAAFChJbnZhbGlkIElkZW50aWZpZXIpZ7I4dTaG3Ahnsjh1NobcCCFDSVEuWFRSQTpHMUEuSVFfUkVWLkZZMjAyMi4uLi5FVVIBAAAAMlcNAAIAAAAINTE2NCw3MTQBCAAAAAUAAAABMQEAAAALLTIwMDcwMzM2MzEDAAAAAjUwAgAAAAMxMTIEAAAAATAHAAAACDYvNS8yMDI0CAAAAAoxMi8zMS8yMDIyCQAAAAEw9C+50nmF3Aii5vfSeYXcCCRDSVEuVFNFOjYxNDEuSVFfTklfRVNULkZZMjAyNC4uLi5FVVIBAAAA0FwNAAMAAAAA | BE1: AHHsBHQ2htwI9U1ZdDaG3AgtQ0lRLlRTRTo2NDA3LklRX1JFVkVOVUVfRVNUX0NJUS5GWTIwMjUuLi4uRVVSAQAAAJddDQACAAAAEDg4Miw2MDcwMzU1NTc4NDcBDgAAAAUAAAABMwEAAAABMAIAAAAKMTAwMzg5OTk5MwMAAAAGMTAwMTgwBAAAAAI1NgYAAAABMAcAAAACNTAIAAAAATAJAAAAATEKAAAAATALAAAACzEzODAzMjE1NTY1DAAAAAExDQAAAAg2LzcvMjAyNBAAAAAINi82LzIwMjRx7AR0NobcCMIxR3U2htwII0NJUS5PVENDSDowMDEyNjg0NjUuSVFfRUJJVC4uLi4uRVVSAQAAAH5ZDQACAAAACjE2MCw4MzYwMzMBCAAAAAUAAAABMQEAAAALLTIwMDgzMjAzMDkDAAAAAjUwAgAAAAM0MDAEAAAAATAHAAAACDYvNS8yMDI0CAAAAAoxMi8zMS8yMDIzCQAAAAEwYEHcdnqF3AhgQdx2eoXcCCpDSVEuVFNFOjY3NzAuSVFfRUJJVF9FU1RfQ0lRLkZZMjAyNC4uLi5FVVIBAAAAT1gNAAIAAAAQMTE4LDIwOTM1MjkwMDMwMwEOAAAABQAAAAEzAQAAAAEwAgAAAAoxMDAxOTcxNjI5AwAAAAYxMDAyMTUEAAAAAjU2BgAAAAEwBwAAAAI1MAgAAAABMAkAAAABMQoAAAABMAsAAAALMTM3NDAzNDI0MDYMAAAAATENAAAACDYvNi8yMDI0EAAAAAkzLzMxLzIwMjT0L7nSeYXcCPc0+NJ5hdwIJ0NJUS4kRVVSSlBZLklRX0xBU1RTQUxFUFJJQ0UuMzEuMDUuMjAyNAEAAAC461oAAgAAAAswLDAwNTg2NTE0MgD6xQR0 | BF1: NobcCPTgVHQ2htwIIkNJUS5YVFJBOk1CRy5JUV9FQklULkZZMjAyMi4uLi5FVVIBAAAAFKEBAAIAAAAFMTczMzMBCAAAAAUAAAABMQEAAAALLTIwMDU5OTUwMTQDAAAAAjUwAgAAAAM0MDAEAAAAATAHAAAACDYvNS8yMDI0CAAAAAoxMi8zMS8yMDIyCQAAAAEw9C+50nmF3AhNbkPTeYXcCCNDSVEuT006QUxGQS5JUV9OSV9FU1QuRlkyMDI0Li4uLkVVUgEAAAA4aAYAAgAAABA3MTUsNTgyMTc4Njg4OTY3AQ4AAAAFAAAAATMBAAAAATACAAAACjEwMDExNjA1NTADAAAABjEwMDI1MAQAAAABMwYAAAABMAcAAAACNTAIAAAAATAJAAAAATEKAAAAATALAAAACzEzODAzMzIwNDA5DAAAAAExDQAAAAg2LzcvMjAyNBAAAAAINi82LzIwMjRx7AR0NobcCPVNWXQ2htwIHENJUS5UU0U6NjkwMi5JUV9FQklULi4uLi5FVVIBAAAAPFYNAAIAAAALMjMzMiwzMzQyNjkBCAAAAAUAAAABMQEAAAALLTE5OTg5ODUyMTUDAAAAAjUwAgAAAAM0MDAEAAAAATAHAAAACDYvNS8yMDI0CAAAAAkzLzMxLzIwMjQJAAAAATByez3TeYXcCHJ7PdN5hdwII0NJUS5FTlhUUEE6TUMuSVFfRUJJVC5GWTIwMjIuLi4uRVVSAQAAAKD7AgACAAAABTIxMDE4AQgAAAAFAAAAATEBAAAACy0yMDEwNjAwNjcwAwAAAAI1MAIAAAADNDAwBAAAAAEwBwAAAAg2LzUvMjAyNAgAAAAKMTIvMzEvMjAyMgkAAAABMPQvudJ5hdwIpJVD03mF3AgoQ0lRLlRT | BG1: RTo2NDA3LklRX01BUktFVENBUC4zMS4wNS4yMDI0LkVVUgEAAACXXQ0AAgAAABAxMTk4LDI3OTU2MTYwMDE3AQYAAAAFAAAAATEBAAAACy0xOTk1MjM2MDgzAwAAAAI1MAIAAAAGMTAwMDU0BAAAAAEwBwAAAAk1LzMxLzIwMjT6xQR0NobcCPTgVHQ2htwILENJUS5PTTpBTEZBLklRX1JFVkVOVUVfRVNUX0NJUS5GWTIwMjUuLi4uRVVSAQAAADhoBgACAAAAEDY0NzcsODQ1Njg4MTYxNzMBDgAAAAUAAAABMwEAAAABMAIAAAAKMTAwMTE2MDU1MQMAAAAGMTAwMTgwBAAAAAEzBgAAAAEwBwAAAAI1MAgAAAABMAkAAAABMQoAAAABMAsAAAALMTM4MDMzMTg3MDEMAAAAATENAAAACDYvNy8yMDI0EAAAAAg2LzYvMjAyNHHsBHQ2htwIS+NGdTaG3AgsQ0lRLlRTWDpMTlIuSVFfUkVWRU5VRV9FU1RfQ0lRLkZZMjAyNC4uLi5FVVIBAAAAdl8NAAIAAAAQNzUxNSw4NDUyMzYxNzY3NAEOAAAABQAAAAEzAQAAAAEwAgAAAAoxMDAyMzc5MzQ1AwAAAAYxMDAxODAEAAAAATMGAAAAATAHAAAAAjUwCAAAAAEwCQAAAAExCgAAAAEwCwAAAAsxMzgwMDc5NTk3MQwAAAABMQ0AAAAINi82LzIwMjQQAAAACDYvNS8yMDI08Va50nmF3Aj3NPjSeYXcCCdDSVEuVFNFOjY0MDcuSVFfUkVWRU5VRV9FU1RfQ0lRLi4uLi5FVVIBAAAAl10NAAIAAAAQODgyLDYwNzAzNTU1Nzg0NwEOAAAABQAAAAIxMQEAAAABMAIAAAAKMTAwMzg5OTk5 | BH1: MwMAAAAGMTAwMTgwBAAAAAI1NgYAAAABMAcAAAACNTAIAAAAATAJAAAAATEKAAAAATALAAAACzEzODAzMjE1NTY1DAAAAAIxMg0AAAAINi83LzIwMjQQAAAACDYvNi8yMDI0Vtk4dTaG3AhW2Th1NobcCCpDSVEuVFNFOjYxNDEuSVFfRUJJVF9FU1RfQ0lRLkZZMjAyNS4uLi5FVVIBAAAA0FwNAAIAAAAQMzk3LDUxNjY2OTkwMDA2NAEOAAAABQAAAAEzAQAAAAEwAgAAAAoxMDAzNzU5NTc0AwAAAAYxMDAyMTUEAAAAATMGAAAAATAHAAAAAjUwCAAAAAEwCQAAAAExCgAAAAEwCwAAAAsxMzc1ODI1MjY0MwwAAAABMQ0AAAAINi83LzIwMjQQAAAACDYvNi8yMDI0cewEdDaG3Agyjlh0NobcCCdDSVEuVFNYOkxOUi5JUV9NQVJLRVRDQVAuMzEuMDUuMjAyMy5FVVIBAAAAdl8NAAIAAAAQMjU1Myw1NDg3MDE5ODM5OQEGAAAABQAAAAExAQAAAAstMjA0NjQ0ODA2MAMAAAACNTACAAAABjEwMDA1NAQAAAABMAcAAAAJNS8zMS8yMDIzLAm50nmF3Agrg/jSeYXcCCdDSVEuJEVVUlNFSy5JUV9MQVNUU0FMRVBSSUNFLjMxLjA1LjIwMjQBAAAAuOtaAAIAAAAKMCwwODc1MzQwMgD6xQR0NobcCGugV3Q2htwILENJUS5UU0U6NjQwNy5JUV9FQklUREFfRVNUX0NJUS5GWTIwMjQuLi4uRVVSAQAAAJddDQACAAAAEDExNyw4NTYwMTgyNzI4NzEBDgAAAAUAAAABMwEAAAABMAIAAAAKMTAwMzczNjI4NgMAAAAGMTAwMTg3BAAA | BI1: AAI1NgYAAAABMAcAAAACNTAIAAAAATAJAAAAATEKAAAAATALAAAACzEzNzMxODI5NjM0DAAAAAExDQAAAAg2LzcvMjAyNBAAAAAJMy8zMS8yMDI0cewEdDaG3AjCMUd1NobcCClDSVEuVFNYOkxOUi5JUV9FQklUX0VTVF9DSVEuRlkyMDI1Li4uLkVVUgEAAAB2Xw0AAgAAABA3MDQsNjIwODQ2OTg3MDg2AQ4AAAAFAAAAATMBAAAAATACAAAACjEwMDIzNzkzNDYDAAAABjEwMDIxNQQAAAABMwYAAAABMAcAAAACNTAIAAAAATAJAAAAATEKAAAAATALAAAACzEzODAwNzk1ODk5DAAAAAExDQAAAAg2LzYvMjAyNBAAAAAINi81LzIwMjTxVrnSeYXcCE1uQ9N5hdwIIENJUS4uSVFfTUFSS0VUQ0FQLjMxLjA1LjIwMjQuRVVSBQAAAAEAAAAIAAAAFChJbnZhbGlkIElkZW50aWZpZXIpZ7I4dTaG3Ahnsjh1NobcCCFDSVEuWFRSQTpEVUUuSVFfUkVWLkZZMjAyMy4uLi5FVVIBAAAAtHMNAAIAAAAINDYyNywzMzQBCAAAAAUAAAABMQEAAAALLTIwMDQxNDk5MjcDAAAAAjUwAgAAAAMxMTIEAAAAATAHAAAACDYvNi8yMDI0CAAAAAoxMi8zMS8yMDIzCQAAAAEw+sUEdDaG3AhIWEd1NobcCC1DSVEuWFRSQTpEVUUuSVFfUkVWRU5VRV9FU1RfQ0lRLkZZMjAyNS4uLi5FVVIBAAAAtHMNAAIAAAAKNDk5NywwNjkyNgEOAAAABQAAAAEzAQAAAAEwAgAAAAoxMDAxNDcwMzg0AwAAAAYxMDAxODAEAAAAATMGAAAAATAHAAAAAjUw | BJ1: CAAAAAEwCQAAAAExCgAAAAEwCwAAAAsxMzgwODI0MDgwNQwAAAABMQ0AAAAINi83LzIwMjQQAAAACDYvNi8yMDI0cewEdDaG3Agvf0d1NobcCBxDSVEuWFRSQTpCTVcuSVFfRUJJVC4uLi4uRVVSAQAAAHrACgACAAAABTE3MDY5AQgAAAAFAAAAATEBAAAACy0xOTk2MDkxOTg3AwAAAAI1MAIAAAADNDAwBAAAAAEwBwAAAAg2LzUvMjAyNAgAAAAJMy8zMS8yMDI0CQAAAAEwcns903mF3Ahyez3TeYXcCC5DSVEuRU5YVFBBOk1DLklRX1JFVkVOVUVfRVNUX0NJUS5GWTIwMjUuLi4uRVVSAQAAAKD7AgACAAAACzk2ODg5LDM2NzE5AQ4AAAAFAAAAATMBAAAAATACAAAACjEwMDE3NjMwODQDAAAABjEwMDE4MAQAAAABMwYAAAABMAcAAAACNTAIAAAAATAJAAAAATEKAAAAATALAAAACzEzODA3MDc1OTkwDAAAAAExDQAAAAg2LzYvMjAyNBAAAAAINi81LzIwMjTxVrnSeYXcCE/89tJ5hdwIKkNJUS5PVENDSDowMDEyNjg0NjUuSVFfTklfRVNUX05PVEUuLi4uLkVVUgEAAAB+WQ0AAwAAAAAAUvmVGnqF3AgS7+IgeoXcCC5DSVEuTllTRTpBUFRWLklRX1JFVkVOVUVfRVNUX0NJUS5GWTIwMjMuLi4uRVVSAQAAAFTviwMCAAAAEDE4MjYxLDc3NTI0NTQ0MDUBDgAAAAUAAAABMwEAAAABMAIAAAAKMTAwMzM2ODA0NQMAAAAGMTAwMTgwBAAAAAEyBgAAAAEwBwAAAAI1MAgAAAABMAkAAAABMQoAAAABMAsAAAALMTM2MzEx | BK1: Mzc0MTEMAAAAATENAAAACDYvNi8yMDI0EAAAAAoxMi8zMS8yMDIz9C+50nmF3Agrg/jSeYXcCCdDSVEuT1RDQ0g6MDAxMjY4NDY1LklRX05JLkZZMjAyMy4uLi5FVVIBAAAAflkNAAIAAAAKMTI3LDUyOTk3NAEIAAAABQAAAAExAQAAAAstMjAwODMyMjMxOQMAAAACNTACAAAAAjE1BAAAAAEwBwAAAAg2LzYvMjAyNAgAAAAKMTIvMzEvMjAyMwkAAAABMPrFBHQ2htwIw3RZdDaG3AgxQ0lRLk9UQ0NIOjAwMTI2ODQ2NS5JUV9FQklUX0VTVF9DSVEuRlkyMDI0Li4uLkVVUgEAAAB+WQ0AAwAAAAAAcewEdDaG3AiVJll0NobcCClDSVEuVFNYOkxOUi5JUV9FQklUX0VTVF9DSVEuRlkyMDIzLi4uLkVVUgEAAAB2Xw0AAgAAABA1MjksNjQ3ODIzNjgwMDA2AQ4AAAAFAAAAATMBAAAAATACAAAACjEwMDIzNzkzNDQDAAAABjEwMDIxNQQAAAABMwYAAAABMAcAAAACNTAIAAAAATAJAAAAATEKAAAAATALAAAACzEzNjc5NTYxMzA0DAAAAAExDQAAAAg2LzYvMjAyNBAAAAAKMTIvMzEvMjAyM/FWudJ5hdwIO9X20nmF3AgsQ0lRLlhUUkE6TUJHLklRX0VCSVREQV9FU1RfQ0lRLkZZMjAyNC4uLi5FVVIBAAAAFKEBAAIAAAALMjMxOTIsNDIxMzMBDgAAAAUAAAABMwEAAAABMAIAAAAKMTAwMTU3NjIzMwMAAAAGMTAwMTg3BAAAAAEzBgAAAAEwBwAAAAI1MAgAAAABMAkAAAABMQoAAAABMAsAAAALMTM4MDY2ODQwNTkMAAAA | BL1: ATENAAAACDYvNi8yMDI0EAAAAAg2LzUvMjAyNPQvudJ5hdwIzg340nmF3AgtQ0lRLlRTRTo2NzcwLklRX1JFVkVOVUVfRVNUX0NJUS5GWTIwMjUuLi4uRVVSAQAAAE9YDQACAAAADzU1MjAsMzQ0MDk0ODIyMwEOAAAABQAAAAEzAQAAAAEwAgAAAAoxMDAxOTcxNjM0AwAAAAYxMDAxODAEAAAAAjU2BgAAAAEwBwAAAAI1MAgAAAABMAkAAAABMQoAAAABMAsAAAALMTM4MDg3MjI4OTMMAAAAATENAAAACDYvNi8yMDI0EAAAAAg2LzUvMjAyNPQvudJ5hdwIeJj30nmF3AgnQ0lRLiRFVVJDSEYuSVFfTEFTVFNBTEVQUklDRS4zMS4wNS4yMDI0AQAAALjrWgACAAAACzEsMDIwNTUyNzIxAPrFBHQ2htwIUlZVdDaG3AghQ0lRLlhUUkE6REVaLklRX1JFVi5GWTIwMjMuLi4uRVVSAQAAAFZwCQACAAAABjIwNjMsMgEIAAAABQAAAAExAQAAAAstMjAwNTYzNTAyMgMAAAACNTACAAAAAzExMgQAAAABMAcAAAAINi82LzIwMjQIAAAACjEyLzMxLzIwMjMJAAAAATD6xQR0NobcCMIxR3U2htwILUNJUS5FTlhUUEE6RlIuSVFfRUJJVERBX0VTVF9DSVEuRlkyMDI1Li4uLkVVUgEAAACGgAoAAgAAAAozMjU1LDgwMTU3AQ4AAAAFAAAAATMBAAAAATACAAAACjEwMDM1MDA2NTIDAAAABjEwMDE4NwQAAAABMwYAAAABMAcAAAACNTAIAAAAATAJAAAAATEKAAAAATALAAAACzEzODA3ODQxNzg4DAAAAAExDQAAAAg2LzYvMjAyNBAA | BM1: AAAINi81LzIwMjTxVrnSeYXcCMNx99J5hdwIJ0NJUS5YVFJBOktSTi5JUV9SRVZFTlVFX0VTVF9DSVEuLi4uLkVVUgEAAADBYQ0AAgAAAAk1Mzg3LDIyNTYBDgAAAAUAAAACMTEBAAAAATACAAAACTE4MDEzNTkyNAMAAAAGMTAwMTgwBAAAAAEzBgAAAAEwBwAAAAI1MAgAAAABMAkAAAABMQoAAAABMAsAAAALMTM3OTQ5ODMyMTQMAAAAAjEyDQAAAAg2LzcvMjAyNBAAAAAINi82LzIwMjRW2Th1NobcCFbZOHU2htwIK0NJUS5PVENDSDowMDEyNjg0NjUuSVFfTklfRVNULkZZMjAyNS4uLi5FVVIBAAAAflkNAAMAAAAAAHHsBHQ2htwImdhYdDaG3AgtQ0lRLlRTRTo2OTAyLklRX1JFVkVOVUVfRVNUX0NJUS5GWTIwMjQuLi4uRVVSAQAAADxWDQACAAAAEDQzNzk4LDM1MTIwNjIwOTYBDgAAAAUAAAABMwEAAAABMAIAAAAKMTAwMjg4NTcyMQMAAAAGMTAwMTgwBAAAAAEzBgAAAAEwBwAAAAI1MAgAAAABMAkAAAABMQoAAAABMAsAAAALMTM3NDU5MTg5NDUMAAAAATENAAAACDYvNi8yMDI0EAAAAAkzLzMxLzIwMjT0L7nSeYXcCOiq+NJ5hdwIHENJUS4uSVFfRUJJVF9FU1RfQ0lRLi4uLi5FVVIFAAAAAAAAAAgAAAAUKEludmFsaWQgSWRlbnRpZmllcilgQdx2eoXcCEUvVXQ2htwILUNJUS5OWVNFOkFQVFYuSVFfRUJJVERBX0VTVF9DSVEuRlkyMDI1Li4uLkVVUgEAAABU74sDAgAAABAzMzQwLDI4OTc5NTczMjIz | BN1: AQ4AAAAFAAAAATMBAAAAATACAAAACjEwMDMzNjgwNDcDAAAABjEwMDE4NwQAAAABMgYAAAABMAcAAAACNTAIAAAAATAJAAAAATEKAAAAATALAAAACzEzNzk4MDY2OTc2DAAAAAExDQAAAAg2LzYvMjAyNBAAAAAINi81LzIwMjT0L7nSeYXcCBxc+NJ5hdwIJENJUS5YVFJBOkRVRS5JUV9OSV9FU1QuRlkyMDI2Li4uLkVVUgEAAAC0cw0AAgAAAAkyMjgsMTEwNjUBDgAAAAUAAAABMwEAAAABMAIAAAAKMTAwMTQ3MDM4NQMAAAAGMTAwMjUwBAAAAAEzBgAAAAEwBwAAAAI1MAgAAAABMAkAAAABMQoAAAABMAsAAAALMTM4MDgyNDA1MjMMAAAAATENAAAACDYvNy8yMDI0EAAAAAg2LzYvMjAyNHHsBHQ2htwI3RVYdDaG3AgzQ0lRLk9UQ0NIOjAwMTI2ODQ2NS5JUV9FQklUREFfRVNUX0NJUS5GWTIwMjQuLi4uRVVSAQAAAH5ZDQADAAAAAABx7AR0NobcCDEKR3U2htwIJENJUS5UU0U6NjQwNy5JUV9OSV9FU1QuRlkyMDI2Li4uLkVVUgEAAACXXQ0AAwAAAAAAcewEdDaG3AjdFVh0NobcCCdDSVEuWFRSQTpHMUEuSVFfUkVWRU5VRV9FU1RfQ0lRLi4uLi5FVVIBAAAAMlcNAAIAAAAJNTUwOSwzMjc0AQ4AAAAFAAAAAjExAQAAAAEwAgAAAAkxNDk3NTc1MDMDAAAABjEwMDE4MAQAAAABMwYAAAABMAcAAAACNTAIAAAAATAJAAAAATEKAAAAATALAAAACzEzODAwNzQ4MTY1DAAAAAIxMg0AAAAINi83LzIwMjQQAAAACDYv | BO1: Ni8yMDI0Vtk4dTaG3AhW2Th1NobcCCBDSVEuWFRSQTpERVouSVFfTkkuRlkyMDIzLi4uLkVVUgEAAABWcAkAAgAAAAQ4MSw5AQgAAAAFAAAAATEBAAAACy0yMDA1NjM1MDIyAwAAAAI1MAIAAAACMTUEAAAAATAHAAAACDYvNi8yMDI0CAAAAAoxMi8zMS8yMDIzCQAAAAEw+sUEdDaG3AjDdFl0NobcCCVDSVEuRU5YVFBBOkZSLklRX0VCSVREQS5GWTIwMjIuLi4uRVVSAQAAAIaACgACAAAABDE3MzkBCAAAAAUAAAABMQEAAAALLTIwMDc5NzM1NTYDAAAAAjUwAgAAAAQ0MDUxBAAAAAEwBwAAAAg2LzUvMjAyNAgAAAAKMTIvMzEvMjAyMgkAAAABMPQvudJ5hdwI6Kr40nmF3AgrQ0lRLkVOWFRQQTpNQy5JUV9FQklUX0VTVF9DSVEuRlkyMDI0Li4uLkVVUgEAAACg+wIAAgAAAAsyMzYzNCw1NTI4NgEOAAAABQAAAAEzAQAAAAEwAgAAAAoxMDAxNzYzMDgzAwAAAAYxMDAyMTUEAAAAATMGAAAAATAHAAAAAjUwCAAAAAEwCQAAAAExCgAAAAEwCwAAAAsxMzgwNzA3NjAwMgwAAAABMQ0AAAAINi82LzIwMjQQAAAACDYvNS8yMDI08Va50nmF3AjSS/fSeYXcCCFDSVEuVFNFOjYxNDEuSVFfUkVWLkZZMjAyMy4uLi5FVVIBAAAA0FwNAAIAAAALMzQ2MiwyMTI3NTcBCAAAAAUAAAABMQEAAAALLTIwMDI5Njg4MDADAAAAAjUwAgAAAAMxMTIEAAAAATAHAAAACDYvNi8yMDI0CAAAAAoxMi8zMS8yMDIzCQAAAAEw+sUEdDaG | BP1: 3AhIWEd1NobcCCRDSVEuVFNFOjYxNDEuSVFfTklfRVNULkZZMjAyNi4uLi5FVVIBAAAA0FwNAAMAAAAAAHHsBHQ2htwI3RVYdDaG3AgdQ0lRLk5ZU0U6QVBUVi5JUV9FQklULi4uLi5FVVIBAAAAVO+LAwIAAAAJMTgxMCwyMzU3AQgAAAAFAAAAATEBAAAACy0xOTk2NzAwNzIwAwAAAAI1MAIAAAADNDAwBAAAAAEwBwAAAAg2LzUvMjAyNAgAAAAJMy8zMS8yMDI0CQAAAAEwcns903mF3Ahyez3TeYXcCCVDSVEuTllTRTpBUFRWLklRX0VCSVRfRVNUX0NJUS4uLi4uRVVSAQAAAFTviwMCAAAADzIzNjIsNjMyMjg2NjI2NwEOAAAABQAAAAIxMQEAAAABMAIAAAAHMTkwODgwMgMAAAAGMTAwMjE1BAAAAAEyBgAAAAEwBwAAAAI1MAgAAAABMAkAAAABMQoAAAABMAsAAAALMTM3OTgwNjgzODIMAAAAAjEyDQAAAAg2LzYvMjAyNBAAAAAINi81LzIwMjRyez3TeYXcCHJ7PdN5hdwILENJUS5UU0U6Njc3MC5JUV9FQklUREFfRVNUX0NJUS5GWTIwMjQuLi4uRVVSAQAAAE9YDQACAAAAEDM1NywzODAwMjk1NTYyMzcBDgAAAAUAAAABMwEAAAABMAIAAAAKMTAwMTk3MTYyOQMAAAAGMTAwMTg3BAAAAAI1NgYAAAABMAcAAAACNTAIAAAAATAJAAAAATEKAAAAATALAAAACzEzNzQwMzM4MDgwDAAAAAExDQAAAAg2LzYvMjAyNBAAAAAJMy8zMS8yMDI09C+50nmF3Aii5vfSeYXcCCRDSVEuWFRSQTpCTVcuSVFfRUJJVF9FU1Rf | BQ1: Q0lRLi4uLi5FVVIBAAAAesAKAAIAAAAKMTYwMDksNTk1NwEOAAAABQAAAAIxMQEAAAABMAIAAAAJMTg1MTYxNTE4AwAAAAYxMDAyMTUEAAAAATMGAAAAATAHAAAAAjUwCAAAAAEwCQAAAAExCgAAAAEwCwAAAAsxMzgwNzg0MzY2NwwAAAACMTINAAAACDYvNi8yMDI0EAAAAAg2LzUvMjAyNHJ7PdN5hdwIcns903mF3AgkQ0lRLlhUUkE6REVaLklRX0VCSVRfRVNUX0NJUS4uLi4uRVVSAQAAAFZwCQACAAAABzEyNSwyMzUBDgAAAAUAAAACMTEBAAAAATACAAAABzE5MjQ5NjUDAAAABjEwMDIxNQQAAAABMwYAAAABMAcAAAACNTAIAAAAATAJAAAAATEKAAAAATALAAAACzEzNzk1MzA0ODk5DAAAAAIxMg0AAAAINi82LzIwMjQQAAAACDYvNS8yMDI0NdaPunmF3Ajta1R0NobcCClDSVEuWFRSQTpHMUEuSVFfTklfRVNUX05PVEUuRlkyMDI2Li4uLkVVUgEAAAAyVw0AAwAAACpJbmNsdWRlcyBBbW9ydGl6YXRpb24gb2YgSW50YW5naWJsZSBBc3NldHMA/j0tK3qF3AgciTgreoXcCC5DSVEuTllTRTpBUFRWLklRX1JFVkVOVUVfRVNUX0NJUS5GWTIwMjQuLi4uRVVSAQAAAFTviwMCAAAAEDE5NDQxLDY2NDQzNTc0ODIBDgAAAAUAAAABMwEAAAABMAIAAAAKMTAwMzM2ODA0NgMAAAAGMTAwMTgwBAAAAAEyBgAAAAEwBwAAAAI1MAgAAAABMAkAAAABMQoAAAABMAsAAAALMTM3OTgwNjcxMzIMAAAAATENAAAACDYvNi8y | BR1: MDI0EAAAAAg2LzUvMjAyNPQvudJ5hdwIeJj30nmF3AgxQ0lRLk9UQ0NIOjAwMTI2ODQ2NS5JUV9FQklUX0VTVF9DSVEuRlkyMDI2Li4uLkVVUgEAAAB+WQ0AAwAAAAAAcewEdDaG3Aiax1d0NobcCBZDSVEuLklRX0VCSVREQS4uLi4uRVVSBQAAAAAAAAAIAAAAFChJbnZhbGlkIElkZW50aWZpZXIpae+3fXqF3AhFL1V0NobcCBxDSVEuVFNFOjY0MDcuSVFfRUJJVC4uLi4uRVVSAQAAAJddDQACAAAACTgwLDM2MzQwNQEIAAAABQAAAAExAQAAAAstMTk5NTIzNjI0MAMAAAACNTACAAAAAzQwMAQAAAABMAcAAAAINi81LzIwMjQIAAAACTMvMzEvMjAyNAkAAAABMGBB3HZ6hdwI+LlUdDaG3AghQ0lRLlRTRTo2OTAyLklRX1JFVi5GWTIwMjIuLi4uRVVSAQAAADxWDQACAAAADDQwODg2LDkzMTY5NwEIAAAABQAAAAExAQAAAAstMjA5MDg3MDkzNgMAAAACNTACAAAAAzExMgQAAAABMAcAAAAINi81LzIwMjQIAAAACTMvMzEvMjAyMgkAAAABMPQvudJ5hdwIw3H30nmF3AgbQ0lRLk9NOkFMRkEuSVFfRUJJVC4uLi4uRVVSAQAAADhoBgACAAAACjc5OCwxNDk3MDIBCAAAAAUAAAABMQEAAAALLTE5OTk2MjQyMjIDAAAAAjUwAgAAAAM0MDAEAAAAATAHAAAACDYvNS8yMDI0CAAAAAkzLzMxLzIwMjQJAAAAATBgQdx2eoXcCHd9VXQ2htwIJENJUS5YVFJBOkJNVy5JUV9FQklUREEuRlkyMDIyLi4uLkVVUgEAAAB6wAoA | BS1: AgAAAAUxOTcwMQEIAAAABQAAAAExAQAAAAstMjAwNTIyODMzOAMAAAACNTACAAAABDQwNTEEAAAAATAHAAAACDYvNS8yMDI0CAAAAAoxMi8zMS8yMDIyCQAAAAEwLAm50nmF3AhjI/fSeYXcCDNDSVEuT1RDQ0g6MDAxMjY4NDY1LklRX0VCSVREQV9FU1RfQ0lRLkZZMjAyNi4uLi5FVVIBAAAAflkNAAMAAAAAAHHsBHQ2htwIMQpHdTaG3Ag0Q0lRLk9UQ0NIOjAwMTI2ODQ2NS5JUV9SRVZFTlVFX0VTVF9DSVEuRlkyMDI0Li4uLkVVUgEAAAB+WQ0AAwAAAAAAcewEdDaG3AgxCkd1NobcCCNDSVEuT006QUxGQS5JUV9OSV9FU1QuRlkyMDI2Li4uLkVVUgEAAAA4aAYAAgAAABA4NDEsMDE3ODQxMzk3NzQ1AQ4AAAAFAAAAATMBAAAAATACAAAACjEwMDExNjA1NTIDAAAABjEwMDI1MAQAAAABMwYAAAABMAcAAAACNTAIAAAAATAJAAAAATEKAAAAATALAAAACzEzODAzMzIwMzc5DAAAAAExDQAAAAg2LzcvMjAyNBAAAAAINi82LzIwMjRx7AR0NobcCN0VWHQ2htwIKkNJUS5YVFJBOkJNVy5JUV9FQklUX0VTVF9DSVEuRlkyMDI1Li4uLkVVUgEAAAB6wAoAAgAAAAoxNTcxOSw4NTI5AQ4AAAAFAAAAATMBAAAAATACAAAACjEwMDE2NjY0NTgDAAAABjEwMDIxNQQAAAABMwYAAAABMAcAAAACNTAIAAAAATAJAAAAATEKAAAAATALAAAACzEzODA3ODQzNTkxDAAAAAExDQAAAAg2LzYvMjAyNBAAAAAINi81LzIwMjT0L7nS | BT1: eYXcCIy8Q9N5hdwIKkNJUS5YVFJBOktSTi5JUV9FQklUX0VTVF9DSVEuRlkyMDI1Li4uLkVVUgEAAADBYQ0AAgAAAAk0NTQsNzQ2NTEBDgAAAAUAAAABMwEAAAABMAIAAAAKMTAwMTY4MDQ1NwMAAAAGMTAwMjE1BAAAAAEzBgAAAAEwBwAAAAI1MAgAAAABMAkAAAABMQoAAAABMAsAAAALMTM3OTQ5ODEyNzUMAAAAATENAAAACDYvNy8yMDI0EAAAAAg2LzYvMjAyNDgTBXQ2htwIvbFYdDaG3AgtQ0lRLlRTRTo2OTAyLklRX1JFVkVOVUVfRVNUX0NJUS5GWTIwMjMuLi4uRVVSAQAAADxWDQACAAAAEDQzMTEzLDMzNTU4ODU3NDIBDgAAAAUAAAABMwEAAAABMAIAAAAKMTAwMjg4NTcyMAMAAAAGMTAwMTgwBAAAAAEzBgAAAAEwBwAAAAI1MAgAAAABMAkAAAABMQoAAAABMAsAAAALMTMyODgxNzc2MzgMAAAAATENAAAACDYvNi8yMDI0EAAAAAkzLzMxLzIwMjP0L7nSeYXcCKLm99J5hdwILENJUS5UU0U6Njc3MC5JUV9FQklUREFfRVNUX0NJUS5GWTIwMjMuLi4uRVVSAQAAAE9YDQACAAAAEDYyMCwwODg4NTg3ODA4MDMBDgAAAAUAAAABMwEAAAABMAIAAAAKMTAwMTk3MTYyNAMAAAAGMTAwMTg3BAAAAAI1NgYAAAABMAcAAAACNTAIAAAAATAJAAAAATEKAAAAATALAAAACzEzMjg5MDc0NDk0DAAAAAExDQAAAAg2LzYvMjAyNBAAAAAJMy8zMS8yMDIz9C+50nmF3AhP/PbSeYXcCCJDSVEuVFNFOjY5MDIuSVFfRUJJ | BU1: VC5GWTIwMjIuLi4uRVVSAQAAADxWDQACAAAACzI2MzEsNDk1MTM4AQgAAAAFAAAAATEBAAAACy0yMDkwODcwOTM2AwAAAAI1MAIAAAADNDAwBAAAAAEwBwAAAAg2LzUvMjAyNAgAAAAJMy8zMS8yMDIyCQAAAAEw9C+50nmF3AiklUPTeYXcCCZDSVEuWFRSQTpLUk4uSVFfRUJJVERBX0VTVF9DSVEuLi4uLkVVUgEAAADBYQ0AAgAAAAg1NTcsMTc0NwEOAAAABQAAAAIxMQEAAAABMAIAAAAJMTgwMTM1OTI0AwAAAAYxMDAxODcEAAAAATMGAAAAATAHAAAAAjUwCAAAAAEwCQAAAAExCgAAAAEwCwAAAAsxMzc5NDk4MzIxOAwAAAACMTINAAAACDYvNy8yMDI0EAAAAAg2LzYvMjAyNGeyOHU2htwIZ7I4dTaG3AgrQ0lRLk9NOkFMRkEuSVFfRUJJVERBX0VTVF9DSVEuRlkyMDI1Li4uLkVVUgEAAAA4aAYAAgAAABAxMjY1LDMxMDM5NDgxMTg3AQ4AAAAFAAAAATMBAAAAATACAAAACjEwMDExNjA1NTEDAAAABjEwMDE4NwQAAAABMwYAAAABMAcAAAACNTAIAAAAATAJAAAAATEKAAAAATALAAAACzEzODAzMzE4NTk5DAAAAAExDQAAAAg2LzcvMjAyNBAAAAAINi82LzIwMjRx7AR0NobcCDEKR3U2htwIIkNJUS5YVFJBOkcxQS5JUV9FQklULkZZMjAyMi4uLi5FVVIBAAAAMlcNAAIAAAAHNDgyLDczNwEIAAAABQAAAAExAQAAAAstMjAwNzAzMzYzMQMAAAACNTACAAAAAzQwMAQAAAABMAcAAAAINi81LzIwMjQIAAAACjEy | BV1: LzMxLzIwMjIJAAAAATD0L7nSeYXcCE1uQ9N5hdwIKENJUS5PTTpBTEZBLklRX05JX0VTVF9OT1RFLkZZMjAyNC4uLi5FVVIBAAAAOGgGAAMAAAAqSW5jbHVkZXMgQW1vcnRpemF0aW9uIG9mIEludGFuZ2libGUgQXNzZXRzAP49LSt6hdwIHIk4K3qF3AgkQ0lRLlRTRTo2NDA3LklRX0VCSVRfRVNUX0NJUS4uLi4uRVVSAQAAAJddDQACAAAAEDEwNyw2OTk1OTM3NTk0NTMBDgAAAAUAAAACMTEBAAAAATACAAAACjEwMDM4OTk5OTMDAAAABjEwMDIxNQQAAAACNTYGAAAAATAHAAAAAjUwCAAAAAEwCQAAAAExCgAAAAEwCwAAAAsxMzgwMzIxNTU3MQwAAAACMTINAAAACDYvNi8yMDI0EAAAAAg2LzUvMjAyNDXWj7p5hdwI+LlUdDaG3AgsQ0lRLlhUUkE6RFVFLklRX0VCSVREQV9FU1RfQ0lRLkZZMjAyNi4uLi5FVVIBAAAAtHMNAAIAAAAJNDg1LDM3MDE2AQ4AAAAFAAAAATMBAAAAATACAAAACjEwMDE0NzAzODUDAAAABjEwMDE4NwQAAAABMwYAAAABMAcAAAACNTAIAAAAATAJAAAAATEKAAAAATALAAAACzEzODA4MjQwNTgzDAAAAAExDQAAAAg2LzcvMjAyNBAAAAAINi82LzIwMjRx7AR0NobcCC9/R3U2htwIHUNJUS5PTTpBTEZBLklRX05JX0VTVC4uLi4uRVVSAQAAADhoBgACAAAAEDcyOSw2NzMyNDg1MTM1NjEBDgAAAAUAAAACMTEBAAAAATACAAAACDI5Mzg1NjQ5AwAAAAYxMDAyNTAEAAAAATMGAAAAATAH | BW1: AAAAAjUwCAAAAAEwCQAAAAExCgAAAAEwCwAAAAsxMzgwMzMyMDg5MgwAAAACMTINAAAACDYvNi8yMDI0EAAAAAg2LzUvMjAyNGBB3HZ6hdwId31VdDaG3AgkQ0lRLlhUUkE6RzFBLklRX05JX0VTVC5GWTIwMjUuLi4uRVVSAQAAADJXDQACAAAACTQ2Miw3NjM5NAEOAAAABQAAAAEzAQAAAAEwAgAAAAoxMDAxNTQ4MDg0AwAAAAYxMDAyNTAEAAAAATMGAAAAATAHAAAAAjUwCAAAAAEwCQAAAAExCgAAAAEwCwAAAAsxMzgwMDc0NjIxMQwAAAABMQ0AAAAINi83LzIwMjQQAAAACDYvNi8yMDI0OBMFdDaG3Aix/1h0NobcCCRDSVEuWFRSQTpNQkcuSVFfRUJJVERBLkZZMjAyMi4uLi5FVVIBAAAAFKEBAAIAAAAFMjExNjUBCAAAAAUAAAABMQEAAAALLTIwMDU5OTUwMTQDAAAAAjUwAgAAAAQ0MDUxBAAAAAEwBwAAAAg2LzUvMjAyNAgAAAAKMTIvMzEvMjAyMgkAAAABMPQvudJ5hdwIK4P40nmF3AgpQ0lRLlhUUkE6REVaLklRX05JX0VTVF9OT1RFLkZZMjAyNi4uLi5FVVIBAAAAVnAJAAMAAABPSW5jbHVkZXMgQW1vcnRpemF0aW9uIG9mIEludGFuZ2libGUgQXNzZXRzIGFuZCBTdG9jayBCYXNlZCBDb21wZW5zYXRpb24gRXhwZW5zZQD+PS0reoXcCC2wOCt6hdwIJENJUS5UU0U6NjkwMi5JUV9FQklUX0VTVF9DSVEuLi4uLkVVUgEAAAA8Vg0AAgAAABA0Mjk1LDkwMzI2NDA3NjQ2AQ4AAAAFAAAAAjExAQAAAAEw | BX1: AgAAAAoxMDAzMTk3MzU0AwAAAAYxMDAyMTUEAAAAATMGAAAAATAHAAAAAjUwCAAAAAEwCQAAAAExCgAAAAEwCwAAAAsxMzgwODQ1ODE4MAwAAAACMTINAAAACDYvNi8yMDI0EAAAAAg2LzUvMjAyNHJ7PdN5hdwIcns903mF3AgsQ0lRLlRTRTo2NDA3LklRX0VCSVREQV9FU1RfQ0lRLkZZMjAyNi4uLi5FVVIBAAAAl10NAAIAAAAQMTk4LDM0ODU4NDEwNjE2OAEOAAAABQAAAAEzAQAAAAEwAgAAAAoxMDAzODk5OTk0AwAAAAYxMDAxODcEAAAAAjU2BgAAAAEwBwAAAAI1MAgAAAABMAkAAAABMQoAAAABMAsAAAALMTM3OTk3NzY4MjcMAAAAATENAAAACDYvNy8yMDI0EAAAAAg2LzYvMjAyNHHsBHQ2htwIwjFHdTaG3AgsQ0lRLlhUUkE6Qk1XLklRX0VCSVREQV9FU1RfQ0lRLkZZMjAyMy4uLi5FVVIBAAAAesAKAAIAAAALMjY2NjcsMDg1MTcBDgAAAAUAAAABMwEAAAABMAIAAAAKMTAwMTU4NzEzMQMAAAAGMTAwMTg3BAAAAAEzBgAAAAEwBwAAAAI1MAgAAAABMAkAAAABMQoAAAABMAsAAAALMTM2OTE3OTI4ODcMAAAAATENAAAACDYvNi8yMDI0EAAAAAoxMi8zMS8yMDIz9C+50nmF3AiX0fjSeYXcCCtDSVEuTllTRTpBUFRWLklRX0VCSVRfRVNUX0NJUS5GWTIwMjUuLi4uRVVSAQAAAFTviwMCAAAAEDI1NzYsMzc2Nzk4NzkyOTMBDgAAAAUAAAABMwEAAAABMAIAAAAKMTAwMzM2ODA0NwMAAAAGMTAwMjE1BAAA | BY1: AAEyBgAAAAEwBwAAAAI1MAgAAAABMAkAAAABMQoAAAABMAsAAAALMTM3OTgwNjY5NzAMAAAAATENAAAACDYvNi8yMDI0EAAAAAg2LzUvMjAyNPQvudJ5hdwIjLxD03mF3AgkQ0lRLlhUUkE6REVaLklRX05JX0VTVC5GWTIwMjQuLi4uRVVSAQAAAFZwCQACAAAABTg5LDMyAQ4AAAAFAAAAATMBAAAAATACAAAACjEwMDM0NDgxNTMDAAAABjEwMDI1MAQAAAABMwYAAAABMAcAAAACNTAIAAAAATAJAAAAATEKAAAAATALAAAACzEzODAwNzIxNTA3DAAAAAExDQAAAAg2LzcvMjAyNBAAAAAINi82LzIwMjRx7AR0NobcCPVNWXQ2htwII0NJUS5UU1g6TE5SLklRX0VCSVREQS5GWTIwMjIuLi4uRVVSAQAAAHZfDQACAAAACjY4MSw3MjM0OTYBCAAAAAUAAAABMQEAAAALLTIwMDQxNDg0MTMDAAAAAjUwAgAAAAQ0MDUxBAAAAAEwBwAAAAg2LzUvMjAyNAgAAAAKMTIvMzEvMjAyMgkAAAABMPQvudJ5hdwI0kv30nmF3AgcQ0lRLlhUUkE6S1JOLklRX0VCSVQuLi4uLkVVUgEAAADBYQ0AAgAAAAczMTgsNzY5AQgAAAAFAAAAATEBAAAACy0xOTk3MDU0NjYwAwAAAAI1MAIAAAADNDAwBAAAAAEwBwAAAAg2LzUvMjAyNAgAAAAJMy8zMS8yMDI0CQAAAAEwYEHcdnqF3AjbM1N0NobcCCpDSVEuVFNFOjY5MDIuSVFfRUJJVF9FU1RfQ0lRLkZZMjAyMy4uLi5FVVIBAAAAPFYNAAIAAAAQMjkxOSw4MjU0OTYyOTcxMgEOAAAABQAA | BZ1: AAEzAQAAAAEwAgAAAAoxMDAyODg1NzIwAwAAAAYxMDAyMTUEAAAAATMGAAAAATAHAAAAAjUwCAAAAAEwCQAAAAExCgAAAAEwCwAAAAsxMzI4ODg1OTcwOAwAAAABMQ0AAAAINi82LzIwMjQQAAAACTMvMzEvMjAyM/QvudJ5hdwIK4P40nmF3AgkQ0lRLlhUUkE6RzFBLklRX0VCSVREQS5GWTIwMjIuLi4uRVVSAQAAADJXDQACAAAABzYyNywyNjEBCAAAAAUAAAABMQEAAAALLTIwMDcwMzM2MzEDAAAAAjUwAgAAAAQ0MDUxBAAAAAEwBwAAAAg2LzUvMjAyNAgAAAAKMTIvMzEvMjAyMgkAAAABMPQvudJ5hdwI0kv30nmF3AgsQ0lRLlhUUkE6RFVFLklRX0VCSVREQV9FU1RfQ0lRLkZZMjAyNC4uLi5FVVIBAAAAtHMNAAIAAAAJMzg5LDc5ODE1AQ4AAAAFAAAAATMBAAAAATACAAAACjEwMDEzNjE5MjADAAAABjEwMDE4NwQAAAABMwYAAAABMAcAAAACNTAIAAAAATAJAAAAATEKAAAAATALAAAACzEzODA4MjQwOTM5DAAAAAExDQAAAAg2LzcvMjAyNBAAAAAINi82LzIwMjRx7AR0NobcCEhYR3U2htwIHkNJUS5UU0U6NjE0MS5JUV9FQklUREEuLi4uLkVVUgEAAADQXA0AAgAAAAo0ODYsODU2MTQyAQgAAAAFAAAAATEBAAAACy0xOTkzOTY3MzAyAwAAAAI1MAIAAAAENDA1MQQAAAABMAcAAAAINi81LzIwMjQIAAAACTMvMzEvMjAyNAkAAAABMGBB3HZ6hdwI0kRUdDaG3AglQ0lRLk9UQ0NIOjAwMTI2ODQ2NS5JUV9F | CA1: QklUREEuLi4uLkVVUgEAAAB+WQ0AAgAAAAoxODgsODc3NTg2AQgAAAAFAAAAATEBAAAACy0yMDA4MzIwMzA5AwAAAAI1MAIAAAAENDA1MQQAAAABMAcAAAAINi81LzIwMjQIAAAACjEyLzMxLzIwMjMJAAAAATBgQdx2eoXcCGBB3HZ6hdwIKkNJUS5YVFJBOkJNVy5JUV9FQklUX0VTVF9DSVEuRlkyMDIzLi4uLkVVUgEAAAB6wAoAAgAAAAsxNzk4OSwzNTQzMwEOAAAABQAAAAEzAQAAAAEwAgAAAAoxMDAxNTg3MTMxAwAAAAYxMDAyMTUEAAAAATMGAAAAATAHAAAAAjUwCAAAAAEwCQAAAAExCgAAAAEwCwAAAAsxMzcxMTQ2MTg1NwwAAAABMQ0AAAAINi82LzIwMjQQAAAACjEyLzMxLzIwMjP0L7nSeYXcCMNx99J5hdwIH0NJUS5PTTpBTEZBLklRX05JLkZZMjAyMy4uLi5FVVIBAAAAOGgGAAIAAAAKNTY5LDQ0NzQ3MQEIAAAABQAAAAExAQAAAAstMjAwNDE3NTA2OAMAAAACNTACAAAAAjE1BAAAAAEwBwAAAAg2LzYvMjAyNAgAAAAKMTIvMzEvMjAyMwkAAAABMPrFBHQ2htwIw3RZdDaG3AgpQ0lRLlhUUkE6REVaLklRX05JX0VTVF9OT1RFLkZZMjAyNC4uLi5FVVIBAAAAVnAJAAMAAABPSW5jbHVkZXMgQW1vcnRpemF0aW9uIG9mIEludGFuZ2libGUgQXNzZXRzIGFuZCBTdG9jayBCYXNlZCBDb21wZW5zYXRpb24gRXhwZW5zZQD+PS0reoXcCC2wOCt6hdwIHkNJUS5UU0U6NjE0MS5JUV9OSV9FU1QuLi4uLkVV | CB1: UgEAAADQXA0AAwAAAAAAYEHcdnqF3AjQHVR0NobcCCtDSVEuRU5YVFBBOkZSLklRX0VCSVRfRVNUX0NJUS5GWTIwMjQuLi4uRVVSAQAAAIaACgACAAAACTk3NCwxNTk4NwEOAAAABQAAAAEzAQAAAAEwAgAAAAoxMDAyMzU4MTk1AwAAAAYxMDAyMTUEAAAAATMGAAAAATAHAAAAAjUwCAAAAAEwCQAAAAExCgAAAAEwCwAAAAsxMzgwNzg0MTg0OAwAAAABMQ0AAAAINi82LzIwMjQQAAAACDYvNS8yMDI08Va50nmF3AjSS/fSeYXcCBxDSVEuWFRSQTpERVouSVFfRUJJVC4uLi4uRVVSAQAAAFZwCQACAAAABTEyMCwxAQgAAAAFAAAAATEBAAAACy0xOTk3NTAwNDU2AwAAAAI1MAIAAAADNDAwBAAAAAEwBwAAAAg2LzUvMjAyNAgAAAAJMy8zMS8yMDI0CQAAAAEwYEHcdnqF3Ajta1R0NobcCBtDSVEuWFRSQTpEVUUuSVFfUkVWLi4uLi5FVVIBAAAAtHMNAAIAAAAINDcxMSwwODgBCAAAAAUAAAABMQEAAAALLTE5OTQ0NzE2NDIDAAAAAjUwAgAAAAMxMTIEAAAAATAHAAAACDYvNi8yMDI0CAAAAAkzLzMxLzIwMjQJAAAAATBnsjh1NobcCGeyOHU2htwILENJUS5UU0U6NjE0MS5JUV9FQklUREFfRVNUX0NJUS5GWTIwMjUuLi4uRVVSAQAAANBcDQACAAAADzU3Nyw0MDg5ODMwMTc5MwEOAAAABQAAAAEzAQAAAAEwAgAAAAoxMDAzNzU5NTc0AwAAAAYxMDAxODcEAAAAATMGAAAAATAHAAAAAjUwCAAAAAEwCQAAAAExCgAA | CC1: AAEwCwAAAAsxMzc1NzA5MTQyMgwAAAABMQ0AAAAINi83LzIwMjQQAAAACDYvNi8yMDI0cewEdDaG3AhIWEd1NobcCC5DSVEuRU5YVFBBOkZSLklRX1JFVkVOVUVfRVNUX0NJUS5GWTIwMjQuLi4uRVVSAQAAAIaACgACAAAACjIyNzAxLDg1MDcBDgAAAAUAAAABMwEAAAABMAIAAAAKMTAwMjM1ODE5NQMAAAAGMTAwMTgwBAAAAAEzBgAAAAEwBwAAAAI1MAgAAAABMAkAAAABMQoAAAABMAsAAAALMTM4MDgxNDkxMzUMAAAAATENAAAACDYvNi8yMDI0EAAAAAg2LzUvMjAyNPFWudJ5hdwI9zT40nmF3AgkQ0lRLlhUUkE6RFVFLklRX05JX0VTVC5GWTIwMjQuLi4uRVVSAQAAALRzDQACAAAACTE1Myw5MDg4MwEOAAAABQAAAAEzAQAAAAEwAgAAAAoxMDAxMzYxOTIwAwAAAAYxMDAyNTAEAAAAATMGAAAAATAHAAAAAjUwCAAAAAEwCQAAAAExCgAAAAEwCwAAAAsxMzgwODI0MDkzMwwAAAABMQ0AAAAINi83LzIwMjQQAAAACDYvNi8yMDI0cewEdDaG3AjDdFl0NobcCB5DSVEuWFRSQTpLUk4uSVFfRUJJVERBLi4uLi5FVVIBAAAAwWENAAIAAAAHNDY5LDczNAEIAAAABQAAAAExAQAAAAstMTk5NzA1NDY2MAMAAAACNTACAAAABDQwNTEEAAAAATAHAAAACDYvNS8yMDI0CAAAAAkzLzMxLzIwMjQJAAAAATBgQdx2eoXcCNszU3Q2htwIKUNJUS5UU0U6NjQwNy5JUV9OSV9FU1RfTk9URS5GWTIwMjUuLi4uRVVSAQAAAJdd | CD1: DQADAAAAAAD+PS0reoXcCByJOCt6hdwIJENJUS5UU0U6NjQwNy5JUV9OSV9FU1QuRlkyMDI0Li4uLkVVUgEAAACXXQ0AAwAAAAAAcewEdDaG3Aj1TVl0NobcCCFDSVEuWFRSQTpCTVcuSVFfUkVWLkZZMjAyMi4uLi5FVVIBAAAAesAKAAIAAAAGMTA3NDg4AQgAAAAFAAAAATEBAAAACy0yMDA1MjI4MzM4AwAAAAI1MAIAAAADMTEyBAAAAAEwBwAAAAg2LzUvMjAyNAgAAAAKMTIvMzEvMjAyMgkAAAABMCwJudJ5hdwIYyP30nmF3AgqQ0lRLlhUUkE6TUJHLklRX0VCSVRfRVNUX0NJUS5GWTIwMjQuLi4uRVVSAQAAABShAQACAAAACzE2NjgzLDg3ODg2AQ4AAAAFAAAAATMBAAAAATACAAAACjEwMDE1NzYyMzMDAAAABjEwMDIxNQQAAAABMwYAAAABMAcAAAACNTAIAAAAATAJAAAAATEKAAAAATALAAAACzEzODA2NjgyNDAyDAAAAAExDQAAAAg2LzYvMjAyNBAAAAAINi81LzIwMjT0L7nSeYXcCPc0+NJ5hdwIHENJUS5UU0U6Njc3MC5JUV9FQklULi4uLi5FVVIBAAAAT1gNAAIAAAAKMTExLDI2MTA5NAEIAAAABQAAAAExAQAAAAstMTk5NTU0NDA4MAMAAAACNTACAAAAAzQwMAQAAAABMAcAAAAINi81LzIwMjQIAAAACTMvMzEvMjAyNAkAAAABMHJ7PdN5hdwIcns903mF3AgqQ0lRLlRTRTo2OTAyLklRX0VCSVRfRVNUX0NJUS5GWTIwMjUuLi4uRVVSAQAAADxWDQACAAAAEDQyOTUsOTAzMjY0MDc2NDYBDgAAAAUA | CE1: AAABMwEAAAABMAIAAAAKMTAwMzE5NzM1NAMAAAAGMTAwMjE1BAAAAAEzBgAAAAEwBwAAAAI1MAgAAAABMAkAAAABMQoAAAABMAsAAAALMTM4MDg0NTgxODAMAAAAATENAAAACDYvNi8yMDI0EAAAAAg2LzUvMjAyNPQvudJ5hdwIpJVD03mF3AgsQ0lRLlRTWDpMTlIuSVFfUkVWRU5VRV9FU1RfQ0lRLkZZMjAyMy4uLi5FVVIBAAAAdl8NAAIAAAAQNjYxMywxMzgyNjY2MDQ2OAEOAAAABQAAAAEzAQAAAAEwAgAAAAoxMDAyMzc5MzQ0AwAAAAYxMDAxODAEAAAAATMGAAAAATAHAAAAAjUwCAAAAAEwCQAAAAExCgAAAAEwCwAAAAsxMzY3OTU2MTk4OAwAAAABMQ0AAAAINi82LzIwMjQQAAAACjEyLzMxLzIwMjPxVrnSeYXcCMNx99J5hdwIGkNJUS5UU0U6NjQwNy5JUV9OSS4uLi4uRVVSAQAAAJddDQACAAAACTUxLDA5NTc4MQEIAAAABQAAAAExAQAAAAstMTk5NTIzNjI0MAMAAAACNTACAAAAAjE1BAAAAAEwBwAAAAg2LzUvMjAyNAgAAAAJMy8zMS8yMDI0CQAAAAEwYEHcdnqF3Aj4uVR0NobcCCZDSVEuVFNFOjY0MDcuSVFfRUJJVERBX0VTVF9DSVEuLi4uLkVVUgEAAACXXQ0AAgAAABAxNTMsMjYyMTg0NTQwOTMzAQ4AAAAFAAAAAjExAQAAAAEwAgAAAAoxMDAzODk5OTkzAwAAAAYxMDAxODcEAAAAAjU2BgAAAAEwBwAAAAI1MAgAAAABMAkAAAABMQoAAAABMAsAAAALMTM3OTk3NzY1NjkMAAAAAjEyDQAAAAg2 | CF1: LzcvMjAyNBAAAAAINi82LzIwMjRW2Th1NobcCFbZOHU2htwIKUNJUS5YVFJBOkcxQS5JUV9OSV9FU1RfTk9URS5GWTIwMjQuLi4uRVVSAQAAADJXDQADAAAAKkluY2x1ZGVzIEFtb3J0aXphdGlvbiBvZiBJbnRhbmdpYmxlIEFzc2V0cwD+PS0reoXcCByJOCt6hdwIFENJUS4uSVFfRUJJVC4uLi4uRVVSBQAAAAAAAAAIAAAAFChJbnZhbGlkIElkZW50aWZpZXIpae+3fXqF3AhFL1V0NobcCC1DSVEuWFRSQTpLUk4uSVFfUkVWRU5VRV9FU1RfQ0lRLkZZMjAyNS4uLi5FVVIBAAAAwWENAAIAAAAKNTY3NiwxNDM3MQEOAAAABQAAAAEzAQAAAAEwAgAAAAoxMDAxNjgwNDU3AwAAAAYxMDAxODAEAAAAATMGAAAAATAHAAAAAjUwCAAAAAEwCQAAAAExCgAAAAEwCwAAAAsxMzc5NDk4MTI5OQwAAAABMQ0AAAAINi83LzIwMjQQAAAACDYvNi8yMDI0OBMFdDaG3AjVpkd1NobcCClDSVEuWFRSQTpLUk4uSVFfTklfRVNUX05PVEUuRlkyMDI1Li4uLkVVUgEAAADBYQ0AAwAAACpJbmNsdWRlcyBBbW9ydGl6YXRpb24gb2YgSW50YW5naWJsZSBBc3NldHMA/j0tK3qF3AgtsDgreoXcCCpDSVEuWFRSQTpEVUUuSVFfRUJJVF9FU1RfQ0lRLkZZMjAyNi4uLi5FVVIBAAAAtHMNAAIAAAAGMzczLDc1AQ4AAAAFAAAAATMBAAAAATACAAAACjEwMDE0NzAzODUDAAAABjEwMDIxNQQAAAABMwYAAAABMAcAAAACNTAIAAAAATAJAAAA | CG1: ATEKAAAAATALAAAACzEzODA4MjQwNTU5DAAAAAExDQAAAAg2LzcvMjAyNBAAAAAINi82LzIwMjRx7AR0NobcCF7uV3Q2htwIIkNJUS5YVFJBOkRFWi5JUV9FQklULkZZMjAyMy4uLi5FVVIBAAAAVnAJAAIAAAAFMTMyLDYBCAAAAAUAAAABMQEAAAALLTIwMDU2MzUwMjIDAAAAAjUwAgAAAAM0MDAEAAAAATAHAAAACDYvNi8yMDI0CAAAAAoxMi8zMS8yMDIzCQAAAAEw+sUEdDaG3Aj1TVl0NobcCCJDSVEuVFNFOjY0MDcuSVFfRUJJVC5GWTIwMjMuLi4uRVVSAQAAAJddDQACAAAACjE0Niw1ODI0MzYBCAAAAAUAAAABMQEAAAALLTIwMzk1NTcxMDQDAAAAAjUwAgAAAAM0MDAEAAAAATAHAAAACDYvNi8yMDI0CAAAAAkzLzMxLzIwMjMJAAAAATD6xQR0NobcCPVNWXQ2htwINENJUS5PVENDSDowMDEyNjg0NjUuSVFfUkVWRU5VRV9FU1RfQ0lRLkZZMjAyNi4uLi5FVVIBAAAAflkNAAMAAAAAAHHsBHQ2htwIMQpHdTaG3AgoQ0lRLk9UQ0NIOjAwMTI2ODQ2NS5JUV9SRVYuRlkyMDIzLi4uLkVVUgEAAAB+WQ0AAgAAAAsyMTA2LDEyNDc1MwEIAAAABQAAAAExAQAAAAstMjAwODMyMjMxOQMAAAACNTACAAAAAzExMgQAAAABMAcAAAAINi82LzIwMjQIAAAACjEyLzMxLzIwMjMJAAAAATD6xQR0NobcCDEKR3U2htwIMENJUS5PVENDSDowMDEyNjg0NjUuSVFfTklfRVNUX05PVEUuRlkyMDI0Li4uLkVVUgEAAAB+WQ0A | CH1: AwAAAAAA9AnoJXqF3AjWavIleoXcCC1DSVEuWFRSQTpERVouSVFfUkVWRU5VRV9FU1RfQ0lRLkZZMjAyNC4uLi5FVVIBAAAAVnAJAAIAAAAGMjAwOCwzAQ4AAAAFAAAAATMBAAAAATACAAAACjEwMDM0NDgxNTMDAAAABjEwMDE4MAQAAAABMwYAAAABMAcAAAACNTAIAAAAATAJAAAAATEKAAAAATALAAAACzEzNzU2MTczNTc4DAAAAAExDQAAAAg2LzcvMjAyNBAAAAAINi82LzIwMjRx7AR0NobcCMIxR3U2htwIJUNJUS5FTlhUUEE6TUMuSVFfRUJJVERBLkZZMjAyMi4uLi5FVVIBAAAAoPsCAAIAAAAFMjMyNTMBCAAAAAUAAAABMQEAAAALLTIwMTA2MDA2NzADAAAAAjUwAgAAAAQ0MDUxBAAAAAEwBwAAAAg2LzUvMjAyNAgAAAAKMTIvMzEvMjAyMgkAAAABMPQvudJ5hdwIeJj30nmF3AgoQ0lRLlhUUkE6TUJHLklRX01BUktFVENBUC4zMS4wNS4yMDIzLkVVUgEAAAAUoQEAAgAAAAw3NDY0Miw1NTg2NzcBBgAAAAUAAAABMQEAAAALLTIwNDgxNDQ0ODUDAAAAAjUwAgAAAAYxMDAwNTQEAAAAATAHAAAACTUvMzEvMjAyMywJudJ5hdwI1b/30nmF3AgeQ0lRLlhUUkE6RzFBLklRX05JX0VTVC4uLi4uRVVSAQAAADJXDQACAAAACDQ0NSw2MDg2AQ4AAAAFAAAAAjExAQAAAAEwAgAAAAkxNDk3NTc1MDMDAAAABjEwMDI1MAQAAAABMwYAAAABMAcAAAACNTAIAAAAATAJAAAAATEKAAAAATALAAAACzEzODAwNzQ3MjQx | CI1: DAAAAAIxMg0AAAAINi82LzIwMjQQAAAACDYvNS8yMDI0YEHcdnqF3AiUgVN0NobcCCRDSVEuWFRSQTpHMUEuSVFfRUJJVF9FU1RfQ0lRLi4uLi5FVVIBAAAAMlcNAAIAAAAINjI1LDU4OTMBDgAAAAUAAAACMTEBAAAAATACAAAACTE0OTc1NzUwMwMAAAAGMTAwMjE1BAAAAAEzBgAAAAEwBwAAAAI1MAgAAAABMAkAAAABMQoAAAABMAsAAAALMTM4MDA3NDcyMzMMAAAAAjEyDQAAAAg2LzYvMjAyNBAAAAAINi81LzIwMjQ11o+6eYXcCJSBU3Q2htwILENJUS5UU0U6NjE0MS5JUV9FQklUREFfRVNUX0NJUS5GWTIwMjYuLi4uRVVSAQAAANBcDQACAAAAEDYyOCw2NzI5NDQ4OTQ5ODEBDgAAAAUAAAABMwEAAAABMAIAAAAKMTAwNTMxOTkzMgMAAAAGMTAwMTg3BAAAAAEzBgAAAAEwBwAAAAI1MAgAAAABMAkAAAABMQoAAAABMAsAAAALMTM3NTcwOTE1ODAMAAAAATENAAAACDYvNy8yMDI0EAAAAAg2LzYvMjAyNHHsBHQ2htwISFhHdTaG3AgoQ0lRLk9NOkFMRkEuSVFfTklfRVNUX05PVEUuRlkyMDI2Li4uLkVVUgEAAAA4aAYAAwAAACpJbmNsdWRlcyBBbW9ydGl6YXRpb24gb2YgSW50YW5naWJsZSBBc3NldHMA/j0tK3qF3AgciTgreoXcCCBDSVEuWFRSQTpEVUUuSVFfTkkuRlkyMDIzLi4uLkVVUgEAAAC0cw0AAgAAAAcxMTEsOTgxAQgAAAAFAAAAATEBAAAACy0yMDA0MTQ5OTI3AwAAAAI1MAIAAAACMTUEAAAA | CJ1: ATAHAAAACDYvNi8yMDI0CAAAAAoxMi8zMS8yMDIzCQAAAAEw+sUEdDaG3AjDdFl0NobcCC1DSVEuVFNFOjYxNDEuSVFfUkVWRU5VRV9FU1RfQ0lRLkZZMjAyNi4uLi5FVVIBAAAA0FwNAAIAAAAQMzYwNywzMzMwNDE1MDkyNwEOAAAABQAAAAEzAQAAAAEwAgAAAAoxMDA1MzE5OTMyAwAAAAYxMDAxODAEAAAAATMGAAAAATAHAAAAAjUwCAAAAAEwCQAAAAExCgAAAAEwCwAAAAsxMzc1ODI1MjYxMwwAAAABMQ0AAAAINi83LzIwMjQQAAAACDYvNi8yMDI0cewEdDaG3AhIWEd1NobcCC1DSVEuWFRSQTpNQkcuSVFfUkVWRU5VRV9FU1RfQ0lRLkZZMjAyNC4uLi5FVVIBAAAAFKEBAAIAAAAMMTUyMzY1LDM2MzI2AQ4AAAAFAAAAATMBAAAAATACAAAACjEwMDE1NzYyMzMDAAAABjEwMDE4MAQAAAABMwYAAAABMAcAAAACNTAIAAAAATAJAAAAATEKAAAAATALAAAACzEzODA2NjgyNDgwDAAAAAExDQAAAAg2LzYvMjAyNBAAAAAINi81LzIwMjT0L7nSeYXcCNJL99J5hdwIG0NJUS5YVFJBOktSTi5JUV9SRVYuLi4uLkVVUgEAAADBYQ0AAgAAAAg0ODE2LDA3OQEIAAAABQAAAAExAQAAAAstMTk5NzA1NDY2MAMAAAACNTACAAAAAzExMgQAAAABMAcAAAAINi82LzIwMjQIAAAACTMvMzEvMjAyNAkAAAABMGeyOHU2htwIZ7I4dTaG3AgkQ0lRLlhUUkE6S1JOLklRX05JX0VTVC5GWTIwMjQuLi4uRVVSAQAAAMFhDQACAAAA | CK1: CTI3Niw0MDU5OQEOAAAABQAAAAEzAQAAAAEwAgAAAAoxMDAxNTgyMDE2AwAAAAYxMDAyNTAEAAAAATMGAAAAATAHAAAAAjUwCAAAAAEwCQAAAAExCgAAAAEwCwAAAAsxMzc4MDg3MDM5NgwAAAABMQ0AAAAINi83LzIwMjQQAAAACDYvNi8yMDI0OBMFdDaG3AjDdFl0NobcCCpDSVEuWFRSQTpEVUUuSVFfRUJJVF9FU1RfQ0lRLkZZMjAyNC4uLi5FVVIBAAAAtHMNAAIAAAAJMjY1LDAxNjY3AQ4AAAAFAAAAATMBAAAAATACAAAACjEwMDEzNjE5MjADAAAABjEwMDIxNQQAAAABMwYAAAABMAcAAAACNTAIAAAAATAJAAAAATEKAAAAATALAAAACzEzODA4MjQwOTI3DAAAAAExDQAAAAg2LzcvMjAyNBAAAAAINi82LzIwMjRx7AR0NobcCJUmWXQ2htwIGkNJUS5YVFJBOkRVRS5JUV9OSS4uLi4uRVVSAQAAALRzDQACAAAABzEwOSw2MzYBCAAAAAUAAAABMQEAAAALLTE5OTQ0NzE2NDIDAAAAAjUwAgAAAAIxNQQAAAABMAcAAAAINi81LzIwMjQIAAAACTMvMzEvMjAyNAkAAAABMGBB3HZ6hdwIjM9TdDaG3AgkQ0lRLlhUUkE6REVaLklRX05JX0VTVC5GWTIwMjYuLi4uRVVSAQAAAFZwCQACAAAABzEzNSw0NzUBDgAAAAUAAAABMwEAAAABMAIAAAAKMTAwMzY2NDM3MwMAAAAGMTAwMjUwBAAAAAEzBgAAAAEwBwAAAAI1MAgAAAABMAkAAAABMQoAAAABMAsAAAALMTM3NTMxNTMzNTcMAAAAATENAAAACDYvNy8yMDI0EAAA | CL1: AAg2LzYvMjAyNHHsBHQ2htwI3RVYdDaG3AgrQ0lRLk9NOkFMRkEuSVFfRUJJVERBX0VTVF9DSVEuRlkyMDI2Li4uLkVVUgEAAAA4aAYAAgAAABAxMzM5LDIwNjkyMTcxNDU0AQ4AAAAFAAAAATMBAAAAATACAAAACjEwMDExNjA1NTIDAAAABjEwMDE4NwQAAAABMwYAAAABMAcAAAACNTAIAAAAATAJAAAAATEKAAAAATALAAAACzEzODAzMzE4NTgxDAAAAAExDQAAAAg2LzcvMjAyNBAAAAAINi82LzIwMjRx7AR0NobcCDEKR3U2htwILUNJUS5FTlhUUEE6RlIuSVFfRUJJVERBX0VTVF9DSVEuRlkyMDIzLi4uLkVVUgEAAACGgAoAAgAAAAoyNjIxLDUzMzE3AQ4AAAAFAAAAATMBAAAAATACAAAACjEwMDIwOTk3MDgDAAAABjEwMDE4NwQAAAABMwYAAAABMAcAAAACNTAIAAAAATAJAAAAATEKAAAAATALAAAACzEzNjY5NDAzODI1DAAAAAExDQAAAAg2LzYvMjAyNBAAAAAKMTIvMzEvMjAyM/FWudJ5hdwIoub30nmF3AgnQ0lRLiRFVVJKUFkuSVFfTEFTVFNBTEVQUklDRS4zMS4wNS4yMDIzAQAAALjrWgACAAAACjAsMDA2NzE1NjcA9C+50nmF3Agrg/jSeYXcCCxDSVEuWFRSQTpCTVcuSVFfRUJJVERBX0VTVF9DSVEuRlkyMDI1Li4uLkVVUgEAAAB6wAoAAgAAAAsyNTE0MSw5ODg2NAEOAAAABQAAAAEzAQAAAAEwAgAAAAoxMDAxNjY2NDU4AwAAAAYxMDAxODcEAAAAATMGAAAAATAHAAAAAjUwCAAAAAEwCQAAAAEx | CM1: CgAAAAEwCwAAAAsxMzgwNzg0MzU5NwwAAAABMQ0AAAAINi82LzIwMjQQAAAACDYvNS8yMDI09C+50nmF3Aii5vfSeYXcCC5DSVEuRU5YVFBBOkZSLklRX1JFVkVOVUVfRVNUX0NJUS5GWTIwMjUuLi4uRVVSAQAAAIaACgACAAAACzI0MjU4LDI4MDQ4AQ4AAAAFAAAAATMBAAAAATACAAAACjEwMDM1MDA2NTIDAAAABjEwMDE4MAQAAAABMwYAAAABMAcAAAACNTAIAAAAATAJAAAAATEKAAAAATALAAAACzEzODA4MTQ5MTE3DAAAAAExDQAAAAg2LzYvMjAyNBAAAAAINi81LzIwMjTxVrnSeYXcCCuD+NJ5hdwILENJUS5YVFJBOkcxQS5JUV9FQklUREFfRVNUX0NJUS5GWTIwMjUuLi4uRVVSAQAAADJXDQACAAAACTgzNCw1NjYxOQEOAAAABQAAAAEzAQAAAAEwAgAAAAoxMDAxNTQ4MDg0AwAAAAYxMDAxODcEAAAAATMGAAAAATAHAAAAAjUwCAAAAAEwCQAAAAExCgAAAAEwCwAAAAsxMzgwMDc0NjI5NQwAAAABMQ0AAAAINi83LzIwMjQQAAAACDYvNi8yMDI0OBMFdDaG3Agvf0d1NobcCBlDSVEuT006QUxGQS5JUV9OSS4uLi4uRVVSAQAAADhoBgACAAAACjU2NCwyNjE1ODQBCAAAAAUAAAABMQEAAAALLTE5OTk2MjQyMjIDAAAAAjUwAgAAAAIxNQQAAAABMAcAAAAINi81LzIwMjQIAAAACTMvMzEvMjAyNAkAAAABMGBB3HZ6hdwId31VdDaG3AgrQ0lRLk9UQ0NIOjAwMTI2ODQ2NS5DSVFfTklfRVNUX05PVEUuLi4u | CN1: LkVVUgUAAAAAAAAACAAAABYoSW52YWxpZCBGb3JtdWxhIE5hbWUpui9dFnqF3Aim1WIWeoXcCC1DSVEuVFNFOjYxNDEuSVFfUkVWRU5VRV9FU1RfQ0lRLkZZMjAyNC4uLi5FVVIBAAAA0FwNAAIAAAAQMzIyNiwwOTQxNTI2MDc1MgEOAAAABQAAAAEzAQAAAAEwAgAAAAoxMDAzNzU5NTczAwAAAAYxMDAxODAEAAAAATMGAAAAATAHAAAAAjUwCAAAAAEwCQAAAAExCgAAAAEwCwAAAAsxMzc1ODI1MjY4MAwAAAABMQ0AAAAINi83LzIwMjQQAAAACDYvNi8yMDI0cewEdDaG3AhIWEd1NobcCCRDSVEuVFNFOjY0MDcuSVFfRUJJVERBLkZZMjAyMy4uLi5FVVIBAAAAl10NAAIAAAAKMTkyLDQ1OTExNwEIAAAABQAAAAExAQAAAAstMjAzOTU1NzEwNAMAAAACNTACAAAABDQwNTEEAAAAATAHAAAACDYvNi8yMDI0CAAAAAkzLzMxLzIwMjMJAAAAATD6xQR0NobcCLH/WHQ2htwIKENJUS5YVFJBOkRFWi5JUV9NQVJLRVRDQVAuMzEuMDUuMjAyNC5FVVIBAAAAVnAJAAIAAAAKNjU4LDQ4ODM1OAEGAAAABQAAAAExAQAAAAstMTk5NzUwMTAxNQMAAAACNTACAAAABjEwMDA1NAQAAAABMAcAAAAJNS8zMS8yMDI0+sUEdDaG3AgIk1R0NobcCCRDSVEuWFRSQTpLUk4uSVFfTklfRVNULkZZMjAyNi4uLi5FVVIBAAAAwWENAAIAAAAJMzczLDIyNTAyAQ4AAAAFAAAAATMBAAAAATACAAAACjEwMDI2MDY1NDkDAAAABjEwMDI1MAQA | CO1: AAABMwYAAAABMAcAAAACNTAIAAAAATAJAAAAATEKAAAAATALAAAACzEzNzcyODU1NDI5DAAAAAExDQAAAAg2LzcvMjAyNBAAAAAINi82LzIwMjQ4EwV0NobcCN0VWHQ2htwIIUNJUS5YVFJBOkcxQS5JUV9SRVYuRlkyMDIzLi4uLkVVUgEAAAAyVw0AAgAAAAg1MzczLDQ5MQEIAAAABQAAAAExAQAAAAstMjAwNzAzMzYzMgMAAAACNTACAAAAAzExMgQAAAABMAcAAAAINi82LzIwMjQIAAAACjEyLzMxLzIwMjMJAAAAATD6xQR0NobcCC9/R3U2htwIKkNJUS5UU0U6Njc3MC5JUV9FQklUX0VTVF9DSVEuRlkyMDIzLi4uLkVVUgEAAABPWA0AAgAAABAyODcsNzQ5MjcwNDY1OTk0AQ4AAAAFAAAAATMBAAAAATACAAAACjEwMDE5NzE2MjQDAAAABjEwMDIxNQQAAAACNTYGAAAAATAHAAAAAjUwCAAAAAEwCQAAAAExCgAAAAEwCwAAAAsxMzI4OTQxMjM3NgwAAAABMQ0AAAAINi82LzIwMjQQAAAACTMvMzEvMjAyM/QvudJ5hdwIw3H30nmF3AggQ0lRLlhUUkE6S1JOLklRX05JLkZZMjAyMy4uLi5FVVIBAAAAwWENAAIAAAAHMjI0LDUxMQEIAAAABQAAAAExAQAAAAstMjAwNTA4NzAwNAMAAAACNTACAAAAAjE1BAAAAAEwBwAAAAg2LzYvMjAyNAgAAAAKMTIvMzEvMjAyMwkAAAABMPrFBHQ2htwIw3RZdDaG3AgkQ0lRLlRTRTo2MTQxLklRX0VCSVREQS5GWTIwMjMuLi4uRVVSAQAAANBcDQACAAAACjQ5NSw1MjQxODcB | CP1: CAAAAAUAAAABMQEAAAALLTIwMDI5Njg4MDADAAAAAjUwAgAAAAQ0MDUxBAAAAAEwBwAAAAg2LzYvMjAyNAgAAAAKMTIvMzEvMjAyMwkAAAABMPrFBHQ2htwIlSZZdDaG3Ag=

Sheet Multiples 
B2: Multiples
E7: Local | F7: Exchange | H7: Market cap | I7: Bridge | J7: EV | M7: EV / Sales | R7: EV / EBITDA | W7: EV / EBIT | AB7: P / E
C8: Companies | E8: currency | F8: rate | H8: (EURm) | I8: (EURm) | J8: (EURm) | L8: ='Financials_hard coded'!Q8 -> 45291 | M8: ='Financials_hard coded'!M8 -> 45657 | N8: ='Financials_hard coded'!N8 -> 46022 | O8: ='Financials_hard coded'!O8 -> 46387 | Q8: ='Financials_hard coded'!Q8 -> 45291 | R8: ='Financials_hard coded'!R8 -> 45657 | S8: ='Financials_hard coded'!S8 -> 46022 | T8: ='Financials_hard coded'!T8 -> 46387 | V8: ='Financials_hard coded'!V8 -> 45291 | W8: ='Financials_hard coded'!W8 -> 45657 | X8: ='Financials_hard coded'!X8 -> 46022 | Y8: ='Financials_hard coded'!Y8 -> 46387 | AA8: ='Financials_hard coded'!AA8 -> 45291 | AB8: ='Financials_hard coded'!AB8 -> 45657 | AC8: ='Financials_hard coded'!AC8 -> 46022 | AD8: ='Financials_hard coded'!AD8 -> 46387
C10: Bobst Group SA | E10: ='Financials_hard coded'!E11 -> CHF | F10: ='Financials_hard coded'!F11 -> 1.02055 | H10: ='Financials_hard coded'!H11 -> 965.96212 | I10: ='Financials_hard coded'!I11 -> 130.22218 | J10: ='Financials_hard coded'!J11 -> 1096.1843 | L10: =$J$10/'Financials_hard coded'!L11 -> 0.52047454 | M10: na | N10: na | O10: na | Q10: =$J$10/'Financials_hard coded'!Q11 -> 5.8036758 | R10: na | S10: na | T10: na | V10: =$J$10/'Financials_hard coded'!V11 -> 6.8155394 | W10: na | X10: na | Y10: na | AA10: =$H$10/'Financials_hard coded'!AA11 -> 7.5743931 | AB10: na | AC10: na | AD10: na
C11: CKD Corp. | E11: ='Financials_hard coded'!E12 -> JPY | F11: ='Financials_hard coded'!F12 -> 0.00587 | H11: ='Financials_hard coded'!H12 -> 1198.2796 | I11: ='Financials_hard coded'!I12 -> -64.29998 | J11: ='Financials_hard coded'!J12 -> 1133.9796 | L11: =$J$11/'Financials_hard coded'!L12 -> 1.0271198 | M11: =$J$11/'Financials_hard coded'!M12 -> 1.3765959 | N11: =$J$11/'Financials_hard coded'!N12 -> 1.2755775 | O11: =$J$11/'Financials_hard coded'!O12 -> 1.1299583 | Q11: =$J$11/'Financials_hard coded'!Q12 -> 5.8920543 | R11: =$J$11/'Financials_hard coded'!R12 -> 9.6217366 | S11: =$J$11/'Financials_hard coded'!S12 -> 7.3458023 | T11: =$J$11/'Financials_hard coded'!T12 -> 5.676036 | V11: =$J$11/'Financials_hard coded'!V12 -> 7.7361216 | W11: =$J$11/'Financials_hard coded'!W12 -> 14.997197 | X11: =$J$11/'Financials_hard coded'!X12 -> 10.529098 | Y11: =$J$11/'Financials_hard coded'!Y12 -> 7.8176849 | AA11: =$H$11/'Financials_hard coded'!AA12 -> 11.703295 | AB11: na | AC11: na | AD11: na
C12: Gea Group AG | E12: ='Financials_hard coded'!E16 -> EUR | F12: ='Financials_hard coded'!F16 -> 1 | H12: ='Financials_hard coded'!H16 -> 6441.47 | I12: ='Financials_hard coded'!I16 -> 643.612 | J12: ='Financials_hard coded'!J16 -> 7085.082 | L12: =$J$12/'Financials_hard coded'!L16 -> 1.318525 | M12: =$J$12/'Financials_hard coded'!M16 -> 1.295499 | N12: =$J$12/'Financials_hard coded'!N16 -> 1.2583811 | O12: =$J$12/'Financials_hard coded'!O16 -> 1.2123102 | Q12: =$J$12/'Financials_hard coded'!Q16 -> 11.866199 | R12: =$J$12/'Financials_hard coded'!R16 -> 8.8350287 | S12: =$J$12/'Financials_hard coded'!S16 -> 8.4895387 | T12: =$J$12/'Financials_hard coded'!T16 -> 8.0784509 | V12: =$J$12/'Financials_hard coded'!V16 -> 13.823984 | W12: =$J$12/'Financials_hard coded'!W16 -> 11.462276 | X12: =$J$12/'Financials_hard coded'!X16 -> 10.933904 | Y12: =$J$12/'Financials_hard coded'!Y16 -> 10.627681 | AA12: =$H$12/'Financials_hard coded'!AA16 -> 16.400316 | AB12: =$H$12/'Financials_hard coded'!AB16 -> 14.643361 | AC12: =$H$12/'Financials_hard coded'!AC16 -> 13.919559 | AD12: =$H$12/'Financials_hard coded'!AD16 -> 12.978146
C13: Krones AG | E13: ='Financials_hard coded'!E17 -> EUR | F13: ='Financials_hard coded'!F17 -> 1 | H13: ='Financials_hard coded'!H17 -> 3980.7271 | I13: ='Financials_hard coded'!I17 -> -68.334 | J13: ='Financials_hard coded'!J17 -> 3912.3931 | L13: =$J$13/'Financials_hard coded'!L17 -> 0.82098632 | M13: =$J$13/'Financials_hard coded'!M17 -> 0.73945428 | N13: =$J$13/'Financials_hard coded'!N17 -> 0.68926956 | O13: =$J$13/'Financials_hard coded'!O17 -> 0.65719267 | Q13: =$J$13/'Financials_hard coded'!Q17 -> 8.4421796 | R13: =$J$13/'Financials_hard coded'!R17 -> 7.2802963 | S13: =$J$13/'Financials_hard coded'!S17 -> 6.345987 | T13: =$J$13/'Financials_hard coded'!T17 -> 5.8202483 | V13: =$J$13/'Financials_hard coded'!V17 -> 12.393973 | W13: =$J$13/'Financials_hard coded'!W17 -> 10.428958 | X13: =$J$13/'Financials_hard coded'!X17 -> 8.6034593 | Y13: =$J$13/'Financials_hard coded'!Y17 -> 7.7198542 | AA13: =$H$13/'Financials_hard coded'!AA17 -> 17.730655 | AB13: =$H$13/'Financials_hard coded'!AB17 -> 14.40174 | AC13: =$H$13/'Financials_hard coded'!AC17 -> 11.863937 | AD13: =$H$13/'Financials_hard coded'!AD17 -> 10.665756
J20: Median | M20: =IFERROR(MEDIAN(M10:M17),"n/a") -> 1.295499 | N20: =IFERROR(MEDIAN(N10:N17),"n/a") -> 1.2583811 | O20: =IFERROR(MEDIAN(O10:O17),"n/a") -> 1.1299583 | R20: =IFERROR(MEDIAN(R10:R17),"n/a") -> 8.8350287 | S20: =IFERROR(MEDIAN(S10:S17),"n/a") -> 7.3458023 | T20: =IFERROR(MEDIAN(T10:T17),"n/a") -> 5.8202483 | W20: =IFERROR(MEDIAN(W10:W17),"n/a") -> 11.462276 | X20: =IFERROR(MEDIAN(X10:X17),"n/a") -> 10.529098 | Y20: =IFERROR(MEDIAN(Y10:Y17),"n/a") -> 7.8176849 | AB20: =IFERROR(MEDIAN(AB10:AB17),"n/a") -> 14.52255 | AC20: =IFERROR(MEDIAN(AC10:AC17),"n/a") -> 12.891748 | AD20: =IFERROR(MEDIAN(AD10:AD17),"n/a") -> 11.821951
J21: Average | M21: =IFERROR(AVERAGE(M10:M17),"n/a") -> 1.1371831 | N21: =IFERROR(AVERAGE(N10:N17),"n/a") -> 1.0744094 | O21: =IFERROR(AVERAGE(O10:O17),"n/a") -> 0.99982039 | R21: =IFERROR(AVERAGE(R10:R17),"n/a") -> 8.5790205 | S21: =IFERROR(AVERAGE(S10:S17),"n/a") -> 7.393776 | T21: =IFERROR(AVERAGE(T10:T17),"n/a") -> 6.5249117 | W21: =IFERROR(AVERAGE(W10:W17),"n/a") -> 12.296144 | X21: =IFERROR(AVERAGE(X10:X17),"n/a") -> 10.022154 | Y21: =IFERROR(AVERAGE(Y10:Y17),"n/a") -> 8.7217399 | AB21: =IFERROR(AVERAGE(AB10:AB17),"n/a") -> 14.52255 | AC21: =IFERROR(AVERAGE(AC10:AC17),"n/a") -> 12.891748 | AD21: =IFERROR(AVERAGE(AD10:AD17),"n/a") -> 11.821951
J24: Omega, EURm | M24: 45657 | N24: 46022 | Q24: EBITDA Multiple | R24: 45657 | S24: 46022 | V24: EBIT Multiple | W24: 45657 | X24: 46022
J25: EBITDA | M25: 22.9 | N25: 27.4 | Q25: Low | R25: =R26*0.95 -> 8.3932772 | S25: =S26*0.95 -> 6.9785122 | V25: Low | W25: =W26*0.95 -> 10.889162 | X25: =X26*0.95 -> 10.002643
J26: EBIT | M26: 15.2 | N26: 19.7 | Q26: Median | R26: =R20 -> 8.8350287 | S26: =S20 -> 7.3458023 | V26: Median | W26: =W20 -> 11.462276 | X26: =X20 -> 10.529098
Q27: High | R27: =R26*1.05 -> 9.2767801 | S27: =S26*1.05 -> 7.7130924 | V27: High | W27: =W26*1.05 -> 12.03539 | X27: =X26*1.05 -> 11.055553
R28: * Multiple range based on +/-5% of the relevant multiple
O30: Enterprise Value, EURm (EBITDA) | R30: 45657 | S30: 46022 | T30: Enterprise Value, EURm (EBIT) | W30: 45657 | X30: 46022
Q31: Low | R31: =$M$25*R25 -> 192.20605 | S31: =$N$25*S25 -> 191.21123 | V31: Low | W31: =$M$26*W25 -> 165.51527 | X31: =$N$26*X25 -> 197.05208
Q32: Median | R32: =$M$25*R26 -> 202.32216 | S32: =$N$25*S26 -> 201.27498 | V32: Median | W32: =$M$26*W26 -> 174.2266 | X32: =$N$26*X26 -> 207.42324
Q33: High | R33: =$M$25*R27 -> 212.43826 | S33: =$N$25*S27 -> 211.33873 | V33: High | W33: =$M$26*W27 -> 182.93793 | X33: =$N$26*X27 -> 217.7944
O35: Equity Value, EURm (EBITDA) | R35: 45657 | S35: 46022 | T35: Equity Value, EURm (EBIT) | W35: 45657 | X35: 46022
Q36: Low | R36: =R31-$S$50 -> 230.40605 | S36: =S31-$S$50 -> 229.41123 | V36: Low | W36: =W31-$S$50 -> 203.71527 | X36: =X31-$S$50 -> 235.25208
Q37: Median | R37: =R32-$S$50 -> 240.52216 | S37: =S32-$S$50 -> 239.47498 | V37: Median | W37: =W32-$S$50 -> 212.4266 | X37: =X32-$S$50 -> 245.62324
Q38: High | R38: =R33-$S$50 -> 250.63826 | S38: =S33-$S$50 -> 249.53873 | V38: High | W38: =W33-$S$50 -> 221.13793 | X38: =X33-$S$50 -> 255.9944
O42: Bridge Calculation
O43: Cash and cash equivalents | S43: 153.1
O44: Financial liabilities | S44: 0
O45: Current financial liabilities | S45: 1.1
O46: Net debt (net cash) | S46: =S44+S45-S43 -> -152
O47: Pension provisions | S47: 74.5
O48: Minority Interest | S48: 0
O49: Advance payments received | S49: 39.3
O50: Bridge | S50: =S46+S47+S48+S49 -> -38.2

Sheet Bilanzen >>>

Sheet BS Bobst
I11: Employer contribution | J11: 25.7
I22: Cash | J22: 252.4
I29: Non-controlling interest | J29: 1.7
I31: Borrowings | J31: 201.2
I33: Employee benefits | J33: 15.2
I37: Borrowings | J37: 185
I39: Employee benefits | J39: 2.6

Sheet BS CKD
J9: Cash | K9: 28568
J35: Retirement benefit asset | K35: 1749
J49: Short-term borrowings | K49: 6062
J50: Current porting of LT borrowings | K50: 2398
J51: Lease liabilities | K51: 329
J61: LT borrowings | K61: 9203
J62: Lease liabilities | K62: 633
J65: Retirement benefit liability | K65: 503
J66: Asset retirement obligation | K66: 235

Sheet BS GEA
K24: Cash | L24: 623.886
K39: Non-controlling interest | L39: =412/1000 -> 0.412
K43: Non-cur Employee benefit obligation | L43: 634.633
K44: Non-cur financial liabilities | L44: 205.267
K52: Cur employee benefit obligation | L52: 291.439
K53: Cur financial liabilities | L53: 135.747

Sheet BS Krones
L25: Cash | N25: 448.364
L43: Non-controlling interest | N43: =462/1000 -> 0.462
L46: Pensions | N46: 178.444
L50: Liabilities to bank | N50: 2.521
L52: Other financial liabilities and lease liabilities | N52: 129.45
L57: Liabilities to bank | N57: 1.244
L61: Other financial liabilities and lease liabilities | N61: 67.909
